{
"meta":{"test_sets":[],"test_metrics":[],"learn_metrics":[{"best_value":"Min","name":"RMSE"}],"launch_mode":"Train","parameters":"","iteration_count":1000,"learn_sets":["learn"],"name":"experiment"},
"iterations":[
{"learn":[211.4497092],"iteration":0,"passed_time":0.0253919254,"remaining_time":25.36653348},
{"learn":[201.0172568],"iteration":1,"passed_time":0.03320670524,"remaining_time":16.57014592},
{"learn":[191.1585386],"iteration":2,"passed_time":0.03932978055,"remaining_time":13.07059707},
{"learn":[181.9566412],"iteration":3,"passed_time":0.0450536731,"remaining_time":11.2183646},
{"learn":[173.6292948],"iteration":4,"passed_time":0.04920729278,"remaining_time":9.792251263},
{"learn":[165.6435795],"iteration":5,"passed_time":0.05378549944,"remaining_time":8.910464408},
{"learn":[158.4110789],"iteration":6,"passed_time":0.0574699586,"remaining_time":8.152524127},
{"learn":[151.7752825],"iteration":7,"passed_time":0.06073867857,"remaining_time":7.531596143},
{"learn":[145.6822911],"iteration":8,"passed_time":0.06421187561,"remaining_time":7.07044097},
{"learn":[139.9886872],"iteration":9,"passed_time":0.06972027592,"remaining_time":6.902307316},
{"learn":[134.8940433],"iteration":10,"passed_time":0.07385433744,"remaining_time":6.640176339},
{"learn":[130.221755],"iteration":11,"passed_time":0.07721417389,"remaining_time":6.357300317},
{"learn":[125.9542727],"iteration":12,"passed_time":0.08159754577,"remaining_time":6.195136744},
{"learn":[121.8532796],"iteration":13,"passed_time":0.08541898382,"remaining_time":6.015937003},
{"learn":[118.0535236],"iteration":14,"passed_time":0.08904265971,"remaining_time":5.847134654},
{"learn":[114.6107609],"iteration":15,"passed_time":0.09265015549,"remaining_time":5.697984562},
{"learn":[111.4028959],"iteration":16,"passed_time":0.0963978067,"remaining_time":5.574061411},
{"learn":[108.6435402],"iteration":17,"passed_time":0.1006450002,"remaining_time":5.490743902},
{"learn":[106.1903743],"iteration":18,"passed_time":0.1045787855,"remaining_time":5.399567822},
{"learn":[103.8441025],"iteration":19,"passed_time":0.1080325364,"remaining_time":5.293594285},
{"learn":[101.5913817],"iteration":20,"passed_time":0.1115518029,"remaining_time":5.200438811},
{"learn":[99.51917613],"iteration":21,"passed_time":0.1171482037,"remaining_time":5.207770144},
{"learn":[97.79039635],"iteration":22,"passed_time":0.1214521251,"remaining_time":5.159075055},
{"learn":[96.0710856],"iteration":23,"passed_time":0.1248151159,"remaining_time":5.075814714},
{"learn":[94.53481769],"iteration":24,"passed_time":0.1285878057,"remaining_time":5.014924421},
{"learn":[93.04849963],"iteration":25,"passed_time":0.1329567441,"remaining_time":4.980764182},
{"learn":[91.84211786],"iteration":26,"passed_time":0.1366659443,"remaining_time":4.925035698},
{"learn":[90.67536181],"iteration":27,"passed_time":0.1401872092,"remaining_time":4.866498833},
{"learn":[89.61930396],"iteration":28,"passed_time":0.1439304407,"remaining_time":4.819188203},
{"learn":[88.58927732],"iteration":29,"passed_time":0.1484908284,"remaining_time":4.801203452},
{"learn":[87.74352873],"iteration":30,"passed_time":0.1524542983,"remaining_time":4.765426291},
{"learn":[86.92887286],"iteration":31,"passed_time":0.1558552307,"remaining_time":4.71462073},
{"learn":[86.22558328],"iteration":32,"passed_time":0.1593055524,"remaining_time":4.66813543},
{"learn":[85.56979865],"iteration":33,"passed_time":0.1649647586,"remaining_time":4.686939907},
{"learn":[84.97719826],"iteration":34,"passed_time":0.1699884145,"remaining_time":4.686823427},
{"learn":[84.44313452],"iteration":35,"passed_time":0.1741434428,"remaining_time":4.663174412},
{"learn":[83.94778479],"iteration":36,"passed_time":0.1790636394,"remaining_time":4.660494183},
{"learn":[83.45669867],"iteration":37,"passed_time":0.183147797,"remaining_time":4.636531072},
{"learn":[83.02503851],"iteration":38,"passed_time":0.1867803874,"remaining_time":4.602460315},
{"learn":[82.64509183],"iteration":39,"passed_time":0.1903752794,"remaining_time":4.569006705},
{"learn":[82.26714446],"iteration":40,"passed_time":0.1948734746,"remaining_time":4.5581381},
{"learn":[81.97430957],"iteration":41,"passed_time":0.1993691908,"remaining_time":4.547516304},
{"learn":[81.65665185],"iteration":42,"passed_time":0.2031141087,"remaining_time":4.520469815},
{"learn":[81.32460968],"iteration":43,"passed_time":0.2068444197,"remaining_time":4.494165119},
{"learn":[81.06004198],"iteration":44,"passed_time":0.2124986551,"remaining_time":4.50969368},
{"learn":[80.85019504],"iteration":45,"passed_time":0.2164065037,"remaining_time":4.488082708},
{"learn":[80.61667769],"iteration":46,"passed_time":0.2200786002,"remaining_time":4.462444808},
{"learn":[80.414103],"iteration":47,"passed_time":0.2236662578,"remaining_time":4.436047446},
{"learn":[80.16994332],"iteration":48,"passed_time":0.2282374321,"remaining_time":4.429669346},
{"learn":[79.99959471],"iteration":49,"passed_time":0.2317937744,"remaining_time":4.404081713},
{"learn":[79.84332475],"iteration":50,"passed_time":0.235046761,"remaining_time":4.373713259},
{"learn":[79.64350199],"iteration":51,"passed_time":0.23843497,"remaining_time":4.346852914},
{"learn":[79.4471721],"iteration":52,"passed_time":0.2419157217,"remaining_time":4.322531858},
{"learn":[79.32139934],"iteration":53,"passed_time":0.2462096816,"remaining_time":4.313228867},
{"learn":[79.20870985],"iteration":54,"passed_time":0.2496072045,"remaining_time":4.288705605},
{"learn":[79.0653621],"iteration":55,"passed_time":0.2527943576,"remaining_time":4.261390599},
{"learn":[78.94344337],"iteration":56,"passed_time":0.2562399048,"remaining_time":4.239197021},
{"learn":[78.81488732],"iteration":57,"passed_time":0.2616696295,"remaining_time":4.249875707},
{"learn":[78.67461528],"iteration":58,"passed_time":0.2653995169,"remaining_time":4.232897379},
{"learn":[78.59433378],"iteration":59,"passed_time":0.2685232374,"remaining_time":4.206864053},
{"learn":[78.47363174],"iteration":60,"passed_time":0.2724186641,"remaining_time":4.193461076},
{"learn":[78.35707531],"iteration":61,"passed_time":0.2775740892,"remaining_time":4.19942735},
{"learn":[78.24443206],"iteration":62,"passed_time":0.2813417183,"remaining_time":4.184399843},
{"learn":[78.15666628],"iteration":63,"passed_time":0.2846052103,"remaining_time":4.162351201},
{"learn":[78.06551075],"iteration":64,"passed_time":0.2882735183,"remaining_time":4.146703687},
{"learn":[77.98818599],"iteration":65,"passed_time":0.2930297455,"remaining_time":4.146814883},
{"learn":[77.83382936],"iteration":66,"passed_time":0.2968717654,"remaining_time":4.134050106},
{"learn":[77.75153255],"iteration":67,"passed_time":0.3003885615,"remaining_time":4.117090285},
{"learn":[77.66556935],"iteration":68,"passed_time":0.3038883831,"remaining_time":4.100291083},
{"learn":[77.6006577],"iteration":69,"passed_time":0.3082998655,"remaining_time":4.095983927},
{"learn":[77.5344732],"iteration":70,"passed_time":0.31190521,"remaining_time":4.081125917},
{"learn":[77.41784228],"iteration":71,"passed_time":0.3152280933,"remaining_time":4.062939869},
{"learn":[77.2677492],"iteration":72,"passed_time":0.3186767343,"remaining_time":4.046757982},
{"learn":[77.20359432],"iteration":73,"passed_time":0.3232732424,"remaining_time":4.045284088},
{"learn":[77.08889399],"iteration":74,"passed_time":0.3274650909,"remaining_time":4.038736122},
{"learn":[76.96837558],"iteration":75,"passed_time":0.33129571,"remaining_time":4.027858369},
{"learn":[76.85399642],"iteration":76,"passed_time":0.3347997137,"remaining_time":4.013248517},
{"learn":[76.77935622],"iteration":77,"passed_time":0.3394954731,"remaining_time":4.013010593},
{"learn":[76.71298057],"iteration":78,"passed_time":0.3433924031,"remaining_time":4.003346877},
{"learn":[76.61691609],"iteration":79,"passed_time":0.3468727847,"remaining_time":3.989037024},
{"learn":[76.58102229],"iteration":80,"passed_time":0.3504978799,"remaining_time":3.97663644},
{"learn":[76.50907034],"iteration":81,"passed_time":0.3544727792,"remaining_time":3.968365992},
{"learn":[76.45257805],"iteration":82,"passed_time":0.3586892037,"remaining_time":3.962867467},
{"learn":[76.37575273],"iteration":83,"passed_time":0.362393908,"remaining_time":3.951819282},
{"learn":[76.34112773],"iteration":84,"passed_time":0.3661296211,"remaining_time":3.941277686},
{"learn":[76.28006928],"iteration":85,"passed_time":0.3699185447,"remaining_time":3.931459882},
{"learn":[76.20490211],"iteration":86,"passed_time":0.374396592,"remaining_time":3.929012512},
{"learn":[76.14854801],"iteration":87,"passed_time":0.3780079577,"remaining_time":3.917537016},
{"learn":[75.99494612],"iteration":88,"passed_time":0.381549419,"remaining_time":3.905522705},
{"learn":[75.8622871],"iteration":89,"passed_time":0.3856316214,"remaining_time":3.899164172},
{"learn":[75.81816529],"iteration":90,"passed_time":0.3898207582,"remaining_time":3.893923837},
{"learn":[75.74739794],"iteration":91,"passed_time":0.3936165245,"remaining_time":3.884823959},
{"learn":[75.69355132],"iteration":92,"passed_time":0.3970712907,"remaining_time":3.87251248},
{"learn":[75.60585703],"iteration":93,"passed_time":0.4010242871,"remaining_time":3.865191533},
{"learn":[75.53574361],"iteration":94,"passed_time":0.4056775699,"remaining_time":3.864612639},
{"learn":[75.46560481],"iteration":95,"passed_time":0.4094902589,"remaining_time":3.856033271},
{"learn":[75.40141423],"iteration":96,"passed_time":0.4129496653,"remaining_time":3.844263379},
{"learn":[75.34314902],"iteration":97,"passed_time":0.4169604655,"remaining_time":3.837738162},
{"learn":[75.27450004],"iteration":98,"passed_time":0.4213680309,"remaining_time":3.834874706},
{"learn":[75.20661209],"iteration":99,"passed_time":0.4252816838,"remaining_time":3.827535154},
{"learn":[75.1387231],"iteration":100,"passed_time":0.4287313616,"remaining_time":3.816133605},
{"learn":[75.10068717],"iteration":101,"passed_time":0.4321809903,"remaining_time":3.804887542},
{"learn":[75.03561811],"iteration":102,"passed_time":0.4369133558,"remaining_time":3.804963885},
{"learn":[74.9689901],"iteration":103,"passed_time":0.4407992259,"remaining_time":3.797654869},
{"learn":[74.88556145],"iteration":104,"passed_time":0.4443947938,"remaining_time":3.787936576},
{"learn":[74.78585899],"iteration":105,"passed_time":0.4479315229,"remaining_time":3.777837561},
{"learn":[74.71863471],"iteration":106,"passed_time":0.4524374099,"remaining_time":3.775949599},
{"learn":[74.6852233],"iteration":107,"passed_time":0.4571135922,"remaining_time":3.775419669},
{"learn":[74.61458466],"iteration":108,"passed_time":0.4604561186,"remaining_time":3.763911942},
{"learn":[74.56656861],"iteration":109,"passed_time":0.4640439947,"remaining_time":3.754537776},
{"learn":[74.49529402],"iteration":110,"passed_time":0.4689081466,"remaining_time":3.75548957},
{"learn":[74.41580039],"iteration":111,"passed_time":0.4730453534,"remaining_time":3.750573873},
{"learn":[74.34813556],"iteration":112,"passed_time":0.4764908523,"remaining_time":3.740242354},
{"learn":[74.22435754],"iteration":113,"passed_time":0.4801030372,"remaining_time":3.731327114},
{"learn":[74.14818113],"iteration":114,"passed_time":0.4847493202,"remaining_time":3.73046216},
{"learn":[74.09254863],"iteration":115,"passed_time":0.4888434519,"remaining_time":3.725324237},
{"learn":[73.96029432],"iteration":116,"passed_time":0.4925976085,"remaining_time":3.717638361},
{"learn":[73.91199368],"iteration":117,"passed_time":0.4962386748,"remaining_time":3.709173824},
{"learn":[73.81485666],"iteration":118,"passed_time":0.5008933765,"remaining_time":3.708294661},
{"learn":[73.74876864],"iteration":119,"passed_time":0.5046780391,"remaining_time":3.700972287},
{"learn":[73.67037131],"iteration":120,"passed_time":0.5082415327,"remaining_time":3.692101713},
{"learn":[73.61328653],"iteration":121,"passed_time":0.5116066107,"remaining_time":3.681890198},
{"learn":[73.52784096],"iteration":122,"passed_time":0.5160341312,"remaining_time":3.67936531},
{"learn":[73.49178829],"iteration":123,"passed_time":0.5199121855,"remaining_time":3.67292802},
{"learn":[73.43875496],"iteration":124,"passed_time":0.5235385911,"remaining_time":3.664770138},
{"learn":[73.36185981],"iteration":125,"passed_time":0.5272375366,"remaining_time":3.657187357},
{"learn":[73.31415696],"iteration":126,"passed_time":0.5320471915,"remaining_time":3.657300773},
{"learn":[73.24913229],"iteration":127,"passed_time":0.5359482216,"remaining_time":3.65114726},
{"learn":[73.16010075],"iteration":128,"passed_time":0.5393264838,"remaining_time":3.641498972},
{"learn":[73.13316974],"iteration":129,"passed_time":0.5427679621,"remaining_time":3.632370208},
{"learn":[73.06776118],"iteration":130,"passed_time":0.546485161,"remaining_time":3.62515729},
{"learn":[72.99078473],"iteration":131,"passed_time":0.5508645777,"remaining_time":3.62235192},
{"learn":[72.94067404],"iteration":132,"passed_time":0.5545924403,"remaining_time":3.615275532},
{"learn":[72.87642281],"iteration":133,"passed_time":0.558285322,"remaining_time":3.608023051},
{"learn":[72.77192114],"iteration":134,"passed_time":0.5623079251,"remaining_time":3.602935964},
{"learn":[72.68646084],"iteration":135,"passed_time":0.566758188,"remaining_time":3.600581429},
{"learn":[72.63757066],"iteration":136,"passed_time":0.5703379132,"remaining_time":3.592712548},
{"learn":[72.55663075],"iteration":137,"passed_time":0.5737152963,"remaining_time":3.583641923},
{"learn":[72.4703885],"iteration":138,"passed_time":0.5777849943,"remaining_time":3.578941583},
{"learn":[72.38541072],"iteration":139,"passed_time":0.5820902182,"remaining_time":3.575697055},
{"learn":[72.33045464],"iteration":140,"passed_time":0.585768286,"remaining_time":3.568616721},
{"learn":[72.28439491],"iteration":141,"passed_time":0.5892221025,"remaining_time":3.560229324},
{"learn":[72.24563816],"iteration":142,"passed_time":0.5930111176,"remaining_time":3.553919775},
{"learn":[72.1990498],"iteration":143,"passed_time":0.5974265111,"remaining_time":3.551368705},
{"learn":[72.15226474],"iteration":144,"passed_time":0.6011704121,"remaining_time":3.54483243},
{"learn":[72.10227493],"iteration":145,"passed_time":0.6046380509,"remaining_time":3.536718462},
{"learn":[72.01175875],"iteration":146,"passed_time":0.6084934071,"remaining_time":3.530917526},
{"learn":[71.9407562],"iteration":147,"passed_time":0.6129711531,"remaining_time":3.528725828},
{"learn":[71.89063964],"iteration":148,"passed_time":0.6166697953,"remaining_time":3.522053663},
{"learn":[71.84668691],"iteration":149,"passed_time":0.6200609072,"remaining_time":3.513678474},
{"learn":[71.752486],"iteration":150,"passed_time":0.6234447354,"remaining_time":3.505328347},
{"learn":[71.69351499],"iteration":151,"passed_time":0.6279772721,"remaining_time":3.50345215},
{"learn":[71.63502155],"iteration":152,"passed_time":0.6318124058,"remaining_time":3.497680443},
{"learn":[71.55418567],"iteration":153,"passed_time":0.6353242643,"remaining_time":3.490157972},
{"learn":[71.45926897],"iteration":154,"passed_time":0.6387622912,"remaining_time":3.482284749},
{"learn":[71.38482553],"iteration":155,"passed_time":0.6423989128,"remaining_time":3.475542836},
{"learn":[71.34817534],"iteration":156,"passed_time":0.6471203558,"remaining_time":3.47466535},
{"learn":[71.290462],"iteration":157,"passed_time":0.6509915355,"remaining_time":3.469208056},
{"learn":[71.23753088],"iteration":158,"passed_time":0.654451756,"remaining_time":3.461597024},
{"learn":[71.16120282],"iteration":159,"passed_time":0.6580575374,"remaining_time":3.454802071},
{"learn":[71.08413149],"iteration":160,"passed_time":0.6628076352,"remaining_time":3.454009975},
{"learn":[71.04197141],"iteration":161,"passed_time":0.6665576559,"remaining_time":3.447995776},
{"learn":[70.98329359],"iteration":162,"passed_time":0.6698303884,"remaining_time":3.439558498},
{"learn":[70.92248511],"iteration":163,"passed_time":0.6735713106,"remaining_time":3.433570827},
{"learn":[70.86389977],"iteration":164,"passed_time":0.6778324692,"remaining_time":3.430243102},
{"learn":[70.80510442],"iteration":165,"passed_time":0.6817290484,"remaining_time":3.425072448},
{"learn":[70.75068901],"iteration":166,"passed_time":0.6852221145,"remaining_time":3.41790432},
{"learn":[70.7109189],"iteration":167,"passed_time":0.688499146,"remaining_time":3.409710057},
{"learn":[70.64187472],"iteration":168,"passed_time":0.692936125,"remaining_time":3.407277632},
{"learn":[70.59050501],"iteration":169,"passed_time":0.6968506798,"remaining_time":3.402270966},
{"learn":[70.50552104],"iteration":170,"passed_time":0.7005216651,"remaining_time":3.396096259},
{"learn":[70.46048747],"iteration":171,"passed_time":0.703825428,"remaining_time":3.388182875},
{"learn":[70.40775915],"iteration":172,"passed_time":0.7080848365,"remaining_time":3.384891097},
{"learn":[70.2982977],"iteration":173,"passed_time":0.7120217117,"remaining_time":3.380057091},
{"learn":[70.25583799],"iteration":174,"passed_time":0.7155609687,"remaining_time":3.373358852},
{"learn":[70.17706314],"iteration":175,"passed_time":0.7189763317,"remaining_time":3.366116462},
{"learn":[70.13178394],"iteration":176,"passed_time":0.7227670046,"remaining_time":3.3606624},
{"learn":[70.08111731],"iteration":177,"passed_time":0.727236235,"remaining_time":3.358360591},
{"learn":[70.00407471],"iteration":178,"passed_time":0.7310323879,"remaining_time":3.352947433},
{"learn":[69.96278133],"iteration":179,"passed_time":0.7345027226,"remaining_time":3.346067958},
{"learn":[69.8782665],"iteration":180,"passed_time":0.7380988726,"remaining_time":3.339795451},
{"learn":[69.8099214],"iteration":181,"passed_time":0.742277073,"remaining_time":3.336168383},
{"learn":[69.76459997],"iteration":182,"passed_time":0.745885577,"remaining_time":3.329991893},
{"learn":[69.69199034],"iteration":183,"passed_time":0.7496289872,"remaining_time":3.324441595},
{"learn":[69.63235962],"iteration":184,"passed_time":0.7529977535,"remaining_time":3.317260374},
{"learn":[69.58609116],"iteration":185,"passed_time":0.7573840763,"remaining_time":3.314573323},
{"learn":[69.54136942],"iteration":186,"passed_time":0.7616807102,"remaining_time":3.311478168},
{"learn":[69.49093193],"iteration":187,"passed_time":0.7652617681,"remaining_time":3.305279552},
{"learn":[69.46237639],"iteration":188,"passed_time":0.7688805237,"remaining_time":3.299270395},
{"learn":[69.42345875],"iteration":189,"passed_time":0.7732496778,"remaining_time":3.296485469},
{"learn":[69.36409994],"iteration":190,"passed_time":0.7773829809,"remaining_time":3.292684982},
{"learn":[69.31703897],"iteration":191,"passed_time":0.7807275215,"remaining_time":3.285561653},
{"learn":[69.2873683],"iteration":192,"passed_time":0.784181266,"remaining_time":3.278934102},
{"learn":[69.22034202],"iteration":193,"passed_time":0.788585529,"remaining_time":3.276288332},
{"learn":[69.15947256],"iteration":194,"passed_time":0.7928180068,"remaining_time":3.272915361},
{"learn":[69.11091962],"iteration":195,"passed_time":0.7962541989,"remaining_time":3.266267224},
{"learn":[69.04831397],"iteration":196,"passed_time":0.7998097946,"remaining_time":3.260138401},
{"learn":[68.99293491],"iteration":197,"passed_time":0.8049232416,"remaining_time":3.260345656},
{"learn":[68.94006114],"iteration":198,"passed_time":0.8096013257,"remaining_time":3.258747045},
{"learn":[68.90064965],"iteration":199,"passed_time":0.813234911,"remaining_time":3.252939644},
{"learn":[68.87218659],"iteration":200,"passed_time":0.8170116909,"remaining_time":3.24772309},
{"learn":[68.7861352],"iteration":201,"passed_time":0.8218503638,"remaining_time":3.246715793},
{"learn":[68.75040194],"iteration":202,"passed_time":0.8256915035,"remaining_time":3.241754327},
{"learn":[68.71956097],"iteration":203,"passed_time":0.8290382563,"remaining_time":3.234874765},
{"learn":[68.64715552],"iteration":204,"passed_time":0.8324242933,"remaining_time":3.228182016},
{"learn":[68.58423552],"iteration":205,"passed_time":0.8372299219,"remaining_time":3.226993},
{"learn":[68.55183741],"iteration":206,"passed_time":0.841044929,"remaining_time":3.221974052},
{"learn":[68.52521912],"iteration":207,"passed_time":0.8445179915,"remaining_time":3.21566466},
{"learn":[68.50888282],"iteration":208,"passed_time":0.8478968138,"remaining_time":3.20902574},
{"learn":[68.41368332],"iteration":209,"passed_time":0.8527601148,"remaining_time":3.208002337},
{"learn":[68.37006478],"iteration":210,"passed_time":0.8568750781,"remaining_time":3.20414425},
{"learn":[68.28807028],"iteration":211,"passed_time":0.8606147912,"remaining_time":3.198888941},
{"learn":[68.23935483],"iteration":212,"passed_time":0.8641172666,"remaining_time":3.192771309},
{"learn":[68.21422003],"iteration":213,"passed_time":0.8685044553,"remaining_time":3.189927579},
{"learn":[68.16623274],"iteration":214,"passed_time":0.8726547091,"remaining_time":3.186204403},
{"learn":[68.08146774],"iteration":215,"passed_time":0.8760616129,"remaining_time":3.179779188},
{"learn":[68.04668106],"iteration":216,"passed_time":0.8794371836,"remaining_time":3.173268732},
{"learn":[67.98507059],"iteration":217,"passed_time":0.8835569195,"remaining_time":3.169456473},
{"learn":[67.95297613],"iteration":218,"passed_time":0.8878016698,"remaining_time":3.166087233},
{"learn":[67.88998293],"iteration":219,"passed_time":0.891355253,"remaining_time":3.160259533},
{"learn":[67.86086763],"iteration":220,"passed_time":0.8945917811,"remaining_time":3.15333483},
{"learn":[67.79584826],"iteration":221,"passed_time":0.8984146677,"remaining_time":3.14849825},
{"learn":[67.74980733],"iteration":222,"passed_time":0.9025737537,"remaining_time":3.144842182},
{"learn":[67.70746708],"iteration":223,"passed_time":0.9065881649,"remaining_time":3.140680428},
{"learn":[67.61559863],"iteration":224,"passed_time":0.910108465,"remaining_time":3.134818046},
{"learn":[67.56772675],"iteration":225,"passed_time":0.914081177,"remaining_time":3.130525801},
{"learn":[67.54999192],"iteration":226,"passed_time":0.9184007587,"remaining_time":3.127417562},
{"learn":[67.49491896],"iteration":227,"passed_time":0.9221687861,"remaining_time":3.122431153},
{"learn":[67.46364454],"iteration":228,"passed_time":0.9256050438,"remaining_time":3.116338379},
{"learn":[67.43850559],"iteration":229,"passed_time":0.9292189419,"remaining_time":3.110863414},
{"learn":[67.37939842],"iteration":230,"passed_time":0.9338910006,"remaining_time":3.108927184},
{"learn":[67.35295187],"iteration":231,"passed_time":0.9374698171,"remaining_time":3.10334836},
{"learn":[67.29267375],"iteration":232,"passed_time":0.9412234718,"remaining_time":3.098362244},
{"learn":[67.2456856],"iteration":233,"passed_time":0.9449944274,"remaining_time":3.093443297},
{"learn":[67.19588653],"iteration":234,"passed_time":0.9491764212,"remaining_time":3.08987218},
{"learn":[67.1222453],"iteration":235,"passed_time":0.9529716571,"remaining_time":3.085043839},
{"learn":[67.0610304],"iteration":236,"passed_time":0.9567892519,"remaining_time":3.080296199},
{"learn":[66.93815174],"iteration":237,"passed_time":0.9603315119,"remaining_time":3.074674841},
{"learn":[66.88267797],"iteration":238,"passed_time":0.9646022832,"remaining_time":3.071390533},
{"learn":[66.85141519],"iteration":239,"passed_time":0.9683403137,"remaining_time":3.066410993},
{"learn":[66.77495808],"iteration":240,"passed_time":0.9720251723,"remaining_time":3.061274298},
{"learn":[66.71883518],"iteration":241,"passed_time":0.9757336132,"remaining_time":3.056223466},
{"learn":[66.69151712],"iteration":242,"passed_time":0.9799669762,"remaining_time":3.052818934},
{"learn":[66.64590004],"iteration":243,"passed_time":0.9838477763,"remaining_time":3.048315241},
{"learn":[66.56180398],"iteration":244,"passed_time":0.9874220273,"remaining_time":3.042871962},
{"learn":[66.53500894],"iteration":245,"passed_time":0.9911308841,"remaining_time":3.03785645},
{"learn":[66.50815669],"iteration":246,"passed_time":0.9953857895,"remaining_time":3.034516192},
{"learn":[66.46538562],"iteration":247,"passed_time":0.9992526045,"remaining_time":3.029991769},
{"learn":[66.40671723],"iteration":248,"passed_time":1.003164517,"remaining_time":3.025608645},
{"learn":[66.36534376],"iteration":249,"passed_time":1.006806959,"remaining_time":3.020420877},
{"learn":[66.33955347],"iteration":250,"passed_time":1.01057006,"remaining_time":3.015605479},
{"learn":[66.28234224],"iteration":251,"passed_time":1.014737938,"remaining_time":3.011999912},
{"learn":[66.2202426],"iteration":252,"passed_time":1.018558751,"remaining_time":3.007365166},
{"learn":[66.1727169],"iteration":253,"passed_time":1.021979826,"remaining_time":3.001562795},
{"learn":[66.10061394],"iteration":254,"passed_time":1.02582425,"remaining_time":2.997015947},
{"learn":[66.07266433],"iteration":255,"passed_time":1.030257548,"remaining_time":2.994186},
{"learn":[65.98801031],"iteration":256,"passed_time":1.034194858,"remaining_time":2.989909647},
{"learn":[65.91995205],"iteration":257,"passed_time":1.037534275,"remaining_time":2.983916403},
{"learn":[65.86034383],"iteration":258,"passed_time":1.040866992,"remaining_time":2.977924482},
{"learn":[65.79965666],"iteration":259,"passed_time":1.045755488,"remaining_time":2.976381004},
{"learn":[65.7404553],"iteration":260,"passed_time":1.0496289,"remaining_time":2.971937765},
{"learn":[65.69893031],"iteration":261,"passed_time":1.053268038,"remaining_time":2.966838977},
{"learn":[65.63948457],"iteration":262,"passed_time":1.056574797,"remaining_time":2.960819867},
{"learn":[65.59889513],"iteration":263,"passed_time":1.061047402,"remaining_time":2.958071544},
{"learn":[65.5702276],"iteration":264,"passed_time":1.064988859,"remaining_time":2.953837024},
{"learn":[65.53586677],"iteration":265,"passed_time":1.068371308,"remaining_time":2.94806218},
{"learn":[65.48231792],"iteration":266,"passed_time":1.071834126,"remaining_time":2.942525897},
{"learn":[65.43704479],"iteration":267,"passed_time":1.076217494,"remaining_time":2.939519423},
{"learn":[65.37341618],"iteration":268,"passed_time":1.080562242,"remaining_time":2.936397764},
{"learn":[65.32782396],"iteration":269,"passed_time":1.084057317,"remaining_time":2.930969784},
{"learn":[65.25187621],"iteration":270,"passed_time":1.087657103,"remaining_time":2.925837742},
{"learn":[65.22653962],"iteration":271,"passed_time":1.091194067,"remaining_time":2.920548827},
{"learn":[65.18740981],"iteration":272,"passed_time":1.095670292,"remaining_time":2.917774002},
{"learn":[65.14848299],"iteration":273,"passed_time":1.099122205,"remaining_time":2.912272703},
{"learn":[65.10324859],"iteration":274,"passed_time":1.102552549,"remaining_time":2.906729448},
{"learn":[65.06645388],"iteration":275,"passed_time":1.105938438,"remaining_time":2.901084888},
{"learn":[65.02160715],"iteration":276,"passed_time":1.110463519,"remaining_time":2.89843005},
{"learn":[64.94321393],"iteration":277,"passed_time":1.114390737,"remaining_time":2.894209037},
{"learn":[64.90075813],"iteration":278,"passed_time":1.117841888,"remaining_time":2.88875986},
{"learn":[64.85889167],"iteration":279,"passed_time":1.121411033,"remaining_time":2.883628371},
{"learn":[64.817193],"iteration":280,"passed_time":1.125704199,"remaining_time":2.880360567},
{"learn":[64.76087485],"iteration":281,"passed_time":1.129602014,"remaining_time":2.876078886},
{"learn":[64.71650274],"iteration":282,"passed_time":1.133040223,"remaining_time":2.870635478},
{"learn":[64.69395736],"iteration":283,"passed_time":1.136532521,"remaining_time":2.865342552},
{"learn":[64.65645895],"iteration":284,"passed_time":1.140857642,"remaining_time":2.862151627},
{"learn":[64.61077076],"iteration":285,"passed_time":1.14497767,"remaining_time":2.858440757},
{"learn":[64.54173578],"iteration":286,"passed_time":1.148786323,"remaining_time":2.853953478},
{"learn":[64.48988603],"iteration":287,"passed_time":1.152768931,"remaining_time":2.849900968},
{"learn":[64.47327185],"iteration":288,"passed_time":1.157457114,"remaining_time":2.847584802},
{"learn":[64.42076347],"iteration":289,"passed_time":1.161343435,"remaining_time":2.843289099},
{"learn":[64.38956895],"iteration":290,"passed_time":1.165263447,"remaining_time":2.839078295},
{"learn":[64.34956231],"iteration":291,"passed_time":1.168777409,"remaining_time":2.83388495},
{"learn":[64.32599733],"iteration":292,"passed_time":1.173397429,"remaining_time":2.831371954},
{"learn":[64.26067602],"iteration":293,"passed_time":1.177001417,"remaining_time":2.826404764},
{"learn":[64.21284045],"iteration":294,"passed_time":1.180702918,"remaining_time":2.821679855},
{"learn":[64.15786631],"iteration":295,"passed_time":1.184456628,"remaining_time":2.817086033},
{"learn":[64.08859236],"iteration":296,"passed_time":1.189336049,"remaining_time":2.815162433},
{"learn":[64.02133003],"iteration":297,"passed_time":1.193198088,"remaining_time":2.810822341},
{"learn":[63.99978989],"iteration":298,"passed_time":1.196676279,"remaining_time":2.805585523},
{"learn":[63.96302522],"iteration":299,"passed_time":1.200432697,"remaining_time":2.801009625},
{"learn":[63.89559624],"iteration":300,"passed_time":1.204739072,"remaining_time":2.797716316},
{"learn":[63.87593625],"iteration":301,"passed_time":1.208243065,"remaining_time":2.792561785},
{"learn":[63.84668473],"iteration":302,"passed_time":1.211622567,"remaining_time":2.787131781},
{"learn":[63.82804786],"iteration":303,"passed_time":1.2151625,"remaining_time":2.782082567},
{"learn":[63.79243824],"iteration":304,"passed_time":1.218709314,"remaining_time":2.777058928},
{"learn":[63.77427314],"iteration":305,"passed_time":1.222267066,"remaining_time":2.772069751},
{"learn":[63.74655159],"iteration":306,"passed_time":1.225566741,"remaining_time":2.766507334},
{"learn":[63.70520328],"iteration":307,"passed_time":1.228714538,"remaining_time":2.760618379},
{"learn":[63.67292434],"iteration":308,"passed_time":1.232053933,"remaining_time":2.755175625},
{"learn":[63.61679622],"iteration":309,"passed_time":1.235956525,"remaining_time":2.751000008},
{"learn":[63.57254054],"iteration":310,"passed_time":1.240177819,"remaining_time":2.747532209},
{"learn":[63.51697801],"iteration":311,"passed_time":1.243862052,"remaining_time":2.742875293},
{"learn":[63.46111862],"iteration":312,"passed_time":1.247400486,"remaining_time":2.737904581},
{"learn":[63.42430049],"iteration":313,"passed_time":1.251117239,"remaining_time":2.733332568},
{"learn":[63.38172522],"iteration":314,"passed_time":1.255335728,"remaining_time":2.729857059},
{"learn":[63.31345617],"iteration":315,"passed_time":1.259273787,"remaining_time":2.725769842},
{"learn":[63.2895169],"iteration":316,"passed_time":1.262534768,"remaining_time":2.720224752},
{"learn":[63.25584542],"iteration":317,"passed_time":1.265820949,"remaining_time":2.714748074},
{"learn":[63.21822779],"iteration":318,"passed_time":1.269668323,"remaining_time":2.71048316},
{"learn":[63.17213917],"iteration":319,"passed_time":1.273965506,"remaining_time":2.707176701},
{"learn":[63.13621992],"iteration":320,"passed_time":1.277809918,"remaining_time":2.702906337},
{"learn":[63.10122966],"iteration":321,"passed_time":1.281049187,"remaining_time":2.697364437},
{"learn":[63.003558],"iteration":322,"passed_time":1.284626954,"remaining_time":2.692546279},
{"learn":[62.97766901],"iteration":323,"passed_time":1.288180217,"remaining_time":2.68768465},
{"learn":[62.95397856],"iteration":324,"passed_time":1.291936011,"remaining_time":2.683251715},
{"learn":[62.90561877],"iteration":325,"passed_time":1.296621144,"remaining_time":2.680744328},
{"learn":[62.85757751],"iteration":326,"passed_time":1.300505121,"remaining_time":2.676574761},
{"learn":[62.83214053],"iteration":327,"passed_time":1.304298476,"remaining_time":2.672221267},
{"learn":[62.79215531],"iteration":328,"passed_time":1.307985341,"remaining_time":2.667653994},
{"learn":[62.76229273],"iteration":329,"passed_time":1.311346292,"remaining_time":2.66243035},
{"learn":[62.71400531],"iteration":330,"passed_time":1.314975768,"remaining_time":2.657760691},
{"learn":[62.67689709],"iteration":331,"passed_time":1.319462099,"remaining_time":2.654821331},
{"learn":[62.62033172],"iteration":332,"passed_time":1.323514384,"remaining_time":2.651003286},
{"learn":[62.58951853],"iteration":333,"passed_time":1.326968144,"remaining_time":2.645990371},
{"learn":[62.54287794],"iteration":334,"passed_time":1.330542082,"remaining_time":2.641225327},
{"learn":[62.50893735],"iteration":335,"passed_time":1.33474687,"remaining_time":2.637714054},
{"learn":[62.48128843],"iteration":336,"passed_time":1.338753835,"remaining_time":2.633809473},
{"learn":[62.44802609],"iteration":337,"passed_time":1.342251009,"remaining_time":2.628905823},
{"learn":[62.42219289],"iteration":338,"passed_time":1.34565617,"remaining_time":2.623831058},
{"learn":[62.34660483],"iteration":339,"passed_time":1.350078013,"remaining_time":2.620739672},
{"learn":[62.3051449],"iteration":340,"passed_time":1.354789644,"remaining_time":2.618200514},
{"learn":[62.26949257],"iteration":341,"passed_time":1.358694719,"remaining_time":2.614096857},
{"learn":[62.23865284],"iteration":342,"passed_time":1.362628364,"remaining_time":2.610049082},
{"learn":[62.21533373],"iteration":343,"passed_time":1.367555538,"remaining_time":2.607896608},
{"learn":[62.19039134],"iteration":344,"passed_time":1.371452967,"remaining_time":2.603773024},
{"learn":[62.17716858],"iteration":345,"passed_time":1.374955821,"remaining_time":2.598904932},
{"learn":[62.13523395],"iteration":346,"passed_time":1.378739916,"remaining_time":2.594573964},
{"learn":[62.11263319],"iteration":347,"passed_time":1.383283049,"remaining_time":2.591668241},
{"learn":[62.06430678],"iteration":348,"passed_time":1.387191073,"remaining_time":2.587568448},
{"learn":[62.02317009],"iteration":349,"passed_time":1.390923999,"remaining_time":2.583144569},
{"learn":[62.00118245],"iteration":350,"passed_time":1.394454699,"remaining_time":2.578350711},
{"learn":[61.97011112],"iteration":351,"passed_time":1.398828314,"remaining_time":2.575115759},
{"learn":[61.92717272],"iteration":352,"passed_time":1.402548413,"remaining_time":2.570676553},
{"learn":[61.88645602],"iteration":353,"passed_time":1.406163168,"remaining_time":2.56604917},
{"learn":[61.85981954],"iteration":354,"passed_time":1.409593372,"remaining_time":2.561092182},
{"learn":[61.80727441],"iteration":355,"passed_time":1.414083969,"remaining_time":2.558062012},
{"learn":[61.76798803],"iteration":356,"passed_time":1.417954778,"remaining_time":2.553907345},
{"learn":[61.74918521],"iteration":357,"passed_time":1.421383265,"remaining_time":2.548961051},
{"learn":[61.70246087],"iteration":358,"passed_time":1.42505295,"remaining_time":2.544453875},
{"learn":[61.65372095],"iteration":359,"passed_time":1.429230024,"remaining_time":2.540853376},
{"learn":[61.6239538],"iteration":360,"passed_time":1.433605272,"remaining_time":2.537600468},
{"learn":[61.59721266],"iteration":361,"passed_time":1.437249505,"remaining_time":2.533052995},
{"learn":[61.56913541],"iteration":362,"passed_time":1.440730298,"remaining_time":2.528223691},
{"learn":[61.52160915],"iteration":363,"passed_time":1.445151725,"remaining_time":2.525045321},
{"learn":[61.47310233],"iteration":364,"passed_time":1.448949044,"remaining_time":2.520774365},
{"learn":[61.425656],"iteration":365,"passed_time":1.45243052,"remaining_time":2.515958879},
{"learn":[61.41150065],"iteration":366,"passed_time":1.455535466,"remaining_time":2.510501226},
{"learn":[61.38453918],"iteration":367,"passed_time":1.459212019,"remaining_time":2.506038032},
{"learn":[61.3519461],"iteration":368,"passed_time":1.463627486,"remaining_time":2.502842666},
{"learn":[61.30578402],"iteration":369,"passed_time":1.467385104,"remaining_time":2.498520582},
{"learn":[61.27884161],"iteration":370,"passed_time":1.470926539,"remaining_time":2.493835022},
{"learn":[61.23509137],"iteration":371,"passed_time":1.474503316,"remaining_time":2.489215275},
{"learn":[61.20631411],"iteration":372,"passed_time":1.478252312,"remaining_time":2.484890615},
{"learn":[61.16425429],"iteration":373,"passed_time":1.482537648,"remaining_time":2.481466759},
{"learn":[61.10694364],"iteration":374,"passed_time":1.486421664,"remaining_time":2.47736944},
{"learn":[61.08357809],"iteration":375,"passed_time":1.490000677,"remaining_time":2.472767081},
{"learn":[61.04056888],"iteration":376,"passed_time":1.493754455,"remaining_time":2.468458954},
{"learn":[60.99536258],"iteration":377,"passed_time":1.498054068,"remaining_time":2.465051933},
{"learn":[60.96799904],"iteration":378,"passed_time":1.501931157,"remaining_time":2.460947885},
{"learn":[60.92063126],"iteration":379,"passed_time":1.505483658,"remaining_time":2.456315442},
{"learn":[60.88956745],"iteration":380,"passed_time":1.508995088,"remaining_time":2.451621941},
{"learn":[60.86380377],"iteration":381,"passed_time":1.512706007,"remaining_time":2.447257362},
{"learn":[60.8482767],"iteration":382,"passed_time":1.516994291,"remaining_time":2.443826312},
{"learn":[60.80438935],"iteration":383,"passed_time":1.520627979,"remaining_time":2.439340716},
{"learn":[60.76270489],"iteration":384,"passed_time":1.524374616,"remaining_time":2.435039971},
{"learn":[60.73612531],"iteration":385,"passed_time":1.527951514,"remaining_time":2.430472098},
{"learn":[60.701289],"iteration":386,"passed_time":1.53151061,"remaining_time":2.425881147},
{"learn":[60.65753276],"iteration":387,"passed_time":1.535181517,"remaining_time":2.421471877},
{"learn":[60.6297532],"iteration":388,"passed_time":1.538905555,"remaining_time":2.417149857},
{"learn":[60.59147649],"iteration":389,"passed_time":1.54335859,"remaining_time":2.413971128},
{"learn":[60.56746714],"iteration":390,"passed_time":1.547374566,"remaining_time":2.410105143},
{"learn":[60.51943664],"iteration":391,"passed_time":1.5511402,"remaining_time":2.405850106},
{"learn":[60.4990924],"iteration":392,"passed_time":1.554598332,"remaining_time":2.401122615},
{"learn":[60.43558661],"iteration":393,"passed_time":1.55903865,"remaining_time":2.397912238},
{"learn":[60.42143968],"iteration":394,"passed_time":1.562587476,"remaining_time":2.393330184},
{"learn":[60.35942933],"iteration":395,"passed_time":1.566668729,"remaining_time":2.389565436},
{"learn":[60.32143429],"iteration":396,"passed_time":1.570447893,"remaining_time":2.38534025},
{"learn":[60.29636547],"iteration":397,"passed_time":1.573914178,"remaining_time":2.380644058},
{"learn":[60.27712098],"iteration":398,"passed_time":1.577225059,"remaining_time":2.375719952},
{"learn":[60.23167629],"iteration":399,"passed_time":1.580965388,"remaining_time":2.371448082},
{"learn":[60.20604252],"iteration":400,"passed_time":1.585153891,"remaining_time":2.36784833},
{"learn":[60.18698792],"iteration":401,"passed_time":1.588937966,"remaining_time":2.36364404},
{"learn":[60.13571087],"iteration":402,"passed_time":1.592588937,"remaining_time":2.359244653},
{"learn":[60.10055779],"iteration":403,"passed_time":1.596182079,"remaining_time":2.354763661},
{"learn":[60.06977595],"iteration":404,"passed_time":1.599776401,"remaining_time":2.350288786},
{"learn":[60.02708949],"iteration":405,"passed_time":1.603317699,"remaining_time":2.345740673},
{"learn":[59.9914993],"iteration":406,"passed_time":1.607650916,"remaining_time":2.342351334},
{"learn":[59.94771706],"iteration":407,"passed_time":1.611674166,"remaining_time":2.338507613},
{"learn":[59.9165028],"iteration":408,"passed_time":1.615409671,"remaining_time":2.334247227},
{"learn":[59.88620745],"iteration":409,"passed_time":1.618907626,"remaining_time":2.32964756},
{"learn":[59.84162899],"iteration":410,"passed_time":1.62335455,"remaining_time":2.326413211},
{"learn":[59.81603745],"iteration":411,"passed_time":1.627113986,"remaining_time":2.322191805},
{"learn":[59.77872011],"iteration":412,"passed_time":1.630720204,"remaining_time":2.317754866},
{"learn":[59.75877308],"iteration":413,"passed_time":1.634039722,"remaining_time":2.312916129},
{"learn":[59.74295857],"iteration":414,"passed_time":1.638165727,"remaining_time":2.309221567},
{"learn":[59.69842202],"iteration":415,"passed_time":1.641897114,"remaining_time":2.304970948},
{"learn":[59.6522258],"iteration":416,"passed_time":1.645451291,"remaining_time":2.300475067},
{"learn":[59.60927854],"iteration":417,"passed_time":1.649141923,"remaining_time":2.296173683},
{"learn":[59.56756023],"iteration":418,"passed_time":1.653606852,"remaining_time":2.292948881},
{"learn":[59.52760795],"iteration":419,"passed_time":1.657548198,"remaining_time":2.28899513},
{"learn":[59.494932],"iteration":420,"passed_time":1.661063946,"remaining_time":2.284456116},
{"learn":[59.46093499],"iteration":421,"passed_time":1.664544159,"remaining_time":2.279873279},
{"learn":[59.43233388],"iteration":422,"passed_time":1.668632683,"remaining_time":2.276125432},
{"learn":[59.40718857],"iteration":423,"passed_time":1.673549717,"remaining_time":2.273501502},
{"learn":[59.3738477],"iteration":424,"passed_time":1.677085462,"remaining_time":2.268997978},
{"learn":[59.3352074],"iteration":425,"passed_time":1.680661156,"remaining_time":2.264552825},
{"learn":[59.30910457],"iteration":426,"passed_time":1.684604194,"remaining_time":2.260604691},
{"learn":[59.26385403],"iteration":427,"passed_time":1.689236032,"remaining_time":2.257577127},
{"learn":[59.21780599],"iteration":428,"passed_time":1.693018437,"remaining_time":2.253411487},
{"learn":[59.19708126],"iteration":429,"passed_time":1.696474481,"remaining_time":2.24881501},
{"learn":[59.16107516],"iteration":430,"passed_time":1.70002848,"remaining_time":2.244353144},
{"learn":[59.13295878],"iteration":431,"passed_time":1.704104453,"remaining_time":2.240581781},
{"learn":[59.08344301],"iteration":432,"passed_time":1.70856017,"remaining_time":2.237306274},
{"learn":[59.05787661],"iteration":433,"passed_time":1.712159766,"remaining_time":2.232908819},
{"learn":[59.02688109],"iteration":434,"passed_time":1.715737695,"remaining_time":2.228486892},
{"learn":[58.98868644],"iteration":435,"passed_time":1.719648532,"remaining_time":2.224499477},
{"learn":[58.95527901],"iteration":436,"passed_time":1.723911549,"remaining_time":2.220966137},
{"learn":[58.92660627],"iteration":437,"passed_time":1.727840131,"remaining_time":2.217000351},
{"learn":[58.8967312],"iteration":438,"passed_time":1.731367276,"remaining_time":2.212521735},
{"learn":[58.87432899],"iteration":439,"passed_time":1.734854192,"remaining_time":2.207996245},
{"learn":[58.84095919],"iteration":440,"passed_time":1.738308271,"remaining_time":2.20343384},
{"learn":[58.80393546],"iteration":441,"passed_time":1.741601329,"remaining_time":2.19867317},
{"learn":[58.78725052],"iteration":442,"passed_time":1.745108192,"remaining_time":2.194187952},
{"learn":[58.73998785],"iteration":443,"passed_time":1.748936756,"remaining_time":2.190109992},
{"learn":[58.71274],"iteration":444,"passed_time":1.752532771,"remaining_time":2.185743118},
{"learn":[58.67230376],"iteration":445,"passed_time":1.756300824,"remaining_time":2.181593401},
{"learn":[58.61894413],"iteration":446,"passed_time":1.760806974,"remaining_time":2.178358516},
{"learn":[58.59741505],"iteration":447,"passed_time":1.765873688,"remaining_time":2.175808652},
{"learn":[58.56133918],"iteration":448,"passed_time":1.770236075,"remaining_time":2.172383246},
{"learn":[58.52366158],"iteration":449,"passed_time":1.774234564,"remaining_time":2.168508912},
{"learn":[58.47407239],"iteration":450,"passed_time":1.778484911,"remaining_time":2.164940612},
{"learn":[58.43571647],"iteration":451,"passed_time":1.783307307,"remaining_time":2.162062842},
{"learn":[58.40871005],"iteration":452,"passed_time":1.787546759,"remaining_time":2.158472576},
{"learn":[58.36046776],"iteration":453,"passed_time":1.791446503,"remaining_time":2.154470904},
{"learn":[58.30884382],"iteration":454,"passed_time":1.795246744,"remaining_time":2.150350495},
{"learn":[58.26842363],"iteration":455,"passed_time":1.799841097,"remaining_time":2.147178853},
{"learn":[58.24823908],"iteration":456,"passed_time":1.803642249,"remaining_time":2.143058514},
{"learn":[58.20825029],"iteration":457,"passed_time":1.80749706,"remaining_time":2.139003071},
{"learn":[58.18110188],"iteration":458,"passed_time":1.811108837,"remaining_time":2.13466205},
{"learn":[58.15160598],"iteration":459,"passed_time":1.815412766,"remaining_time":2.131136726},
{"learn":[58.11187522],"iteration":460,"passed_time":1.818991427,"remaining_time":2.126760042},
{"learn":[58.0816699],"iteration":461,"passed_time":1.822938614,"remaining_time":2.122815962},
{"learn":[58.03887738],"iteration":462,"passed_time":1.826620534,"remaining_time":2.118564205},
{"learn":[58.00228737],"iteration":463,"passed_time":1.83105406,"remaining_time":2.115183139},
{"learn":[57.96413274],"iteration":464,"passed_time":1.834597621,"remaining_time":2.110773607},
{"learn":[57.95045867],"iteration":465,"passed_time":1.838227414,"remaining_time":2.106466608},
{"learn":[57.92079636],"iteration":466,"passed_time":1.841940339,"remaining_time":2.102257389},
{"learn":[57.88455884],"iteration":467,"passed_time":1.846573296,"remaining_time":2.099096139},
{"learn":[57.85579419],"iteration":468,"passed_time":1.850360502,"remaining_time":2.094971059},
{"learn":[57.82087584],"iteration":469,"passed_time":1.854277138,"remaining_time":2.090993368},
{"learn":[57.79635149],"iteration":470,"passed_time":1.858110544,"remaining_time":2.086922458},
{"learn":[57.75275379],"iteration":471,"passed_time":1.862227197,"remaining_time":2.083169407},
{"learn":[57.73207582],"iteration":472,"passed_time":1.866135487,"remaining_time":2.079182667},
{"learn":[57.68988589],"iteration":473,"passed_time":1.869471847,"remaining_time":2.074561585},
{"learn":[57.66857999],"iteration":474,"passed_time":1.873116974,"remaining_time":2.070287182},
{"learn":[57.60984417],"iteration":475,"passed_time":1.876743753,"remaining_time":2.065995224},
{"learn":[57.57444513],"iteration":476,"passed_time":1.880968888,"remaining_time":2.062362114},
{"learn":[57.54633343],"iteration":477,"passed_time":1.884685516,"remaining_time":2.058171212},
{"learn":[57.51908536],"iteration":478,"passed_time":1.887860492,"remaining_time":2.053393145},
{"learn":[57.48421745],"iteration":479,"passed_time":1.891438844,"remaining_time":2.049058747},
{"learn":[57.46768184],"iteration":480,"passed_time":1.895627863,"remaining_time":2.045386405},
{"learn":[57.43433597],"iteration":481,"passed_time":1.899703607,"remaining_time":2.041590183},
{"learn":[57.41139137],"iteration":482,"passed_time":1.903215298,"remaining_time":2.037189046},
{"learn":[57.35275274],"iteration":483,"passed_time":1.906675022,"remaining_time":2.032736181},
{"learn":[57.33505767],"iteration":484,"passed_time":1.910346337,"remaining_time":2.02851209},
{"learn":[57.30600374],"iteration":485,"passed_time":1.915062453,"remaining_time":2.025395269},
{"learn":[57.26591914],"iteration":486,"passed_time":1.918694242,"remaining_time":2.021129663},
{"learn":[57.23875743],"iteration":487,"passed_time":1.921989501,"remaining_time":2.016513575},
{"learn":[57.20403403],"iteration":488,"passed_time":1.925626172,"remaining_time":2.01225966},
{"learn":[57.1710524],"iteration":489,"passed_time":1.929925075,"remaining_time":2.008697527},
{"learn":[57.14338171],"iteration":490,"passed_time":1.933288416,"remaining_time":2.004162533},
{"learn":[57.11744794],"iteration":491,"passed_time":1.936551927,"remaining_time":1.999529225},
{"learn":[57.07885264],"iteration":492,"passed_time":1.940021982,"remaining_time":1.995113884},
{"learn":[57.05325763],"iteration":493,"passed_time":1.945077281,"remaining_time":1.992326121},
{"learn":[57.03430902],"iteration":494,"passed_time":1.948946262,"remaining_time":1.988318914},
{"learn":[56.98665982],"iteration":495,"passed_time":1.952790827,"remaining_time":1.984287453},
{"learn":[56.9588708],"iteration":496,"passed_time":1.961278382,"remaining_time":1.984955787},
{"learn":[56.91523506],"iteration":497,"passed_time":1.965466834,"remaining_time":1.981253717},
{"learn":[56.87183272],"iteration":498,"passed_time":1.969379103,"remaining_time":1.977272406},
{"learn":[56.84948947],"iteration":499,"passed_time":1.973925872,"remaining_time":1.973925872},
{"learn":[56.83280263],"iteration":500,"passed_time":1.977904306,"remaining_time":1.97000848},
{"learn":[56.81066581],"iteration":501,"passed_time":1.981563713,"remaining_time":1.965774361},
{"learn":[56.76744001],"iteration":502,"passed_time":1.984980222,"remaining_time":1.961302526},
{"learn":[56.73505914],"iteration":503,"passed_time":1.988393578,"remaining_time":1.956831775},
{"learn":[56.69094328],"iteration":504,"passed_time":1.993128142,"remaining_time":1.953660258},
{"learn":[56.66908647],"iteration":505,"passed_time":1.996883696,"remaining_time":1.94952677},
{"learn":[56.628223],"iteration":506,"passed_time":2.000134161,"remaining_time":1.944903632},
{"learn":[56.60174968],"iteration":507,"passed_time":2.003631044,"remaining_time":1.940524554},
{"learn":[56.56135279],"iteration":508,"passed_time":2.008053168,"remaining_time":1.937041465},
{"learn":[56.53733546],"iteration":509,"passed_time":2.012076812,"remaining_time":1.933171839},
{"learn":[56.51073959],"iteration":510,"passed_time":2.015706033,"remaining_time":1.928924169},
{"learn":[56.48414761],"iteration":511,"passed_time":2.019059378,"remaining_time":1.92441597},
{"learn":[56.45478089],"iteration":512,"passed_time":2.023532888,"remaining_time":1.920975666},
{"learn":[56.44020391],"iteration":513,"passed_time":2.027486788,"remaining_time":1.917040037},
{"learn":[56.40830289],"iteration":514,"passed_time":2.031412798,"remaining_time":1.913078071},
{"learn":[56.37610562],"iteration":515,"passed_time":2.035064362,"remaining_time":1.90885882},
{"learn":[56.34927436],"iteration":516,"passed_time":2.039418147,"remaining_time":1.905297805},
{"learn":[56.2988042],"iteration":517,"passed_time":2.043169633,"remaining_time":1.901173288},
{"learn":[56.26265188],"iteration":518,"passed_time":2.046866088,"remaining_time":1.896999207},
{"learn":[56.22091834],"iteration":519,"passed_time":2.050299089,"remaining_time":1.892583774},
{"learn":[56.17821845],"iteration":520,"passed_time":2.054899891,"remaining_time":1.889245773},
{"learn":[56.15523109],"iteration":521,"passed_time":2.058850477,"remaining_time":1.885307525},
{"learn":[56.11313944],"iteration":522,"passed_time":2.062506353,"remaining_time":1.881100441},
{"learn":[56.09060654],"iteration":523,"passed_time":2.066211552,"remaining_time":1.876940265},
{"learn":[56.05269213],"iteration":524,"passed_time":2.070557319,"remaining_time":1.873361384},
{"learn":[56.01437582],"iteration":525,"passed_time":2.074278736,"remaining_time":1.86921696},
{"learn":[55.9770495],"iteration":526,"passed_time":2.07779291,"remaining_time":1.864888134},
{"learn":[55.95084089],"iteration":527,"passed_time":2.08184313,"remaining_time":1.861041586},
{"learn":[55.90957421],"iteration":528,"passed_time":2.085595039,"remaining_time":1.856928664},
{"learn":[55.86169249],"iteration":529,"passed_time":2.089965634,"remaining_time":1.853365751},
{"learn":[55.84831184],"iteration":530,"passed_time":2.093597628,"remaining_time":1.849147434},
{"learn":[55.80777304],"iteration":531,"passed_time":2.097051586,"remaining_time":1.844774704},
{"learn":[55.77896784],"iteration":532,"passed_time":2.100840296,"remaining_time":1.840698721},
{"learn":[55.74692791],"iteration":533,"passed_time":2.105370534,"remaining_time":1.837270915},
{"learn":[55.71532616],"iteration":534,"passed_time":2.109055815,"remaining_time":1.833104587},
{"learn":[55.6890565],"iteration":535,"passed_time":2.112580507,"remaining_time":1.828801036},
{"learn":[55.66028243],"iteration":536,"passed_time":2.116331672,"remaining_time":1.82469565},
{"learn":[55.63046645],"iteration":537,"passed_time":2.120700527,"remaining_time":1.821122013},
{"learn":[55.5885979],"iteration":538,"passed_time":2.124705182,"remaining_time":1.817233931},
{"learn":[55.56172945],"iteration":539,"passed_time":2.128421495,"remaining_time":1.813099792},
{"learn":[55.54355126],"iteration":540,"passed_time":2.131732547,"remaining_time":1.808623362},
{"learn":[55.50976849],"iteration":541,"passed_time":2.135645497,"remaining_time":1.804659848},
{"learn":[55.48784417],"iteration":542,"passed_time":2.139813021,"remaining_time":1.800910774},
{"learn":[55.45334759],"iteration":543,"passed_time":2.143563551,"remaining_time":1.796810624},
{"learn":[55.43158868],"iteration":544,"passed_time":2.147112541,"remaining_time":1.792543498},
{"learn":[55.41737483],"iteration":545,"passed_time":2.150850761,"remaining_time":1.788436347},
{"learn":[55.37364578],"iteration":546,"passed_time":2.155278165,"remaining_time":1.784901295},
{"learn":[55.34592951],"iteration":547,"passed_time":2.159595534,"remaining_time":1.781272229},
{"learn":[55.32396095],"iteration":548,"passed_time":2.163464482,"remaining_time":1.77727228},
{"learn":[55.31046048],"iteration":549,"passed_time":2.167291819,"remaining_time":1.773238761},
{"learn":[55.28574299],"iteration":550,"passed_time":2.171325049,"remaining_time":1.76937377},
{"learn":[55.25119009],"iteration":551,"passed_time":2.175170476,"remaining_time":1.765355749},
{"learn":[55.23002751],"iteration":552,"passed_time":2.17908561,"remaining_time":1.761394698},
{"learn":[55.19539038],"iteration":553,"passed_time":2.183840797,"remaining_time":1.7581101},
{"learn":[55.15904729],"iteration":554,"passed_time":2.188252511,"remaining_time":1.754544806},
{"learn":[55.13217619],"iteration":555,"passed_time":2.192111125,"remaining_time":1.750534783},
{"learn":[55.11077161],"iteration":556,"passed_time":2.196167111,"remaining_time":1.74668228},
{"learn":[55.1011027],"iteration":557,"passed_time":2.200724881,"remaining_time":1.743226519},
{"learn":[55.08429926],"iteration":558,"passed_time":2.20487981,"remaining_time":1.739449009},
{"learn":[55.0618314],"iteration":559,"passed_time":2.208658747,"remaining_time":1.73537473},
{"learn":[55.03746954],"iteration":560,"passed_time":2.212309034,"remaining_time":1.731200831},
{"learn":[55.00563377],"iteration":561,"passed_time":2.216620575,"remaining_time":1.727544149},
{"learn":[54.96075833],"iteration":562,"passed_time":2.220949408,"remaining_time":1.723898563},
{"learn":[54.94512644],"iteration":563,"passed_time":2.224285854,"remaining_time":1.719483391},
{"learn":[54.91795162],"iteration":564,"passed_time":2.227685213,"remaining_time":1.715120474},
{"learn":[54.88512521],"iteration":565,"passed_time":2.232140006,"remaining_time":1.711570252},
{"learn":[54.85807955],"iteration":566,"passed_time":2.236200203,"remaining_time":1.707715499},
{"learn":[54.8059248],"iteration":567,"passed_time":2.239815449,"remaining_time":1.703521609},
{"learn":[54.78779948],"iteration":568,"passed_time":2.243503384,"remaining_time":1.699384813},
{"learn":[54.75324979],"iteration":569,"passed_time":2.247634534,"remaining_time":1.695583947},
{"learn":[54.71959609],"iteration":570,"passed_time":2.252154932,"remaining_time":1.692074371},
{"learn":[54.68148271],"iteration":571,"passed_time":2.25634124,"remaining_time":1.688311278},
{"learn":[54.65656113],"iteration":572,"passed_time":2.259887565,"remaining_time":1.684069791},
{"learn":[54.63271348],"iteration":573,"passed_time":2.263298697,"remaining_time":1.679730392},
{"learn":[54.61095648],"iteration":574,"passed_time":2.2665249,"remaining_time":1.675257535},
{"learn":[54.59431595],"iteration":575,"passed_time":2.269895043,"remaining_time":1.670894963},
{"learn":[54.56520259],"iteration":576,"passed_time":2.273519603,"remaining_time":1.666722343},
{"learn":[54.51441731],"iteration":577,"passed_time":2.277312448,"remaining_time":1.662674486},
{"learn":[54.49462745],"iteration":578,"passed_time":2.281554629,"remaining_time":1.65895423},
{"learn":[54.46682059],"iteration":579,"passed_time":2.285045838,"remaining_time":1.654688365},
{"learn":[54.45009586],"iteration":580,"passed_time":2.288624831,"remaining_time":1.650488475},
{"learn":[54.42722764],"iteration":581,"passed_time":2.292414665,"remaining_time":1.646442148},
{"learn":[54.40535616],"iteration":582,"passed_time":2.296781261,"remaining_time":1.642809238},
{"learn":[54.38150371],"iteration":583,"passed_time":2.300376199,"remaining_time":1.638624142},
{"learn":[54.34773854],"iteration":584,"passed_time":2.303792204,"remaining_time":1.634314128},
{"learn":[54.31827137],"iteration":585,"passed_time":2.3074932,"remaining_time":1.630208506},
{"learn":[54.30488177],"iteration":586,"passed_time":2.311876822,"remaining_time":1.626584544},
{"learn":[54.28100738],"iteration":587,"passed_time":2.315552121,"remaining_time":1.62246169},
{"learn":[54.24176979],"iteration":588,"passed_time":2.318932553,"remaining_time":1.618134599},
{"learn":[54.21198077],"iteration":589,"passed_time":2.32254213,"remaining_time":1.613969955},
{"learn":[54.18932408],"iteration":590,"passed_time":2.327582828,"remaining_time":1.610797592},
{"learn":[54.15973458],"iteration":591,"passed_time":2.331894313,"remaining_time":1.607116351},
{"learn":[54.13574222],"iteration":592,"passed_time":2.33540272,"remaining_time":1.602881799},
{"learn":[54.09998081],"iteration":593,"passed_time":2.338869902,"remaining_time":1.598621515},
{"learn":[54.07246634],"iteration":594,"passed_time":2.343800954,"remaining_time":1.595360313},
{"learn":[54.0274839],"iteration":595,"passed_time":2.347571593,"remaining_time":1.591306919},
{"learn":[53.98673379],"iteration":596,"passed_time":2.350912758,"remaining_time":1.586964559},
{"learn":[53.97849715],"iteration":597,"passed_time":2.354053725,"remaining_time":1.582490965},
{"learn":[53.95293251],"iteration":598,"passed_time":2.358732801,"remaining_time":1.579051508},
{"learn":[53.93603923],"iteration":599,"passed_time":2.362495511,"remaining_time":1.574997008},
{"learn":[53.91691566],"iteration":600,"passed_time":2.365921033,"remaining_time":1.570719621},
{"learn":[53.87358737],"iteration":601,"passed_time":2.369537537,"remaining_time":1.566571328},
{"learn":[53.85420372],"iteration":602,"passed_time":2.37323896,"remaining_time":1.562480708},
{"learn":[53.83610793],"iteration":603,"passed_time":2.37795063,"remaining_time":1.559053725},
{"learn":[53.7970395],"iteration":604,"passed_time":2.381751277,"remaining_time":1.555027693},
{"learn":[53.74865248],"iteration":605,"passed_time":2.385147561,"remaining_time":1.550739503},
{"learn":[53.73391649],"iteration":606,"passed_time":2.388930482,"remaining_time":1.546704579},
{"learn":[53.70777705],"iteration":607,"passed_time":2.393580112,"remaining_time":1.543229283},
{"learn":[53.66894954],"iteration":608,"passed_time":2.397356558,"remaining_time":1.539189515},
{"learn":[53.65581639],"iteration":609,"passed_time":2.400627395,"remaining_time":1.534827351},
{"learn":[53.62853271],"iteration":610,"passed_time":2.404065833,"remaining_time":1.530575465},
{"learn":[53.60203376],"iteration":611,"passed_time":2.408387141,"remaining_time":1.526885965},
{"learn":[53.57541277],"iteration":612,"passed_time":2.41215295,"remaining_time":1.522843706},
{"learn":[53.55499544],"iteration":613,"passed_time":2.415782471,"remaining_time":1.518716668},
{"learn":[53.51520384],"iteration":614,"passed_time":2.419086232,"remaining_time":1.514387316},
{"learn":[53.5037454],"iteration":615,"passed_time":2.422364893,"remaining_time":1.510045647},
{"learn":[53.47173929],"iteration":616,"passed_time":2.425861293,"remaining_time":1.505842585},
{"learn":[53.44609038],"iteration":617,"passed_time":2.43060704,"remaining_time":1.50241406},
{"learn":[53.41808623],"iteration":618,"passed_time":2.435847189,"remaining_time":1.499285588},
{"learn":[53.38975122],"iteration":619,"passed_time":2.439557765,"remaining_time":1.495212824},
{"learn":[53.35262076],"iteration":620,"passed_time":2.443104488,"remaining_time":1.491041226},
{"learn":[53.33925495],"iteration":621,"passed_time":2.447198441,"remaining_time":1.487204197},
{"learn":[53.31830342],"iteration":622,"passed_time":2.450651437,"remaining_time":1.482978478},
{"learn":[53.28806857],"iteration":623,"passed_time":2.455113214,"remaining_time":1.479363091},
{"learn":[53.26454818],"iteration":624,"passed_time":2.458924783,"remaining_time":1.47535487},
{"learn":[53.23478818],"iteration":625,"passed_time":2.463661651,"remaining_time":1.471900092},
{"learn":[53.2146735],"iteration":626,"passed_time":2.467043828,"remaining_time":1.467635324},
{"learn":[53.20075662],"iteration":627,"passed_time":2.471376232,"remaining_time":1.463936239},
{"learn":[53.18378739],"iteration":628,"passed_time":2.475003034,"remaining_time":1.459818959},
{"learn":[53.15600876],"iteration":629,"passed_time":2.478707086,"remaining_time":1.455748606},
{"learn":[53.113907],"iteration":630,"passed_time":2.482271583,"remaining_time":1.451597804},
{"learn":[53.08749714],"iteration":631,"passed_time":2.486582163,"remaining_time":1.447883285},
{"learn":[53.06169904],"iteration":632,"passed_time":2.490630297,"remaining_time":1.444014722},
{"learn":[53.04287035],"iteration":633,"passed_time":2.494397951,"remaining_time":1.439983675},
{"learn":[53.02721224],"iteration":634,"passed_time":2.498112071,"remaining_time":1.435922687},
{"learn":[53.00404266],"iteration":635,"passed_time":2.501871759,"remaining_time":1.431888868},
{"learn":[52.97233264],"iteration":636,"passed_time":2.506029549,"remaining_time":1.428082773},
{"learn":[52.95795858],"iteration":637,"passed_time":2.509472027,"remaining_time":1.423869708},
{"learn":[52.92565006],"iteration":638,"passed_time":2.51323183,"remaining_time":1.419838326},
{"learn":[52.90430084],"iteration":639,"passed_time":2.516787955,"remaining_time":1.415693225},
{"learn":[52.88494464],"iteration":640,"passed_time":2.521072051,"remaining_time":1.41195767},
{"learn":[52.86585359],"iteration":641,"passed_time":2.524796137,"remaining_time":1.407908127},
{"learn":[52.83646765],"iteration":642,"passed_time":2.528309262,"remaining_time":1.403742467},
{"learn":[52.8166097],"iteration":643,"passed_time":2.53211614,"remaining_time":1.39974122},
{"learn":[52.79447768],"iteration":644,"passed_time":2.536243813,"remaining_time":1.395917137},
{"learn":[52.75754948],"iteration":645,"passed_time":2.540485907,"remaining_time":1.392154816},
{"learn":[52.72780155],"iteration":646,"passed_time":2.543930671,"remaining_time":1.387955992},
{"learn":[52.69242372],"iteration":647,"passed_time":2.547385267,"remaining_time":1.383764836},
{"learn":[52.6514161],"iteration":648,"passed_time":2.551961708,"remaining_time":1.38018268},
{"learn":[52.62850899],"iteration":649,"passed_time":2.556190346,"remaining_time":1.376410186},
{"learn":[52.59677587],"iteration":650,"passed_time":2.559886852,"remaining_time":1.372351016},
{"learn":[52.56308344],"iteration":651,"passed_time":2.563374147,"remaining_time":1.368181293},
{"learn":[52.54403061],"iteration":652,"passed_time":2.567504589,"remaining_time":1.364355425},
{"learn":[52.51804006],"iteration":653,"passed_time":2.571912609,"remaining_time":1.360675478},
{"learn":[52.49629913],"iteration":654,"passed_time":2.57556318,"remaining_time":1.356594347},
{"learn":[52.47639211],"iteration":655,"passed_time":2.57897165,"remaining_time":1.352387573},
{"learn":[52.45096083],"iteration":656,"passed_time":2.582659503,"remaining_time":1.348329086},
{"learn":[52.44108172],"iteration":657,"passed_time":2.58683059,"remaining_time":1.34452289},
{"learn":[52.41877208],"iteration":658,"passed_time":2.590769677,"remaining_time":1.340595538},
{"learn":[52.38129198],"iteration":659,"passed_time":2.59414083,"remaining_time":1.336375579},
{"learn":[52.36358691],"iteration":660,"passed_time":2.59755964,"remaining_time":1.332182629},
{"learn":[52.32967589],"iteration":661,"passed_time":2.601306565,"remaining_time":1.328159545},
{"learn":[52.29303182],"iteration":662,"passed_time":2.604742277,"remaining_time":1.323979106},
{"learn":[52.27679325],"iteration":663,"passed_time":2.608098953,"remaining_time":1.319760916},
{"learn":[52.26187648],"iteration":664,"passed_time":2.611557666,"remaining_time":1.315596719},
{"learn":[52.23848429],"iteration":665,"passed_time":2.616067994,"remaining_time":1.311962027},
{"learn":[52.20597659],"iteration":666,"passed_time":2.620139955,"remaining_time":1.308105855},
{"learn":[52.19005281],"iteration":667,"passed_time":2.623553266,"remaining_time":1.303921683},
{"learn":[52.17432726],"iteration":668,"passed_time":2.626990158,"remaining_time":1.299751483},
{"learn":[52.15219921],"iteration":669,"passed_time":2.631343019,"remaining_time":1.296034621},
{"learn":[52.13311842],"iteration":670,"passed_time":2.63544335,"remaining_time":1.292192045},
{"learn":[52.10922945],"iteration":671,"passed_time":2.638683594,"remaining_time":1.287928897},
{"learn":[52.06996983],"iteration":672,"passed_time":2.642135072,"remaining_time":1.283771424},
{"learn":[52.0369631],"iteration":673,"passed_time":2.64669278,"remaining_time":1.280151107},
{"learn":[52.01689749],"iteration":674,"passed_time":2.650741008,"remaining_time":1.276282708},
{"learn":[51.98242855],"iteration":675,"passed_time":2.654463063,"remaining_time":1.272257444},
{"learn":[51.95486329],"iteration":676,"passed_time":2.658110144,"remaining_time":1.268197306},
{"learn":[51.93234349],"iteration":677,"passed_time":2.662646932,"remaining_time":1.264560932},
{"learn":[51.89010272],"iteration":678,"passed_time":2.666726232,"remaining_time":1.260705627},
{"learn":[51.87149062],"iteration":679,"passed_time":2.670376281,"remaining_time":1.256647662},
{"learn":[51.85630188],"iteration":680,"passed_time":2.673678898,"remaining_time":1.252428147},
{"learn":[51.84984474],"iteration":681,"passed_time":2.677252793,"remaining_time":1.248337812},
{"learn":[51.83902067],"iteration":682,"passed_time":2.68158362,"remaining_time":1.244600304},
{"learn":[51.82158827],"iteration":683,"passed_time":2.68542524,"remaining_time":1.240635052},
{"learn":[51.8026552],"iteration":684,"passed_time":2.689180651,"remaining_time":1.236630518},
{"learn":[51.76933896],"iteration":685,"passed_time":2.693529577,"remaining_time":1.232898378},
{"learn":[51.75229797],"iteration":686,"passed_time":2.698183209,"remaining_time":1.229303267},
{"learn":[51.71415289],"iteration":687,"passed_time":2.702199833,"remaining_time":1.225416203},
{"learn":[51.67125767],"iteration":688,"passed_time":2.706315041,"remaining_time":1.221573262},
{"learn":[51.63149598],"iteration":689,"passed_time":2.710445551,"remaining_time":1.217736407},
{"learn":[51.60126991],"iteration":690,"passed_time":2.714294702,"remaining_time":1.213772884},
{"learn":[51.56404694],"iteration":691,"passed_time":2.718121219,"remaining_time":1.209799618},
{"learn":[51.55215614],"iteration":692,"passed_time":2.723029441,"remaining_time":1.206305972},
{"learn":[51.51385013],"iteration":693,"passed_time":2.727477504,"remaining_time":1.202605355},
{"learn":[51.48764212],"iteration":694,"passed_time":2.73187369,"remaining_time":1.198879821},
{"learn":[51.45825926],"iteration":695,"passed_time":2.737079958,"remaining_time":1.195506189},
{"learn":[51.43962848],"iteration":696,"passed_time":2.741862236,"remaining_time":1.191942981},
{"learn":[51.39870347],"iteration":697,"passed_time":2.746878621,"remaining_time":1.188477569},
{"learn":[51.37650223],"iteration":698,"passed_time":2.752017089,"remaining_time":1.185060291},
{"learn":[51.33953875],"iteration":699,"passed_time":2.757499018,"remaining_time":1.181785294},
{"learn":[51.31396761],"iteration":700,"passed_time":2.762005368,"remaining_time":1.178087882},
{"learn":[51.29472908],"iteration":701,"passed_time":2.766215421,"remaining_time":1.174262387},
{"learn":[51.2635047],"iteration":702,"passed_time":2.770088207,"remaining_time":1.170293311},
{"learn":[51.22221606],"iteration":703,"passed_time":2.775036369,"remaining_time":1.166776655},
{"learn":[51.18034238],"iteration":704,"passed_time":2.77887933,"remaining_time":1.162793478},
{"learn":[51.14162036],"iteration":705,"passed_time":2.782866147,"remaining_time":1.158870605},
{"learn":[51.11103756],"iteration":706,"passed_time":2.786996922,"remaining_time":1.155007211},
{"learn":[51.08281828],"iteration":707,"passed_time":2.792198665,"remaining_time":1.15158476},
{"learn":[51.05395346],"iteration":708,"passed_time":2.796769952,"remaining_time":1.147898527},
{"learn":[51.0290978],"iteration":709,"passed_time":2.800481159,"remaining_time":1.143858502},
{"learn":[51.00922525],"iteration":710,"passed_time":2.805911931,"remaining_time":1.140518352},
{"learn":[50.96835809],"iteration":711,"passed_time":2.811105298,"remaining_time":1.1370763},
{"learn":[50.9417093],"iteration":712,"passed_time":2.814903675,"remaining_time":1.133067819},
{"learn":[50.9167081],"iteration":713,"passed_time":2.818617366,"remaining_time":1.129026004},
{"learn":[50.89156758],"iteration":714,"passed_time":2.823555457,"remaining_time":1.125473154},
{"learn":[50.87617323],"iteration":715,"passed_time":2.827925569,"remaining_time":1.121691147},
{"learn":[50.8458433],"iteration":716,"passed_time":2.83171544,"remaining_time":1.117678479},
{"learn":[50.80654785],"iteration":717,"passed_time":2.835402891,"remaining_time":1.113626205},
{"learn":[50.77343371],"iteration":718,"passed_time":2.840819295,"remaining_time":1.110250656},
{"learn":[50.75442568],"iteration":719,"passed_time":2.845439155,"remaining_time":1.106559671},
{"learn":[50.73015937],"iteration":720,"passed_time":2.849712255,"remaining_time":1.102731927},
{"learn":[50.69705086],"iteration":721,"passed_time":2.856725411,"remaining_time":1.099957984},
{"learn":[50.67576695],"iteration":722,"passed_time":2.863363347,"remaining_time":1.097028558},
{"learn":[50.64537462],"iteration":723,"passed_time":2.869328362,"remaining_time":1.093832359},
{"learn":[50.61923375],"iteration":724,"passed_time":2.873795049,"remaining_time":1.090060191},
{"learn":[50.59310432],"iteration":725,"passed_time":2.878909011,"remaining_time":1.086530398},
{"learn":[50.57902726],"iteration":726,"passed_time":2.883163431,"remaining_time":1.082673476},
{"learn":[50.56078922],"iteration":727,"passed_time":2.888376734,"remaining_time":1.079173725},
{"learn":[50.52192881],"iteration":728,"passed_time":2.893381922,"remaining_time":1.075591908},
{"learn":[50.50833016],"iteration":729,"passed_time":2.897276394,"remaining_time":1.071595379},
{"learn":[50.48863089],"iteration":730,"passed_time":2.901277219,"remaining_time":1.067638265},
{"learn":[50.46217294],"iteration":731,"passed_time":2.905215407,"remaining_time":1.0636581},
{"learn":[50.44358105],"iteration":732,"passed_time":2.909787279,"remaining_time":1.059908873},
{"learn":[50.42153532],"iteration":733,"passed_time":2.913726337,"remaining_time":1.055928073},
{"learn":[50.40817374],"iteration":734,"passed_time":2.917607484,"remaining_time":1.051926508},
{"learn":[50.38296432],"iteration":735,"passed_time":2.922231011,"remaining_time":1.048191558},
{"learn":[50.36337257],"iteration":736,"passed_time":2.926552402,"remaining_time":1.04434638},
{"learn":[50.32410025],"iteration":737,"passed_time":2.931615422,"remaining_time":1.040763198},
{"learn":[50.29084715],"iteration":738,"passed_time":2.936524139,"remaining_time":1.037121516},
{"learn":[50.2657138],"iteration":739,"passed_time":2.940335287,"remaining_time":1.033090777},
{"learn":[50.25599709],"iteration":740,"passed_time":2.944346328,"remaining_time":1.029130498},
{"learn":[50.21203262],"iteration":741,"passed_time":2.948968568,"remaining_time":1.025382602},
{"learn":[50.17098155],"iteration":742,"passed_time":2.953252479,"remaining_time":1.021515326},
{"learn":[50.1571437],"iteration":743,"passed_time":2.956859499,"remaining_time":1.017414021},
{"learn":[50.13476794],"iteration":744,"passed_time":2.960517827,"remaining_time":1.013331605},
{"learn":[50.10984231],"iteration":745,"passed_time":2.964888669,"remaining_time":1.009492925},
{"learn":[50.08493358],"iteration":746,"passed_time":2.968869471,"remaining_time":1.005520718},
{"learn":[50.05138111],"iteration":747,"passed_time":2.972578558,"remaining_time":1.001456947},
{"learn":[50.02987208],"iteration":748,"passed_time":2.975997765,"remaining_time":0.9972969812},
{"learn":[50.01644095],"iteration":749,"passed_time":2.979829918,"remaining_time":0.9932766392},
{"learn":[49.99745576],"iteration":750,"passed_time":2.984300842,"remaining_time":0.9894685881},
{"learn":[49.97893679],"iteration":751,"passed_time":2.98788657,"remaining_time":0.9853668475},
{"learn":[49.97026328],"iteration":752,"passed_time":2.991296982,"remaining_time":0.9812089701},
{"learn":[49.94694479],"iteration":753,"passed_time":2.995286735,"remaining_time":0.9772420914},
{"learn":[49.913628],"iteration":754,"passed_time":2.999693684,"remaining_time":0.9734105333},
{"learn":[49.89340139],"iteration":755,"passed_time":3.003290277,"remaining_time":0.9693159094},
{"learn":[49.87379032],"iteration":756,"passed_time":3.006909516,"remaining_time":0.9652298709},
{"learn":[49.84402118],"iteration":757,"passed_time":3.010249061,"remaining_time":0.9610557688},
{"learn":[49.82566777],"iteration":758,"passed_time":3.014816749,"remaining_time":0.9572738293},
{"learn":[49.80272643],"iteration":759,"passed_time":3.018584362,"remaining_time":0.953237167},
{"learn":[49.78481772],"iteration":760,"passed_time":3.022040237,"remaining_time":0.949103307},
{"learn":[49.76891754],"iteration":761,"passed_time":3.025386547,"remaining_time":0.9449370054},
{"learn":[49.7562081],"iteration":762,"passed_time":3.029960238,"remaining_time":0.9411540975},
{"learn":[49.7341463],"iteration":763,"passed_time":3.033826838,"remaining_time":0.9371506986},
{"learn":[49.70420144],"iteration":764,"passed_time":3.037264125,"remaining_time":0.9330157768},
{"learn":[49.67944881],"iteration":765,"passed_time":3.040470997,"remaining_time":0.9288122888},
{"learn":[49.65578444],"iteration":766,"passed_time":3.044138324,"remaining_time":0.9247512769},
{"learn":[49.62924229],"iteration":767,"passed_time":3.0488717,"remaining_time":0.921013326},
{"learn":[49.61570847],"iteration":768,"passed_time":3.052740528,"remaining_time":0.9170130846},
{"learn":[49.60013972],"iteration":769,"passed_time":3.056645412,"remaining_time":0.9130239541},
{"learn":[49.57604795],"iteration":770,"passed_time":3.061935301,"remaining_time":0.9094464123},
{"learn":[49.55714246],"iteration":771,"passed_time":3.066636629,"remaining_time":0.9056906105},
{"learn":[49.51407919],"iteration":772,"passed_time":3.07091576,"remaining_time":0.9018083797},
{"learn":[49.48065413],"iteration":773,"passed_time":3.074609808,"remaining_time":0.897754285},
{"learn":[49.46270917],"iteration":774,"passed_time":3.080437453,"remaining_time":0.8943205509},
{"learn":[49.44872156],"iteration":775,"passed_time":3.084987739,"remaining_time":0.8905119248},
{"learn":[49.42525509],"iteration":776,"passed_time":3.088788951,"remaining_time":0.8864864041},
{"learn":[49.40404607],"iteration":777,"passed_time":3.093161017,"remaining_time":0.882624352},
{"learn":[49.3813001],"iteration":778,"passed_time":3.097729074,"remaining_time":0.8788165923},
{"learn":[49.35619091],"iteration":779,"passed_time":3.1019389,"remaining_time":0.8749058435},
{"learn":[49.31857317],"iteration":780,"passed_time":3.105774323,"remaining_time":0.8708893428},
{"learn":[49.29362676],"iteration":781,"passed_time":3.110315314,"remaining_time":0.867069998},
{"learn":[49.25689443],"iteration":782,"passed_time":3.114483192,"remaining_time":0.8631454058},
{"learn":[49.23480513],"iteration":783,"passed_time":3.118418007,"remaining_time":0.8591559814},
{"learn":[49.21200735],"iteration":784,"passed_time":3.121799858,"remaining_time":0.8550152478},
{"learn":[49.18978803],"iteration":785,"passed_time":3.126641288,"remaining_time":0.8512738367},
{"learn":[49.15873252],"iteration":786,"passed_time":3.13061213,"remaining_time":0.8472940074},
{"learn":[49.14089592],"iteration":787,"passed_time":3.134239118,"remaining_time":0.8432216918},
{"learn":[49.11307798],"iteration":788,"passed_time":3.138127351,"remaining_time":0.8392203688},
{"learn":[49.09544065],"iteration":789,"passed_time":3.142907841,"remaining_time":0.8354565148},
{"learn":[49.07641846],"iteration":790,"passed_time":3.146761829,"remaining_time":0.8314452873},
{"learn":[49.06610197],"iteration":791,"passed_time":3.150345452,"remaining_time":0.827363452},
{"learn":[49.04777409],"iteration":792,"passed_time":3.154015059,"remaining_time":0.823305318},
{"learn":[49.03453638],"iteration":793,"passed_time":3.158500859,"remaining_time":0.8194599207},
{"learn":[48.99764977],"iteration":794,"passed_time":3.162703182,"remaining_time":0.8155398142},
{"learn":[48.97819357],"iteration":795,"passed_time":3.166201168,"remaining_time":0.8114384904},
{"learn":[48.96883687],"iteration":796,"passed_time":3.169998929,"remaining_time":0.8074150346},
{"learn":[48.95218375],"iteration":797,"passed_time":3.174506769,"remaining_time":0.8035718888},
{"learn":[48.93717878],"iteration":798,"passed_time":3.178167107,"remaining_time":0.799513878},
{"learn":[48.92170573],"iteration":799,"passed_time":3.181503452,"remaining_time":0.7953758629},
{"learn":[48.89561671],"iteration":800,"passed_time":3.185115909,"remaining_time":0.7913084467},
{"learn":[48.87436576],"iteration":801,"passed_time":3.190093738,"remaining_time":0.7875792521},
{"learn":[48.85728641],"iteration":802,"passed_time":3.194428054,"remaining_time":0.7836890742},
{"learn":[48.82868324],"iteration":803,"passed_time":3.198568368,"remaining_time":0.7797504977},
{"learn":[48.81398396],"iteration":804,"passed_time":3.202385215,"remaining_time":0.7757330645},
{"learn":[48.79726002],"iteration":805,"passed_time":3.206915153,"remaining_time":0.7718877662},
{"learn":[48.78704443],"iteration":806,"passed_time":3.210653345,"remaining_time":0.7678514196},
{"learn":[48.77051895],"iteration":807,"passed_time":3.214062843,"remaining_time":0.7637377053},
{"learn":[48.75179502],"iteration":808,"passed_time":3.217356068,"remaining_time":0.7595982805},
{"learn":[48.7345953],"iteration":809,"passed_time":3.22183821,"remaining_time":0.7557398271},
{"learn":[48.70896197],"iteration":810,"passed_time":3.225696623,"remaining_time":0.7517344782},
{"learn":[48.69889167],"iteration":811,"passed_time":3.229401894,"remaining_time":0.7476940345},
{"learn":[48.67111393],"iteration":812,"passed_time":3.232828673,"remaining_time":0.743590359},
{"learn":[48.65839885],"iteration":813,"passed_time":3.237362979,"remaining_time":0.7397414179},
{"learn":[48.6304447],"iteration":814,"passed_time":3.241504388,"remaining_time":0.7358016095},
{"learn":[48.60072634],"iteration":815,"passed_time":3.245035723,"remaining_time":0.7317237414},
{"learn":[48.56950747],"iteration":816,"passed_time":3.248728794,"remaining_time":0.7276834385},
{"learn":[48.54971041],"iteration":817,"passed_time":3.253017588,"remaining_time":0.7237765293},
{"learn":[48.52540133],"iteration":818,"passed_time":3.257163712,"remaining_time":0.7198371573},
{"learn":[48.50069662],"iteration":819,"passed_time":3.260629058,"remaining_time":0.715747842},
{"learn":[48.49029567],"iteration":820,"passed_time":3.264030982,"remaining_time":0.711646219},
{"learn":[48.46282433],"iteration":821,"passed_time":3.267871707,"remaining_time":0.7076413185},
{"learn":[48.44853517],"iteration":822,"passed_time":3.272315675,"remaining_time":0.7037665545},
{"learn":[48.42164049],"iteration":823,"passed_time":3.275777615,"remaining_time":0.6996806557},
{"learn":[48.41505608],"iteration":824,"passed_time":3.27914785,"remaining_time":0.6955768167},
{"learn":[48.40202888],"iteration":825,"passed_time":3.282382015,"remaining_time":0.6914460902},
{"learn":[48.39634084],"iteration":826,"passed_time":3.285547713,"remaining_time":0.6873032096},
{"learn":[48.37978102],"iteration":827,"passed_time":3.28936285,"remaining_time":0.6832975968},
{"learn":[48.35399425],"iteration":828,"passed_time":3.29371093,"remaining_time":0.6794023752},
{"learn":[48.33156223],"iteration":829,"passed_time":3.297741145,"remaining_time":0.6754409575},
{"learn":[48.31467548],"iteration":830,"passed_time":3.301102653,"remaining_time":0.6713433794},
{"learn":[48.29320731],"iteration":831,"passed_time":3.304463122,"remaining_time":0.6672473612},
{"learn":[48.27706935],"iteration":832,"passed_time":3.308169289,"remaining_time":0.6632224144},
{"learn":[48.25596638],"iteration":833,"passed_time":3.312286756,"remaining_time":0.6592800976},
{"learn":[48.21906133],"iteration":834,"passed_time":3.316502496,"remaining_time":0.6553567807},
{"learn":[48.20151501],"iteration":835,"passed_time":3.320918678,"remaining_time":0.6514720851},
{"learn":[48.18358996],"iteration":836,"passed_time":3.325469268,"remaining_time":0.6476122948},
{"learn":[48.14489528],"iteration":837,"passed_time":3.329878621,"remaining_time":0.6437235521},
{"learn":[48.13093339],"iteration":838,"passed_time":3.333550063,"remaining_time":0.6396919668},
{"learn":[48.11992691],"iteration":839,"passed_time":3.337933075,"remaining_time":0.6357967762},
{"learn":[48.09665603],"iteration":840,"passed_time":3.342629546,"remaining_time":0.6319596882},
{"learn":[48.06417244],"iteration":841,"passed_time":3.346562284,"remaining_time":0.6279772457},
{"learn":[48.04528254],"iteration":842,"passed_time":3.349852379,"remaining_time":0.6238752355},
{"learn":[48.02037601],"iteration":843,"passed_time":3.353153099,"remaining_time":0.6197771132},
{"learn":[48.01036805],"iteration":844,"passed_time":3.356925904,"remaining_time":0.6157674735},
{"learn":[47.99351657],"iteration":845,"passed_time":3.360469496,"remaining_time":0.6117166694},
{"learn":[47.96035455],"iteration":846,"passed_time":3.364012974,"remaining_time":0.6076670425},
{"learn":[47.94085518],"iteration":847,"passed_time":3.368475591,"remaining_time":0.6037833607},
{"learn":[47.91243334],"iteration":848,"passed_time":3.372106595,"remaining_time":0.5997504074},
{"learn":[47.88918541],"iteration":849,"passed_time":3.375631284,"remaining_time":0.5956996383},
{"learn":[47.87492722],"iteration":850,"passed_time":3.37904146,"remaining_time":0.5916300559},
{"learn":[47.8692186],"iteration":851,"passed_time":3.383333959,"remaining_time":0.5877152887},
{"learn":[47.84362011],"iteration":852,"passed_time":3.387243808,"remaining_time":0.5837336926},
{"learn":[47.82881038],"iteration":853,"passed_time":3.390549178,"remaining_time":0.5796489227},
{"learn":[47.81647048],"iteration":854,"passed_time":3.394387119,"remaining_time":0.575656295},
{"learn":[47.79333057],"iteration":855,"passed_time":3.398853296,"remaining_time":0.5717697134},
{"learn":[47.77862814],"iteration":856,"passed_time":3.402767987,"remaining_time":0.5677897574},
{"learn":[47.76267301],"iteration":857,"passed_time":3.40606834,"remaining_time":0.56370828},
{"learn":[47.72543385],"iteration":858,"passed_time":3.409815492,"remaining_time":0.5597019609},
{"learn":[47.70944251],"iteration":859,"passed_time":3.414198519,"remaining_time":0.5557997589},
{"learn":[47.68887166],"iteration":860,"passed_time":3.418135738,"remaining_time":0.5518244687},
{"learn":[47.67287513],"iteration":861,"passed_time":3.421705681,"remaining_time":0.5477904686},
{"learn":[47.64273398],"iteration":862,"passed_time":3.425299496,"remaining_time":0.5437613336},
{"learn":[47.63415854],"iteration":863,"passed_time":3.429441906,"remaining_time":0.5398195593},
{"learn":[47.61412355],"iteration":864,"passed_time":3.43349174,"remaining_time":0.5358628728},
{"learn":[47.59760609],"iteration":865,"passed_time":3.4369231,"remaining_time":0.5318102718},
{"learn":[47.57332504],"iteration":866,"passed_time":3.440329078,"remaining_time":0.5277552103},
{"learn":[47.54931548],"iteration":867,"passed_time":3.444203968,"remaining_time":0.5237729537},
{"learn":[47.52644616],"iteration":868,"passed_time":3.448778639,"remaining_time":0.5198964346},
{"learn":[47.50772685],"iteration":869,"passed_time":3.452570403,"remaining_time":0.5159013246},
{"learn":[47.48891961],"iteration":870,"passed_time":3.455887664,"remaining_time":0.5118364049},
{"learn":[47.46669624],"iteration":871,"passed_time":3.459538307,"remaining_time":0.5078221367},
{"learn":[47.44496659],"iteration":872,"passed_time":3.464229287,"remaining_time":0.5039600452},
{"learn":[47.42728461],"iteration":873,"passed_time":3.46801692,"remaining_time":0.499965826},
{"learn":[47.40689166],"iteration":874,"passed_time":3.471313108,"remaining_time":0.4959018726},
{"learn":[47.36489253],"iteration":875,"passed_time":3.474620012,"remaining_time":0.4918411889},
{"learn":[47.34111738],"iteration":876,"passed_time":3.479736741,"remaining_time":0.4880360537},
{"learn":[47.32040887],"iteration":877,"passed_time":3.483784607,"remaining_time":0.4840794101},
{"learn":[47.29391104],"iteration":878,"passed_time":3.487266881,"remaining_time":0.4800447014},
{"learn":[47.27152677],"iteration":879,"passed_time":3.491011838,"remaining_time":0.4760470688},
{"learn":[47.24775838],"iteration":880,"passed_time":3.495892763,"remaining_time":0.4722034493},
{"learn":[47.22537052],"iteration":881,"passed_time":3.500076388,"remaining_time":0.4682641879},
{"learn":[47.19486976],"iteration":882,"passed_time":3.503885588,"remaining_time":0.4642747608},
{"learn":[47.17769934],"iteration":883,"passed_time":3.508009505,"remaining_time":0.4603270391},
{"learn":[47.15106905],"iteration":884,"passed_time":3.512379087,"remaining_time":0.4564108418},
{"learn":[47.1411768],"iteration":885,"passed_time":3.516560593,"remaining_time":0.4524694217},
{"learn":[47.13566055],"iteration":886,"passed_time":3.520146536,"remaining_time":0.448451588},
{"learn":[47.1251891],"iteration":887,"passed_time":3.524262554,"remaining_time":0.4445015834},
{"learn":[47.11400663],"iteration":888,"passed_time":3.528746499,"remaining_time":0.4405971445},
{"learn":[47.08926577],"iteration":889,"passed_time":3.532486718,"remaining_time":0.436599482},
{"learn":[47.07850156],"iteration":890,"passed_time":3.535824304,"remaining_time":0.4325531415},
{"learn":[47.06555815],"iteration":891,"passed_time":3.539774882,"remaining_time":0.4285826091},
{"learn":[47.04819724],"iteration":892,"passed_time":3.544063472,"remaining_time":0.424652622},
{"learn":[47.03508829],"iteration":893,"passed_time":3.547767429,"remaining_time":0.420652514},
{"learn":[47.01699191],"iteration":894,"passed_time":3.5513917,"remaining_time":0.416643719},
{"learn":[47.00077095],"iteration":895,"passed_time":3.556134609,"remaining_time":0.4127656242},
{"learn":[46.989631],"iteration":896,"passed_time":3.560546394,"remaining_time":0.4088475793},
{"learn":[46.96823596],"iteration":897,"passed_time":3.564307036,"remaining_time":0.404854474},
{"learn":[46.94643893],"iteration":898,"passed_time":3.567987174,"remaining_time":0.4008528416},
{"learn":[46.91787006],"iteration":899,"passed_time":3.571856091,"remaining_time":0.396872899},
{"learn":[46.89563202],"iteration":900,"passed_time":3.575877919,"remaining_time":0.3929100044},
{"learn":[46.87420787],"iteration":901,"passed_time":3.580235186,"remaining_time":0.3889834237},
{"learn":[46.86101891],"iteration":902,"passed_time":3.584217665,"remaining_time":0.3850156296},
{"learn":[46.84602148],"iteration":903,"passed_time":3.587882831,"remaining_time":0.381014106},
{"learn":[46.80941102],"iteration":904,"passed_time":3.591332359,"remaining_time":0.3769906896},
{"learn":[46.78593274],"iteration":905,"passed_time":3.594791522,"remaining_time":0.3729695398},
{"learn":[46.77116638],"iteration":906,"passed_time":3.598296761,"remaining_time":0.3689543537},
{"learn":[46.74002519],"iteration":907,"passed_time":3.602372506,"remaining_time":0.3649980953},
{"learn":[46.70894274],"iteration":908,"passed_time":3.606722973,"remaining_time":0.3610690765},
{"learn":[46.67518531],"iteration":909,"passed_time":3.610711256,"remaining_time":0.357103311},
{"learn":[46.65426865],"iteration":910,"passed_time":3.614575604,"remaining_time":0.3531253883},
{"learn":[46.6385287],"iteration":911,"passed_time":3.618080337,"remaining_time":0.349113015},
{"learn":[46.6205966],"iteration":912,"passed_time":3.622605084,"remaining_time":0.3451989511},
{"learn":[46.60973352],"iteration":913,"passed_time":3.626295063,"remaining_time":0.341205006},
{"learn":[46.59507952],"iteration":914,"passed_time":3.629712265,"remaining_time":0.3371863852},
{"learn":[46.57992004],"iteration":915,"passed_time":3.633044875,"remaining_time":0.3331613204},
{"learn":[46.55953091],"iteration":916,"passed_time":3.636975386,"remaining_time":0.3291918833},
{"learn":[46.54504849],"iteration":917,"passed_time":3.641277575,"remaining_time":0.3252557311},
{"learn":[46.52264616],"iteration":918,"passed_time":3.64526994,"remaining_time":0.3212914746},
{"learn":[46.5113755],"iteration":919,"passed_time":3.648567227,"remaining_time":0.3172667154},
{"learn":[46.48864902],"iteration":920,"passed_time":3.652069419,"remaining_time":0.3132611119},
{"learn":[46.45935157],"iteration":921,"passed_time":3.656299664,"remaining_time":0.3093181929},
{"learn":[46.45049244],"iteration":922,"passed_time":3.660460866,"remaining_time":0.3053688913},
{"learn":[46.42899185],"iteration":923,"passed_time":3.664115431,"remaining_time":0.3013774597},
{"learn":[46.40964463],"iteration":924,"passed_time":3.667530881,"remaining_time":0.2973673687},
{"learn":[46.39823589],"iteration":925,"passed_time":3.671481065,"remaining_time":0.2934012946},
{"learn":[46.38142137],"iteration":926,"passed_time":3.675619992,"remaining_time":0.289450118},
{"learn":[46.36510128],"iteration":927,"passed_time":3.679326913,"remaining_time":0.2854650191},
{"learn":[46.33725897],"iteration":928,"passed_time":3.682941562,"remaining_time":0.2814734671},
{"learn":[46.31202377],"iteration":929,"passed_time":3.686705926,"remaining_time":0.2774939944},
{"learn":[46.30187779],"iteration":930,"passed_time":3.691139727,"remaining_time":0.2735645984},
{"learn":[46.26753859],"iteration":931,"passed_time":3.695589231,"remaining_time":0.2696352658},
{"learn":[46.24340275],"iteration":932,"passed_time":3.700090992,"remaining_time":0.2657085707},
{"learn":[46.23471151],"iteration":933,"passed_time":3.703556859,"remaining_time":0.261707444},
{"learn":[46.22407069],"iteration":934,"passed_time":3.707274148,"remaining_time":0.2577249408},
{"learn":[46.20374999],"iteration":935,"passed_time":3.710940884,"remaining_time":0.2537395476},
{"learn":[46.1863242],"iteration":936,"passed_time":3.714332949,"remaining_time":0.2497363669},
{"learn":[46.17399048],"iteration":937,"passed_time":3.718556446,"remaining_time":0.2457894453},
{"learn":[46.16067193],"iteration":938,"passed_time":3.723454367,"remaining_time":0.2418857469},
{"learn":[46.14262195],"iteration":939,"passed_time":3.726776847,"remaining_time":0.2378793732},
{"learn":[46.11450274],"iteration":940,"passed_time":3.730191094,"remaining_time":0.2338802067},
{"learn":[46.09730882],"iteration":941,"passed_time":3.734341553,"remaining_time":0.2299276116},
{"learn":[46.08000078],"iteration":942,"passed_time":3.738703129,"remaining_time":0.2259873578},
{"learn":[46.05985791],"iteration":943,"passed_time":3.742387032,"remaining_time":0.2220060104},
{"learn":[46.0412575],"iteration":944,"passed_time":3.745880426,"remaining_time":0.2180142047},
{"learn":[46.03410352],"iteration":945,"passed_time":3.750475637,"remaining_time":0.2140863472},
{"learn":[46.01787089],"iteration":946,"passed_time":3.755103145,"remaining_time":0.2101588877},
{"learn":[46.00498764],"iteration":947,"passed_time":3.75915324,"remaining_time":0.206198279},
{"learn":[45.9944966],"iteration":948,"passed_time":3.762954679,"remaining_time":0.2022241187},
{"learn":[45.97745992],"iteration":949,"passed_time":3.76866108,"remaining_time":0.1983505831},
{"learn":[45.96928098],"iteration":950,"passed_time":3.773095332,"remaining_time":0.1944076459},
{"learn":[45.95428427],"iteration":951,"passed_time":3.777513752,"remaining_time":0.1904628782},
{"learn":[45.93442291],"iteration":952,"passed_time":3.782758567,"remaining_time":0.1865578727},
{"learn":[45.89952561],"iteration":953,"passed_time":3.787687511,"remaining_time":0.1826348276},
{"learn":[45.88759751],"iteration":954,"passed_time":3.792242275,"remaining_time":0.1786920443},
{"learn":[45.8615342],"iteration":955,"passed_time":3.796891631,"remaining_time":0.1747523345},
{"learn":[45.83760608],"iteration":956,"passed_time":3.802120636,"remaining_time":0.1708371863},
{"learn":[45.81668805],"iteration":957,"passed_time":3.806258002,"remaining_time":0.1668714364},
{"learn":[45.80093896],"iteration":958,"passed_time":3.810608102,"remaining_time":0.1629144236},
{"learn":[45.77369504],"iteration":959,"passed_time":3.814850146,"remaining_time":0.1589520894},
{"learn":[45.73483028],"iteration":960,"passed_time":3.81950858,"remaining_time":0.1550060714},
{"learn":[45.73115912],"iteration":961,"passed_time":3.824440077,"remaining_time":0.1510693586},
{"learn":[45.70408915],"iteration":962,"passed_time":3.829288109,"remaining_time":0.1471273728},
{"learn":[45.69360164],"iteration":963,"passed_time":3.833940476,"remaining_time":0.1431762004},
{"learn":[45.6681478],"iteration":964,"passed_time":3.838252717,"remaining_time":0.1392112384},
{"learn":[45.64404273],"iteration":965,"passed_time":3.842262102,"remaining_time":0.135234898},
{"learn":[45.63869201],"iteration":966,"passed_time":3.847058495,"remaining_time":0.1312853468},
{"learn":[45.62865036],"iteration":967,"passed_time":3.851338868,"remaining_time":0.1273169874},
{"learn":[45.6108067],"iteration":968,"passed_time":3.856146979,"remaining_time":0.1233648672},
{"learn":[45.59031387],"iteration":969,"passed_time":3.860972582,"remaining_time":0.1194115232},
{"learn":[45.57071703],"iteration":970,"passed_time":3.86642079,"remaining_time":0.1154749773},
{"learn":[45.55051812],"iteration":971,"passed_time":3.870301199,"remaining_time":0.111490158},
{"learn":[45.52278614],"iteration":972,"passed_time":3.874512076,"remaining_time":0.1075147236},
{"learn":[45.50283251],"iteration":973,"passed_time":3.879553556,"remaining_time":0.1035609779},
{"learn":[45.48730191],"iteration":974,"passed_time":3.884106761,"remaining_time":0.09959248106},
{"learn":[45.47001619],"iteration":975,"passed_time":3.887946637,"remaining_time":0.09560524517},
{"learn":[45.45012743],"iteration":976,"passed_time":3.892417492,"remaining_time":0.09163316512},
{"learn":[45.43627539],"iteration":977,"passed_time":3.897252576,"remaining_time":0.08766825836},
{"learn":[45.41970656],"iteration":978,"passed_time":3.901757107,"remaining_time":0.0836944834},
{"learn":[45.40649309],"iteration":979,"passed_time":3.90547592,"remaining_time":0.07970359021},
{"learn":[45.39307273],"iteration":980,"passed_time":3.909585737,"remaining_time":0.07572082466},
{"learn":[45.3782748],"iteration":981,"passed_time":3.914369579,"remaining_time":0.07175015521},
{"learn":[45.35064688],"iteration":982,"passed_time":3.918432009,"remaining_time":0.06776535518},
{"learn":[45.33952053],"iteration":983,"passed_time":3.922215985,"remaining_time":0.06377586968},
{"learn":[45.32019723],"iteration":984,"passed_time":3.926890548,"remaining_time":0.05980036367},
{"learn":[45.30524959],"iteration":985,"passed_time":3.930954919,"remaining_time":0.05581477572},
{"learn":[45.28127172],"iteration":986,"passed_time":3.935173024,"remaining_time":0.05183105301},
{"learn":[45.27305893],"iteration":987,"passed_time":3.93849987,"remaining_time":0.04783603081},
{"learn":[45.24010596],"iteration":988,"passed_time":3.942813517,"remaining_time":0.04385333538},
{"learn":[45.22771087],"iteration":989,"passed_time":3.947038379,"remaining_time":0.03986907454},
{"learn":[45.20926826],"iteration":990,"passed_time":3.950727966,"remaining_time":0.03587946689},
{"learn":[45.1823946],"iteration":991,"passed_time":3.954226206,"remaining_time":0.03188892102},
{"learn":[45.1566931],"iteration":992,"passed_time":3.958497742,"remaining_time":0.02790481792},
{"learn":[45.13886215],"iteration":993,"passed_time":3.962542157,"remaining_time":0.02391876554},
{"learn":[45.11921842],"iteration":994,"passed_time":3.966428202,"remaining_time":0.01993180001},
{"learn":[45.09809401],"iteration":995,"passed_time":3.970009023,"remaining_time":0.01594381134},
{"learn":[45.08130921],"iteration":996,"passed_time":3.974238488,"remaining_time":0.01195859124},
{"learn":[45.06022967],"iteration":997,"passed_time":3.978209793,"remaining_time":0.007972364314},
{"learn":[45.05036567],"iteration":998,"passed_time":3.982068317,"remaining_time":0.003986054371},
{"learn":[45.03071883],"iteration":999,"passed_time":3.985450211,"remaining_time":0}
]}