{
"meta":{"test_sets":[],"test_metrics":[],"learn_metrics":[{"best_value":"Min","name":"RMSE"}],"launch_mode":"Train","parameters":"","iteration_count":1000,"learn_sets":["learn"],"name":"experiment"},
"iterations":[
{"learn":[202.0480352],"iteration":0,"passed_time":0.01291835315,"remaining_time":12.9054348},
{"learn":[191.8931591],"iteration":1,"passed_time":0.02318548538,"remaining_time":11.5695572},
{"learn":[182.3988526],"iteration":2,"passed_time":0.0324837583,"remaining_time":10.79543567},
{"learn":[173.5645155],"iteration":3,"passed_time":0.04368660898,"remaining_time":10.87796564},
{"learn":[165.5056099],"iteration":4,"passed_time":0.05353550085,"remaining_time":10.65356467},
{"learn":[157.9600668],"iteration":5,"passed_time":0.06387887378,"remaining_time":10.58260009},
{"learn":[151.1102025],"iteration":6,"passed_time":0.07265067334,"remaining_time":10.30601695},
{"learn":[144.6761328],"iteration":7,"passed_time":0.08266958388,"remaining_time":10.2510284},
{"learn":[138.8791245],"iteration":8,"passed_time":0.09279195424,"remaining_time":10.21742518},
{"learn":[133.4172281],"iteration":9,"passed_time":0.1028933777,"remaining_time":10.1864444},
{"learn":[128.382132],"iteration":10,"passed_time":0.112197021,"remaining_time":10.08753216},
{"learn":[123.6731171],"iteration":11,"passed_time":0.1220372105,"remaining_time":10.04773033},
{"learn":[119.3603433],"iteration":12,"passed_time":0.1312872933,"remaining_time":9.96773527},
{"learn":[115.5269876],"iteration":13,"passed_time":0.142070729,"remaining_time":10.00583849},
{"learn":[112.0170755],"iteration":14,"passed_time":0.1513429658,"remaining_time":9.938188089},
{"learn":[108.8671287],"iteration":15,"passed_time":0.1610950419,"remaining_time":9.907345079},
{"learn":[105.8365387],"iteration":16,"passed_time":0.170268726,"remaining_time":9.845538685},
{"learn":[103.12972],"iteration":17,"passed_time":0.1799659853,"remaining_time":9.818144309},
{"learn":[100.6562544],"iteration":18,"passed_time":0.1899833896,"remaining_time":9.809142381},
{"learn":[98.34317422],"iteration":19,"passed_time":0.2010418145,"remaining_time":9.851048912},
{"learn":[96.32112567],"iteration":20,"passed_time":0.2117899607,"remaining_time":9.873446263},
{"learn":[94.45093372],"iteration":21,"passed_time":0.2222074852,"remaining_time":9.878132751},
{"learn":[92.78016367],"iteration":22,"passed_time":0.231085888,"remaining_time":9.816126632},
{"learn":[91.18563616],"iteration":23,"passed_time":0.2425268758,"remaining_time":9.862759615},
{"learn":[89.83635264],"iteration":24,"passed_time":0.2520719901,"remaining_time":9.830807612},
{"learn":[88.50079776],"iteration":25,"passed_time":0.2618421748,"remaining_time":9.809010702},
{"learn":[87.33677102],"iteration":26,"passed_time":0.2706630243,"remaining_time":9.753893431},
{"learn":[86.29997018],"iteration":27,"passed_time":0.2813696901,"remaining_time":9.767547813},
{"learn":[85.27849146],"iteration":28,"passed_time":0.2914102273,"remaining_time":9.757218301},
{"learn":[84.46602426],"iteration":29,"passed_time":0.3010107221,"remaining_time":9.732680013},
{"learn":[83.71135137],"iteration":30,"passed_time":0.3097698293,"remaining_time":9.68280531},
{"learn":[83.016204],"iteration":31,"passed_time":0.318999742,"remaining_time":9.649742196},
{"learn":[82.38714108],"iteration":32,"passed_time":0.3273108519,"remaining_time":9.591199813},
{"learn":[81.76301665],"iteration":33,"passed_time":0.3372914519,"remaining_time":9.583045368},
{"learn":[81.22447883],"iteration":34,"passed_time":0.3460051863,"remaining_time":9.53985728},
{"learn":[80.72969058],"iteration":35,"passed_time":0.3553628879,"remaining_time":9.515828444},
{"learn":[80.28278115],"iteration":36,"passed_time":0.3650441741,"remaining_time":9.501014586},
{"learn":[79.78291919],"iteration":37,"passed_time":0.3746414318,"remaining_time":9.484343616},
{"learn":[79.30997802],"iteration":38,"passed_time":0.3840966123,"remaining_time":9.464534472},
{"learn":[78.9685],"iteration":39,"passed_time":0.3934992071,"remaining_time":9.44398097},
{"learn":[78.63340455],"iteration":40,"passed_time":0.4020019981,"remaining_time":9.402924785},
{"learn":[78.30838543],"iteration":41,"passed_time":0.412458121,"remaining_time":9.407973331},
{"learn":[77.97020788],"iteration":42,"passed_time":0.4225080462,"remaining_time":9.40326047},
{"learn":[77.73269489],"iteration":43,"passed_time":0.4319110411,"remaining_time":9.384248984},
{"learn":[77.46311039],"iteration":44,"passed_time":0.4412774396,"remaining_time":9.364887884},
{"learn":[77.22675392],"iteration":45,"passed_time":0.4502785407,"remaining_time":9.338385387},
{"learn":[77.02817034],"iteration":46,"passed_time":0.4588486029,"remaining_time":9.303887629},
{"learn":[76.80424341],"iteration":47,"passed_time":0.4684644006,"remaining_time":9.291210611},
{"learn":[76.60394434],"iteration":48,"passed_time":0.4774257029,"remaining_time":9.265955989},
{"learn":[76.43840929],"iteration":49,"passed_time":0.486994262,"remaining_time":9.252890978},
{"learn":[76.26142424],"iteration":50,"passed_time":0.4964041663,"remaining_time":9.237010858},
{"learn":[76.10461612],"iteration":51,"passed_time":0.5056703519,"remaining_time":9.218759493},
{"learn":[75.96429338],"iteration":52,"passed_time":0.5139335431,"remaining_time":9.18292576},
{"learn":[75.82126602],"iteration":53,"passed_time":0.5227099732,"remaining_time":9.157104346},
{"learn":[75.69444066],"iteration":54,"passed_time":0.5324237664,"remaining_time":9.14800835},
{"learn":[75.53902212],"iteration":55,"passed_time":0.5411423384,"remaining_time":9.122113705},
{"learn":[75.42774754],"iteration":56,"passed_time":0.549745714,"remaining_time":9.094915935},
{"learn":[75.32054548],"iteration":57,"passed_time":0.5586106928,"remaining_time":9.072608149},
{"learn":[75.20580818],"iteration":58,"passed_time":0.5680635208,"remaining_time":9.060131747},
{"learn":[75.05739679],"iteration":59,"passed_time":0.5768527299,"remaining_time":9.037359434},
{"learn":[74.91534915],"iteration":60,"passed_time":0.5859388631,"remaining_time":9.01961627},
{"learn":[74.85139897],"iteration":61,"passed_time":0.5953543199,"remaining_time":9.007134711},
{"learn":[74.69667161],"iteration":62,"passed_time":0.6057817928,"remaining_time":9.00980222},
{"learn":[74.59336158],"iteration":63,"passed_time":0.6147091949,"remaining_time":8.990121976},
{"learn":[74.5230884],"iteration":64,"passed_time":0.6239761158,"remaining_time":8.975656435},
{"learn":[74.4470257],"iteration":65,"passed_time":0.6363301663,"remaining_time":9.005035989},
{"learn":[74.30760207],"iteration":66,"passed_time":0.6509570021,"remaining_time":9.064819149},
{"learn":[74.2108207],"iteration":67,"passed_time":0.6661220592,"remaining_time":9.129790576},
{"learn":[74.1363799],"iteration":68,"passed_time":0.6813814644,"remaining_time":9.193712222},
{"learn":[74.08929291],"iteration":69,"passed_time":0.6922145529,"remaining_time":9.196564774},
{"learn":[74.01821579],"iteration":70,"passed_time":0.7034830444,"remaining_time":9.204728848},
{"learn":[73.94533368],"iteration":71,"passed_time":0.7136912462,"remaining_time":9.198687173},
{"learn":[73.88827422],"iteration":72,"passed_time":0.724252271,"remaining_time":9.197011715},
{"learn":[73.81861178],"iteration":73,"passed_time":0.7328535852,"remaining_time":9.170573241},
{"learn":[73.76024],"iteration":74,"passed_time":0.7422655142,"remaining_time":9.154608008},
{"learn":[73.68641162],"iteration":75,"passed_time":0.7506490068,"remaining_time":9.126311609},
{"learn":[73.62606324],"iteration":76,"passed_time":0.7591061784,"remaining_time":9.099415619},
{"learn":[73.57053808],"iteration":77,"passed_time":0.7677953626,"remaining_time":9.075734927},
{"learn":[73.49612948],"iteration":78,"passed_time":0.7777809923,"remaining_time":9.067548024},
{"learn":[73.46032244],"iteration":79,"passed_time":0.7873344689,"remaining_time":9.054346393},
{"learn":[73.36856253],"iteration":80,"passed_time":0.7963818796,"remaining_time":9.035493177},
{"learn":[73.26756455],"iteration":81,"passed_time":0.806611309,"remaining_time":9.030111971},
{"learn":[73.15484225],"iteration":82,"passed_time":0.8161275515,"remaining_time":9.016734515},
{"learn":[73.02054344],"iteration":83,"passed_time":0.8274025573,"remaining_time":9.022627887},
{"learn":[72.95448463],"iteration":84,"passed_time":0.8367561524,"remaining_time":9.007433876},
{"learn":[72.86954879],"iteration":85,"passed_time":0.8477684339,"remaining_time":9.010004053},
{"learn":[72.80003378],"iteration":86,"passed_time":0.8571954131,"remaining_time":8.995625427},
{"learn":[72.74804904],"iteration":87,"passed_time":0.8670313162,"remaining_time":8.985597277},
{"learn":[72.69073334],"iteration":88,"passed_time":0.8775892186,"remaining_time":8.982963799},
{"learn":[72.62652344],"iteration":89,"passed_time":0.8867526288,"remaining_time":8.966054357},
{"learn":[72.57585426],"iteration":90,"passed_time":0.896781995,"remaining_time":8.957965203},
{"learn":[72.51079715],"iteration":91,"passed_time":0.905531441,"remaining_time":8.937201613},
{"learn":[72.45855229],"iteration":92,"passed_time":0.9145750471,"remaining_time":8.919565244},
{"learn":[72.40233928],"iteration":93,"passed_time":0.9240684645,"remaining_time":8.906447115},
{"learn":[72.3480038],"iteration":94,"passed_time":0.9342393398,"remaining_time":8.899858974},
{"learn":[72.25607173],"iteration":95,"passed_time":0.9433356088,"remaining_time":8.883076983},
{"learn":[72.18023587],"iteration":96,"passed_time":0.9524159324,"remaining_time":8.86630502},
{"learn":[72.1158365],"iteration":97,"passed_time":0.9622599809,"remaining_time":8.856719416},
{"learn":[72.05867869],"iteration":98,"passed_time":0.9712714994,"remaining_time":8.839551727},
{"learn":[72.01755041],"iteration":99,"passed_time":0.9804767528,"remaining_time":8.824290775},
{"learn":[71.98544058],"iteration":100,"passed_time":0.9890783348,"remaining_time":8.803776465},
{"learn":[71.91283731],"iteration":101,"passed_time":0.9984809238,"remaining_time":8.790547741},
{"learn":[71.8780908],"iteration":102,"passed_time":1.007534717,"remaining_time":8.774355743},
{"learn":[71.79935591],"iteration":103,"passed_time":1.017960488,"remaining_time":8.770121128},
{"learn":[71.77507388],"iteration":104,"passed_time":1.027225555,"remaining_time":8.755874967},
{"learn":[71.68105975],"iteration":105,"passed_time":1.036490415,"remaining_time":8.741721049},
{"learn":[71.59771535],"iteration":106,"passed_time":1.046019436,"remaining_time":8.729863141},
{"learn":[71.53495869],"iteration":107,"passed_time":1.055484972,"remaining_time":8.717524029},
{"learn":[71.45482408],"iteration":108,"passed_time":1.065036999,"remaining_time":8.705944643},
{"learn":[71.41853199],"iteration":109,"passed_time":1.073963817,"remaining_time":8.689343611},
{"learn":[71.37888732],"iteration":110,"passed_time":1.08248775,"remaining_time":8.669654145},
{"learn":[71.34161471],"iteration":111,"passed_time":1.09235649,"remaining_time":8.660826455},
{"learn":[71.27751478],"iteration":112,"passed_time":1.101033098,"remaining_time":8.642622639},
{"learn":[71.22502201],"iteration":113,"passed_time":1.110490538,"remaining_time":8.630654534},
{"learn":[71.16772134],"iteration":114,"passed_time":1.118982993,"remaining_time":8.611303902},
{"learn":[71.12556731],"iteration":115,"passed_time":1.127864011,"remaining_time":8.595101604},
{"learn":[71.01901095],"iteration":116,"passed_time":1.137014889,"remaining_time":8.581061083},
{"learn":[70.95444413],"iteration":117,"passed_time":1.145593725,"remaining_time":8.562827671},
{"learn":[70.90867281],"iteration":118,"passed_time":1.155405403,"remaining_time":8.553883698},
{"learn":[70.87861878],"iteration":119,"passed_time":1.164823765,"remaining_time":8.542040943},
{"learn":[70.81787335],"iteration":120,"passed_time":1.173358418,"remaining_time":8.523818592},
{"learn":[70.72801014],"iteration":121,"passed_time":1.18257233,"remaining_time":8.510643488},
{"learn":[70.66901185],"iteration":122,"passed_time":1.191477462,"remaining_time":8.495331172},
{"learn":[70.62035139],"iteration":123,"passed_time":1.199736784,"remaining_time":8.475559861},
{"learn":[70.55985678],"iteration":124,"passed_time":1.209349184,"remaining_time":8.465444287},
{"learn":[70.48229044],"iteration":125,"passed_time":1.218600864,"remaining_time":8.452834565},
{"learn":[70.43558421],"iteration":126,"passed_time":1.228963392,"remaining_time":8.447913709},
{"learn":[70.38218876],"iteration":127,"passed_time":1.238441527,"remaining_time":8.436882901},
{"learn":[70.34498014],"iteration":128,"passed_time":1.247478964,"remaining_time":8.422900599},
{"learn":[70.28971859],"iteration":129,"passed_time":1.256875435,"remaining_time":8.411397141},
{"learn":[70.22667778],"iteration":130,"passed_time":1.266457583,"remaining_time":8.401157557},
{"learn":[70.16711655],"iteration":131,"passed_time":1.274748283,"remaining_time":8.382435682},
{"learn":[70.10783565],"iteration":132,"passed_time":1.284012392,"remaining_time":8.37021612},
{"learn":[70.04647262],"iteration":133,"passed_time":1.29248177,"remaining_time":8.352904571},
{"learn":[69.98123997],"iteration":134,"passed_time":1.301505871,"remaining_time":8.339278357},
{"learn":[69.92350319],"iteration":135,"passed_time":1.310407231,"remaining_time":8.324940055},
{"learn":[69.79881215],"iteration":136,"passed_time":1.319925585,"remaining_time":8.314567737},
{"learn":[69.73336962],"iteration":137,"passed_time":1.33062821,"remaining_time":8.311605194},
{"learn":[69.65331979],"iteration":138,"passed_time":1.340212237,"remaining_time":8.301602419},
{"learn":[69.60051014],"iteration":139,"passed_time":1.348784945,"remaining_time":8.285393231},
{"learn":[69.55081281],"iteration":140,"passed_time":1.359563793,"remaining_time":8.282732608},
{"learn":[69.50816932],"iteration":141,"passed_time":1.369032415,"remaining_time":8.272040928},
{"learn":[69.45165515],"iteration":142,"passed_time":1.379264074,"remaining_time":8.26593924},
{"learn":[69.3936318],"iteration":143,"passed_time":1.387691941,"remaining_time":8.249057648},
{"learn":[69.31443951],"iteration":144,"passed_time":1.396618016,"remaining_time":8.235230372},
{"learn":[69.24169474],"iteration":145,"passed_time":1.405995164,"remaining_time":8.224108701},
{"learn":[69.18225158],"iteration":146,"passed_time":1.414345143,"remaining_time":8.20705039},
{"learn":[69.14173769],"iteration":147,"passed_time":1.423568415,"remaining_time":8.19513709},
{"learn":[69.0900125],"iteration":148,"passed_time":1.43173571,"remaining_time":8.177228785},
{"learn":[69.03868609],"iteration":149,"passed_time":1.441062728,"remaining_time":8.166022127},
{"learn":[68.99033698],"iteration":150,"passed_time":1.449741111,"remaining_time":8.151193401},
{"learn":[68.92027071],"iteration":151,"passed_time":1.459892927,"remaining_time":8.144665806},
{"learn":[68.88752157],"iteration":152,"passed_time":1.469472498,"remaining_time":8.134922915},
{"learn":[68.86025039],"iteration":153,"passed_time":1.478365354,"remaining_time":8.12140967},
{"learn":[68.80011559],"iteration":154,"passed_time":1.487831247,"remaining_time":8.111080023},
{"learn":[68.73099277],"iteration":155,"passed_time":1.498323657,"remaining_time":8.106315172},
{"learn":[68.66478764],"iteration":156,"passed_time":1.506999507,"remaining_time":8.091723468},
{"learn":[68.62045329],"iteration":157,"passed_time":1.51637936,"remaining_time":8.080958359},
{"learn":[68.55618903],"iteration":158,"passed_time":1.52488247,"remaining_time":8.065573314},
{"learn":[68.49254815],"iteration":159,"passed_time":1.534279683,"remaining_time":8.054968335},
{"learn":[68.41154686],"iteration":160,"passed_time":1.543053332,"remaining_time":8.041128854},
{"learn":[68.36890927],"iteration":161,"passed_time":1.553220171,"remaining_time":8.034558662},
{"learn":[68.31602813],"iteration":162,"passed_time":1.562632192,"remaining_time":8.024068371},
{"learn":[68.24600017],"iteration":163,"passed_time":1.570893009,"remaining_time":8.007722897},
{"learn":[68.19422174],"iteration":164,"passed_time":1.580261482,"remaining_time":7.997080831},
{"learn":[68.14412288],"iteration":165,"passed_time":1.588205514,"remaining_time":7.979297583},
{"learn":[68.1010345],"iteration":166,"passed_time":1.60323966,"remaining_time":7.996997824},
{"learn":[68.0417394],"iteration":167,"passed_time":1.615988497,"remaining_time":8.002990651},
{"learn":[67.98711695],"iteration":168,"passed_time":1.626592836,"remaining_time":7.998216844},
{"learn":[67.90848532],"iteration":169,"passed_time":1.637855839,"remaining_time":7.996590272},
{"learn":[67.86766466],"iteration":170,"passed_time":1.647312799,"remaining_time":7.986095381},
{"learn":[67.81090393],"iteration":171,"passed_time":1.658174344,"remaining_time":7.982374167},
{"learn":[67.77862792],"iteration":172,"passed_time":1.666741175,"remaining_time":7.967600879},
{"learn":[67.74416616],"iteration":173,"passed_time":1.677389189,"remaining_time":7.962778562},
{"learn":[67.692839],"iteration":174,"passed_time":1.687683952,"remaining_time":7.956224344},
{"learn":[67.6266777],"iteration":175,"passed_time":1.698053477,"remaining_time":7.949977642},
{"learn":[67.59070659],"iteration":176,"passed_time":1.708341077,"remaining_time":7.943303426},
{"learn":[67.51445647],"iteration":177,"passed_time":1.719208865,"remaining_time":7.939267905},
{"learn":[67.47072935],"iteration":178,"passed_time":1.728686056,"remaining_time":7.928777944},
{"learn":[67.41615967],"iteration":179,"passed_time":1.74003759,"remaining_time":7.92683791},
{"learn":[67.36716251],"iteration":180,"passed_time":1.751639055,"remaining_time":7.925924786},
{"learn":[67.31967131],"iteration":181,"passed_time":1.76083615,"remaining_time":7.91408775},
{"learn":[67.24615552],"iteration":182,"passed_time":1.771390542,"remaining_time":7.908339194},
{"learn":[67.17651068],"iteration":183,"passed_time":1.782581231,"remaining_time":7.905360241},
{"learn":[67.10060054],"iteration":184,"passed_time":1.793076907,"remaining_time":7.899230697},
{"learn":[67.06178279],"iteration":185,"passed_time":1.802590317,"remaining_time":7.888755475},
{"learn":[66.99663589],"iteration":186,"passed_time":1.812314665,"remaining_time":7.87920761},
{"learn":[66.94129131],"iteration":187,"passed_time":1.821300919,"remaining_time":7.866469928},
{"learn":[66.90563363],"iteration":188,"passed_time":1.832068932,"remaining_time":7.861417483},
{"learn":[66.85714939],"iteration":189,"passed_time":1.8418575,"remaining_time":7.852129341},
{"learn":[66.81579647],"iteration":190,"passed_time":1.853423886,"remaining_time":7.850366094},
{"learn":[66.79052423],"iteration":191,"passed_time":1.862923725,"remaining_time":7.839804011},
{"learn":[66.70888738],"iteration":192,"passed_time":1.874196405,"remaining_time":7.836665799},
{"learn":[66.62271969],"iteration":193,"passed_time":1.884437511,"remaining_time":7.829157907},
{"learn":[66.59746732],"iteration":194,"passed_time":1.895168035,"remaining_time":7.823642401},
{"learn":[66.51604167],"iteration":195,"passed_time":1.904709185,"remaining_time":7.813194818},
{"learn":[66.44277278],"iteration":196,"passed_time":1.915491705,"remaining_time":7.807816444},
{"learn":[66.3880015],"iteration":197,"passed_time":1.924673507,"remaining_time":7.795899761},
{"learn":[66.35092572],"iteration":198,"passed_time":1.93443782,"remaining_time":7.786355247},
{"learn":[66.30664305],"iteration":199,"passed_time":1.944274702,"remaining_time":7.777098807},
{"learn":[66.25768719],"iteration":200,"passed_time":1.953652233,"remaining_time":7.766010616},
{"learn":[66.203299],"iteration":201,"passed_time":1.962233935,"remaining_time":7.751795448},
{"learn":[66.13067007],"iteration":202,"passed_time":1.971706829,"remaining_time":7.741134692},
{"learn":[66.04437106],"iteration":203,"passed_time":1.981143865,"remaining_time":7.730345671},
{"learn":[66.00676651],"iteration":204,"passed_time":1.991714421,"remaining_time":7.723965683},
{"learn":[65.9436437],"iteration":205,"passed_time":2.00085573,"remaining_time":7.712036162},
{"learn":[65.88187917],"iteration":206,"passed_time":2.010433061,"remaining_time":7.701803949},
{"learn":[65.82369823],"iteration":207,"passed_time":2.018842282,"remaining_time":7.687130228},
{"learn":[65.78176047],"iteration":208,"passed_time":2.02801347,"remaining_time":7.675400262},
{"learn":[65.76302251],"iteration":209,"passed_time":2.036389248,"remaining_time":7.660702408},
{"learn":[65.72180177],"iteration":210,"passed_time":2.045395864,"remaining_time":7.648423398},
{"learn":[65.6668829],"iteration":211,"passed_time":2.054351861,"remaining_time":7.635987107},
{"learn":[65.61974913],"iteration":212,"passed_time":2.062873684,"remaining_time":7.621979294},
{"learn":[65.52219429],"iteration":213,"passed_time":2.072897618,"remaining_time":7.61353985},
{"learn":[65.45125752],"iteration":214,"passed_time":2.083325251,"remaining_time":7.606559636},
{"learn":[65.39376444],"iteration":215,"passed_time":2.091940794,"remaining_time":7.592970288},
{"learn":[65.35252116],"iteration":216,"passed_time":2.100910597,"remaining_time":7.580705058},
{"learn":[65.30357937],"iteration":217,"passed_time":2.109583066,"remaining_time":7.567403476},
{"learn":[65.2672207],"iteration":218,"passed_time":2.118079333,"remaining_time":7.553515795},
{"learn":[65.24298125],"iteration":219,"passed_time":2.12826419,"remaining_time":7.545663948},
{"learn":[65.18812347],"iteration":220,"passed_time":2.13694504,"remaining_time":7.532489529},
{"learn":[65.14022734],"iteration":221,"passed_time":2.146158638,"remaining_time":7.521222615},
{"learn":[65.10844635],"iteration":222,"passed_time":2.154245142,"remaining_time":7.506046976},
{"learn":[65.06664693],"iteration":223,"passed_time":2.163437374,"remaining_time":7.49476519},
{"learn":[65.04463502],"iteration":224,"passed_time":2.171553567,"remaining_time":7.479795619},
{"learn":[64.99652088],"iteration":225,"passed_time":2.181682876,"remaining_time":7.471781178},
{"learn":[64.96040835],"iteration":226,"passed_time":2.190043182,"remaining_time":7.457724141},
{"learn":[64.90727117],"iteration":227,"passed_time":2.198666607,"remaining_time":7.444607986},
{"learn":[64.85998284],"iteration":228,"passed_time":2.207905718,"remaining_time":7.433603968},
{"learn":[64.78304698],"iteration":229,"passed_time":2.216427284,"remaining_time":7.420213083},
{"learn":[64.74012236],"iteration":230,"passed_time":2.225755895,"remaining_time":7.409551009},
{"learn":[64.70277082],"iteration":231,"passed_time":2.234979425,"remaining_time":7.39855258},
{"learn":[64.6622475],"iteration":232,"passed_time":2.258636929,"remaining_time":7.435083797},
{"learn":[64.63075855],"iteration":233,"passed_time":2.267352057,"remaining_time":7.422186647},
{"learn":[64.60606644],"iteration":234,"passed_time":2.277379553,"remaining_time":7.413597268},
{"learn":[64.560062],"iteration":235,"passed_time":2.285926771,"remaining_time":7.400203616},
{"learn":[64.5018779],"iteration":236,"passed_time":2.295124619,"remaining_time":7.388945503},
{"learn":[64.47102125],"iteration":237,"passed_time":2.303916969,"remaining_time":7.376406431},
{"learn":[64.44149666],"iteration":238,"passed_time":2.312350488,"remaining_time":7.362756157},
{"learn":[64.39347664],"iteration":239,"passed_time":2.322005488,"remaining_time":7.353017379},
{"learn":[64.37224895],"iteration":240,"passed_time":2.330620473,"remaining_time":7.340003896},
{"learn":[64.32034931],"iteration":241,"passed_time":2.339957282,"remaining_time":7.329287685},
{"learn":[64.27780204],"iteration":242,"passed_time":2.348439061,"remaining_time":7.315919215},
{"learn":[64.23363934],"iteration":243,"passed_time":2.357316115,"remaining_time":7.303815504},
{"learn":[64.18877163],"iteration":244,"passed_time":2.365864359,"remaining_time":7.290724862},
{"learn":[64.14234957],"iteration":245,"passed_time":2.375356114,"remaining_time":7.28056305},
{"learn":[64.12127921],"iteration":246,"passed_time":2.384500328,"remaining_time":7.269347154},
{"learn":[64.05498187],"iteration":247,"passed_time":2.393729389,"remaining_time":7.258405245},
{"learn":[63.96270525],"iteration":248,"passed_time":2.40310221,"remaining_time":7.247910682},
{"learn":[63.93482798],"iteration":249,"passed_time":2.41241871,"remaining_time":7.23725613},
{"learn":[63.89225303],"iteration":250,"passed_time":2.422175445,"remaining_time":7.227925931},
{"learn":[63.85824362],"iteration":251,"passed_time":2.431229239,"remaining_time":7.216505837},
{"learn":[63.8011681],"iteration":252,"passed_time":2.440436916,"remaining_time":7.205558799},
{"learn":[63.75908642],"iteration":253,"passed_time":2.449444292,"remaining_time":7.194037173},
{"learn":[63.72270563],"iteration":254,"passed_time":2.458575391,"remaining_time":7.18289673},
{"learn":[63.69313318],"iteration":255,"passed_time":2.468354531,"remaining_time":7.173655357},
{"learn":[63.66053002],"iteration":256,"passed_time":2.477551004,"remaining_time":7.162725277},
{"learn":[63.61401236],"iteration":257,"passed_time":2.485814425,"remaining_time":7.149125208},
{"learn":[63.57101458],"iteration":258,"passed_time":2.495443911,"remaining_time":7.139474665},
{"learn":[63.51052993],"iteration":259,"passed_time":2.504286641,"remaining_time":7.127585056},
{"learn":[63.47106136],"iteration":260,"passed_time":2.51363568,"remaining_time":7.117152365},
{"learn":[63.43896456],"iteration":261,"passed_time":2.521844829,"remaining_time":7.103517113},
{"learn":[63.42216345],"iteration":262,"passed_time":2.530201641,"remaining_time":7.090336919},
{"learn":[63.39020339],"iteration":263,"passed_time":2.539654026,"remaining_time":7.080247588},
{"learn":[63.34404563],"iteration":264,"passed_time":2.548155384,"remaining_time":7.067525309},
{"learn":[63.30051428],"iteration":265,"passed_time":2.557826656,"remaining_time":7.058063028},
{"learn":[63.24542319],"iteration":266,"passed_time":2.567695234,"remaining_time":7.049140848},
{"learn":[63.20945692],"iteration":267,"passed_time":2.576185007,"remaining_time":7.036445615},
{"learn":[63.14796867],"iteration":268,"passed_time":2.585597997,"remaining_time":7.026290469},
{"learn":[63.09749054],"iteration":269,"passed_time":2.594289413,"remaining_time":7.014189895},
{"learn":[63.05647749],"iteration":270,"passed_time":2.603498112,"remaining_time":7.003505993},
{"learn":[63.02781616],"iteration":271,"passed_time":2.613796357,"remaining_time":6.995749074},
{"learn":[63.00332328],"iteration":272,"passed_time":2.622383623,"remaining_time":6.983417193},
{"learn":[62.96861077],"iteration":273,"passed_time":2.631330503,"remaining_time":6.972065494},
{"learn":[62.92535203],"iteration":274,"passed_time":2.639648181,"remaining_time":6.959072476},
{"learn":[62.88361887],"iteration":275,"passed_time":2.649520819,"remaining_time":6.950192293},
{"learn":[62.8208681],"iteration":276,"passed_time":2.65758361,"remaining_time":6.936581048},
{"learn":[62.74662526],"iteration":277,"passed_time":2.66823324,"remaining_time":6.929728054},
{"learn":[62.71524502],"iteration":278,"passed_time":2.676705842,"remaining_time":6.917221908},
{"learn":[62.69150902],"iteration":279,"passed_time":2.685779273,"remaining_time":6.906289558},
{"learn":[62.66278112],"iteration":280,"passed_time":2.694670206,"remaining_time":6.894903481},
{"learn":[62.62868037],"iteration":281,"passed_time":2.702979779,"remaining_time":6.882054899},
{"learn":[62.59512308],"iteration":282,"passed_time":2.712252685,"remaining_time":6.871679064},
{"learn":[62.549443],"iteration":283,"passed_time":2.721162923,"remaining_time":6.860396665},
{"learn":[62.51538161],"iteration":284,"passed_time":2.729677309,"remaining_time":6.848137811},
{"learn":[62.47194937],"iteration":285,"passed_time":2.740979053,"remaining_time":6.842863791},
{"learn":[62.40774694],"iteration":286,"passed_time":2.750617019,"remaining_time":6.833414405},
{"learn":[62.34723893],"iteration":287,"passed_time":2.760374574,"remaining_time":6.824259363},
{"learn":[62.29319847],"iteration":288,"passed_time":2.769430368,"remaining_time":6.813373674},
{"learn":[62.24943765],"iteration":289,"passed_time":2.778212359,"remaining_time":6.801830258},
{"learn":[62.22125217],"iteration":290,"passed_time":2.787222091,"remaining_time":6.790860696},
{"learn":[62.17007683],"iteration":291,"passed_time":2.795813368,"remaining_time":6.778889948},
{"learn":[62.12285376],"iteration":292,"passed_time":2.806366408,"remaining_time":6.77167594},
{"learn":[62.07523187],"iteration":293,"passed_time":2.815652585,"remaining_time":6.761397025},
{"learn":[62.03515919],"iteration":294,"passed_time":2.825139271,"remaining_time":6.751604021},
{"learn":[61.97679219],"iteration":295,"passed_time":2.833358071,"remaining_time":6.738797574},
{"learn":[61.94612338],"iteration":296,"passed_time":2.841893013,"remaining_time":6.726770331},
{"learn":[61.87725755],"iteration":297,"passed_time":2.850582651,"remaining_time":6.715130942},
{"learn":[61.84328474],"iteration":298,"passed_time":2.860969796,"remaining_time":6.707491059},
{"learn":[61.78455436],"iteration":299,"passed_time":2.869970296,"remaining_time":6.696597357},
{"learn":[61.7378708],"iteration":300,"passed_time":2.880041033,"remaining_time":6.688201602},
{"learn":[61.6956959],"iteration":301,"passed_time":2.896458801,"remaining_time":6.694464382},
{"learn":[61.66139646],"iteration":302,"passed_time":2.907975213,"remaining_time":6.689302718},
{"learn":[61.62055677],"iteration":303,"passed_time":2.918453649,"remaining_time":6.681722828},
{"learn":[61.58461199],"iteration":304,"passed_time":2.927331123,"remaining_time":6.670475838},
{"learn":[61.549575],"iteration":305,"passed_time":2.937388696,"remaining_time":6.661920769},
{"learn":[61.51394309],"iteration":306,"passed_time":2.946782646,"remaining_time":6.651857896},
{"learn":[61.47337229],"iteration":307,"passed_time":2.958394659,"remaining_time":6.646782805},
{"learn":[61.44553812],"iteration":308,"passed_time":2.967643613,"remaining_time":6.636381024},
{"learn":[61.38910527],"iteration":309,"passed_time":2.977723944,"remaining_time":6.627837166},
{"learn":[61.3171688],"iteration":310,"passed_time":2.987268149,"remaining_time":6.618095675},
{"learn":[61.27450861],"iteration":311,"passed_time":2.998763884,"remaining_time":6.61265882},
{"learn":[61.23754517],"iteration":312,"passed_time":3.009169694,"remaining_time":6.60479099},
{"learn":[61.20877735],"iteration":313,"passed_time":3.017852571,"remaining_time":6.593142879},
{"learn":[61.16871499],"iteration":314,"passed_time":3.028337113,"remaining_time":6.585431499},
{"learn":[61.14642832],"iteration":315,"passed_time":3.037227902,"remaining_time":6.574252801},
{"learn":[61.08923635],"iteration":316,"passed_time":3.048274404,"remaining_time":6.56773318},
{"learn":[61.06425737],"iteration":317,"passed_time":3.057977259,"remaining_time":6.55830343},
{"learn":[61.036403],"iteration":318,"passed_time":3.067229394,"remaining_time":6.547909771},
{"learn":[60.99621937],"iteration":319,"passed_time":3.077228354,"remaining_time":6.539110252},
{"learn":[60.96565602],"iteration":320,"passed_time":3.086757643,"remaining_time":6.52930978},
{"learn":[60.92956288],"iteration":321,"passed_time":3.096507317,"remaining_time":6.519975033},
{"learn":[60.90928354],"iteration":322,"passed_time":3.106448817,"remaining_time":6.511039781},
{"learn":[60.86324832],"iteration":323,"passed_time":3.116289013,"remaining_time":6.501886954},
{"learn":[60.79576033],"iteration":324,"passed_time":3.126812947,"remaining_time":6.494149967},
{"learn":[60.76402151],"iteration":325,"passed_time":3.13680206,"remaining_time":6.485290149},
{"learn":[60.72572413],"iteration":326,"passed_time":3.1465477,"remaining_time":6.47592233},
{"learn":[60.70764195],"iteration":327,"passed_time":3.15684463,"remaining_time":6.46768168},
{"learn":[60.67923367],"iteration":328,"passed_time":3.168438861,"remaining_time":6.462074395},
{"learn":[60.64189937],"iteration":329,"passed_time":3.178386561,"remaining_time":6.453087866},
{"learn":[60.60511586],"iteration":330,"passed_time":3.189113698,"remaining_time":6.445670887},
{"learn":[60.56860793],"iteration":331,"passed_time":3.199285236,"remaining_time":6.437116078},
{"learn":[60.53469766],"iteration":332,"passed_time":3.209831173,"remaining_time":6.429301478},
{"learn":[60.51167922],"iteration":333,"passed_time":3.218740187,"remaining_time":6.418206481},
{"learn":[60.46044659],"iteration":334,"passed_time":3.230092782,"remaining_time":6.411975224},
{"learn":[60.42012798],"iteration":335,"passed_time":3.240836431,"remaining_time":6.404510089},
{"learn":[60.38529033],"iteration":336,"passed_time":3.251153831,"remaining_time":6.396186913},
{"learn":[60.35341941],"iteration":337,"passed_time":3.261413886,"remaining_time":6.387739623},
{"learn":[60.33008935],"iteration":338,"passed_time":3.272673285,"remaining_time":6.381230212},
{"learn":[60.28673216],"iteration":339,"passed_time":3.281737627,"remaining_time":6.370431865},
{"learn":[60.26623326],"iteration":340,"passed_time":3.290967127,"remaining_time":6.359962865},
{"learn":[60.23494773],"iteration":341,"passed_time":3.299216577,"remaining_time":6.34761552},
{"learn":[60.20589191],"iteration":342,"passed_time":3.308606487,"remaining_time":6.337476565},
{"learn":[60.18952167],"iteration":343,"passed_time":3.317756563,"remaining_time":6.326884609},
{"learn":[60.12936863],"iteration":344,"passed_time":3.327097933,"remaining_time":6.316664191},
{"learn":[60.0864412],"iteration":345,"passed_time":3.335929098,"remaining_time":6.305484481},
{"learn":[60.05696706],"iteration":346,"passed_time":3.344918446,"remaining_time":6.294615981},
{"learn":[60.01332984],"iteration":347,"passed_time":3.354083484,"remaining_time":6.284087447},
{"learn":[59.9771936],"iteration":348,"passed_time":3.363628185,"remaining_time":6.274274924},
{"learn":[59.91771129],"iteration":349,"passed_time":3.372943919,"remaining_time":6.264038707},
{"learn":[59.88962487],"iteration":350,"passed_time":3.38141769,"remaining_time":6.252250942},
{"learn":[59.84188598],"iteration":351,"passed_time":3.391072027,"remaining_time":6.242655323},
{"learn":[59.79923638],"iteration":352,"passed_time":3.399807015,"remaining_time":6.23137433},
{"learn":[59.75867903],"iteration":353,"passed_time":3.409573099,"remaining_time":6.221989328},
{"learn":[59.71426971],"iteration":354,"passed_time":3.418242964,"remaining_time":6.210610456},
{"learn":[59.67550275],"iteration":355,"passed_time":3.427730101,"remaining_time":6.200725239},
{"learn":[59.63288614],"iteration":356,"passed_time":3.436219672,"remaining_time":6.189045516},
{"learn":[59.60510897],"iteration":357,"passed_time":3.445990491,"remaining_time":6.179681271},
{"learn":[59.5738847],"iteration":358,"passed_time":3.456232528,"remaining_time":6.17115613},
{"learn":[59.52283405],"iteration":359,"passed_time":3.466915055,"remaining_time":6.163404543},
{"learn":[59.49236685],"iteration":360,"passed_time":3.475445575,"remaining_time":6.151827487},
{"learn":[59.45940718],"iteration":361,"passed_time":3.485081351,"remaining_time":6.142215198},
{"learn":[59.42490805],"iteration":362,"passed_time":3.494138398,"remaining_time":6.131587216},
{"learn":[59.38912997],"iteration":363,"passed_time":3.503791963,"remaining_time":6.122010133},
{"learn":[59.36055265],"iteration":364,"passed_time":3.513637814,"remaining_time":6.112767156},
{"learn":[59.30588454],"iteration":365,"passed_time":3.523183704,"remaining_time":6.10300128},
{"learn":[59.26631371],"iteration":366,"passed_time":3.531971355,"remaining_time":6.091928795},
{"learn":[59.22311224],"iteration":367,"passed_time":3.540713006,"remaining_time":6.080789727},
{"learn":[59.19041053],"iteration":368,"passed_time":3.549940403,"remaining_time":6.070494293},
{"learn":[59.15066491],"iteration":369,"passed_time":3.559486261,"remaining_time":6.060746878},
{"learn":[59.12161824],"iteration":370,"passed_time":3.568889479,"remaining_time":6.050758712},
{"learn":[59.08633708],"iteration":371,"passed_time":3.577468588,"remaining_time":6.039382455},
{"learn":[59.03366191],"iteration":372,"passed_time":3.58704966,"remaining_time":6.02970546},
{"learn":[58.98704921],"iteration":373,"passed_time":3.595627886,"remaining_time":6.018350419},
{"learn":[58.94329549],"iteration":374,"passed_time":3.60529643,"remaining_time":6.008827383},
{"learn":[58.88695966],"iteration":375,"passed_time":3.614567123,"remaining_time":5.99864331},
{"learn":[58.83780596],"iteration":376,"passed_time":3.624662137,"remaining_time":5.98982629},
{"learn":[58.81121578],"iteration":377,"passed_time":3.634270414,"remaining_time":5.980201581},
{"learn":[58.7816681],"iteration":378,"passed_time":3.644572767,"remaining_time":5.971714217},
{"learn":[58.76029511],"iteration":379,"passed_time":3.654468183,"remaining_time":5.962553351},
{"learn":[58.70061866],"iteration":380,"passed_time":3.663842637,"remaining_time":5.952542237},
{"learn":[58.66915986],"iteration":381,"passed_time":3.672407282,"remaining_time":5.941224346},
{"learn":[58.63359218],"iteration":382,"passed_time":3.682120465,"remaining_time":5.931771089},
{"learn":[58.60110643],"iteration":383,"passed_time":3.690137724,"remaining_time":5.919595932},
{"learn":[58.54141961],"iteration":384,"passed_time":3.699859983,"remaining_time":5.910165946},
{"learn":[58.50600061],"iteration":385,"passed_time":3.708592168,"remaining_time":5.899159563},
{"learn":[58.4546929],"iteration":386,"passed_time":3.718191904,"remaining_time":5.889539114},
{"learn":[58.42568812],"iteration":387,"passed_time":3.727138779,"remaining_time":5.878889002},
{"learn":[58.38614001],"iteration":388,"passed_time":3.736280464,"remaining_time":5.868553633},
{"learn":[58.36008246],"iteration":389,"passed_time":3.745972909,"remaining_time":5.859085833},
{"learn":[58.32283836],"iteration":390,"passed_time":3.756876392,"remaining_time":5.851503127},
{"learn":[58.29603284],"iteration":391,"passed_time":3.766110605,"remaining_time":5.841314408},
{"learn":[58.23319049],"iteration":392,"passed_time":3.774611947,"remaining_time":5.829998605},
{"learn":[58.19979081],"iteration":393,"passed_time":3.783862397,"remaining_time":5.819849271},
{"learn":[58.16881364],"iteration":394,"passed_time":3.793143575,"remaining_time":5.809751552},
{"learn":[58.13458691],"iteration":395,"passed_time":3.80271373,"remaining_time":5.800098719},
{"learn":[58.10019735],"iteration":396,"passed_time":3.811901306,"remaining_time":5.789865208},
{"learn":[58.0688963],"iteration":397,"passed_time":3.82031369,"remaining_time":5.778464426},
{"learn":[58.03636005],"iteration":398,"passed_time":3.828081541,"remaining_time":5.766107785},
{"learn":[58.00453523],"iteration":399,"passed_time":3.837378901,"remaining_time":5.756068352},
{"learn":[57.94788745],"iteration":400,"passed_time":3.847992636,"remaining_time":5.747998975},
{"learn":[57.92370364],"iteration":401,"passed_time":3.858092728,"remaining_time":5.739152863},
{"learn":[57.87226249],"iteration":402,"passed_time":3.86798667,"remaining_time":5.729995141},
{"learn":[57.84838701],"iteration":403,"passed_time":3.878348585,"remaining_time":5.72152415},
{"learn":[57.82791481],"iteration":404,"passed_time":3.88743993,"remaining_time":5.711177182},
{"learn":[57.80327064],"iteration":405,"passed_time":3.89742627,"remaining_time":5.702145824},
{"learn":[57.78208258],"iteration":406,"passed_time":3.907207519,"remaining_time":5.692810955},
{"learn":[57.74496793],"iteration":407,"passed_time":3.918299817,"remaining_time":5.685376206},
{"learn":[57.70101379],"iteration":408,"passed_time":3.927470758,"remaining_time":5.675147232},
{"learn":[57.64906546],"iteration":409,"passed_time":3.937345263,"remaining_time":5.665935866},
{"learn":[57.62472265],"iteration":410,"passed_time":3.947816274,"remaining_time":5.65757612},
{"learn":[57.58783124],"iteration":411,"passed_time":3.956534999,"remaining_time":5.64670529},
{"learn":[57.56462531],"iteration":412,"passed_time":3.965310524,"remaining_time":5.635925612},
{"learn":[57.52457632],"iteration":413,"passed_time":3.974005148,"remaining_time":5.625041104},
{"learn":[57.49744371],"iteration":414,"passed_time":3.981890707,"remaining_time":5.613026659},
{"learn":[57.45670179],"iteration":415,"passed_time":3.991588355,"remaining_time":5.60357596},
{"learn":[57.43446666],"iteration":416,"passed_time":4.000513551,"remaining_time":5.593044125},
{"learn":[57.39567018],"iteration":417,"passed_time":4.010132671,"remaining_time":5.583486159},
{"learn":[57.36479926],"iteration":418,"passed_time":4.018612405,"remaining_time":5.572347989},
{"learn":[57.33245349],"iteration":419,"passed_time":4.028168657,"remaining_time":5.562709097},
{"learn":[57.31346469],"iteration":420,"passed_time":4.037348056,"remaining_time":5.552552315},
{"learn":[57.27234047],"iteration":421,"passed_time":4.048611199,"remaining_time":5.545254202},
{"learn":[57.24995003],"iteration":422,"passed_time":4.057785626,"remaining_time":5.535088194},
{"learn":[57.22593491],"iteration":423,"passed_time":4.066893353,"remaining_time":5.524836253},
{"learn":[57.19478828],"iteration":424,"passed_time":4.075868295,"remaining_time":5.514410046},
{"learn":[57.1700201],"iteration":425,"passed_time":4.085093378,"remaining_time":5.504327697},
{"learn":[57.14332],"iteration":426,"passed_time":4.0944931,"remaining_time":5.494483715},
{"learn":[57.10968109],"iteration":427,"passed_time":4.103848594,"remaining_time":5.4845827},
{"learn":[57.0750584],"iteration":428,"passed_time":4.114174671,"remaining_time":5.475976077},
{"learn":[57.041893],"iteration":429,"passed_time":4.130818729,"remaining_time":5.475736455},
{"learn":[56.99419721],"iteration":430,"passed_time":4.141825296,"remaining_time":5.467978175},
{"learn":[56.97000216],"iteration":431,"passed_time":4.152378988,"remaining_time":5.45960941},
{"learn":[56.94748305],"iteration":432,"passed_time":4.161553636,"remaining_time":5.449424738},
{"learn":[56.91662789],"iteration":433,"passed_time":4.173033225,"remaining_time":5.442250704},
{"learn":[56.88854645],"iteration":434,"passed_time":4.183668749,"remaining_time":5.433960559},
{"learn":[56.84280678],"iteration":435,"passed_time":4.193627032,"remaining_time":5.424783592},
{"learn":[56.79336849],"iteration":436,"passed_time":4.203166867,"remaining_time":5.415063949},
{"learn":[56.74761892],"iteration":437,"passed_time":4.213803415,"remaining_time":5.406752327},
{"learn":[56.71729873],"iteration":438,"passed_time":4.223676356,"remaining_time":5.397454295},
{"learn":[56.68861476],"iteration":439,"passed_time":4.234772956,"remaining_time":5.389711035},
{"learn":[56.64737548],"iteration":440,"passed_time":4.244924181,"remaining_time":5.380754234},
{"learn":[56.59691214],"iteration":441,"passed_time":4.25413247,"remaining_time":5.370601625},
{"learn":[56.57501816],"iteration":442,"passed_time":4.263642057,"remaining_time":5.360832112},
{"learn":[56.53560244],"iteration":443,"passed_time":4.272911469,"remaining_time":5.35076301},
{"learn":[56.50331901],"iteration":444,"passed_time":4.283349912,"remaining_time":5.342155508},
{"learn":[56.47935851],"iteration":445,"passed_time":4.293112827,"remaining_time":5.332700687},
{"learn":[56.44734308],"iteration":446,"passed_time":4.302387789,"remaining_time":5.322640822},
{"learn":[56.42834642],"iteration":447,"passed_time":4.312571812,"remaining_time":5.313704554},
{"learn":[56.39788334],"iteration":448,"passed_time":4.322129611,"remaining_time":5.303994244},
{"learn":[56.35577169],"iteration":449,"passed_time":4.332605165,"remaining_time":5.295406313},
{"learn":[56.32584227],"iteration":450,"passed_time":4.342171432,"remaining_time":5.28570314},
{"learn":[56.31763846],"iteration":451,"passed_time":4.352168318,"remaining_time":5.276522651},
{"learn":[56.27731167],"iteration":452,"passed_time":4.361525235,"remaining_time":5.266565792},
{"learn":[56.24917777],"iteration":453,"passed_time":4.371581148,"remaining_time":5.257452217},
{"learn":[56.22768593],"iteration":454,"passed_time":4.38185939,"remaining_time":5.248600808},
{"learn":[56.18298663],"iteration":455,"passed_time":4.392032181,"remaining_time":5.239617339},
{"learn":[56.15505424],"iteration":456,"passed_time":4.402397032,"remaining_time":5.230856868},
{"learn":[56.11687084],"iteration":457,"passed_time":4.411514102,"remaining_time":5.220612758},
{"learn":[56.09789599],"iteration":458,"passed_time":4.421276663,"remaining_time":5.211134368},
{"learn":[56.05768639],"iteration":459,"passed_time":4.431939708,"remaining_time":5.202711832},
{"learn":[56.02225067],"iteration":460,"passed_time":4.441704257,"remaining_time":5.193229055},
{"learn":[55.98948467],"iteration":461,"passed_time":4.452727816,"remaining_time":5.185211179},
{"learn":[55.97093941],"iteration":462,"passed_time":4.462098172,"remaining_time":5.17526289},
{"learn":[55.91823285],"iteration":463,"passed_time":4.47167487,"remaining_time":5.165555453},
{"learn":[55.89397052],"iteration":464,"passed_time":4.481961191,"remaining_time":5.156665026},
{"learn":[55.85462374],"iteration":465,"passed_time":4.491066608,"remaining_time":5.146415384},
{"learn":[55.83088042],"iteration":466,"passed_time":4.499452145,"remaining_time":5.135349022},
{"learn":[55.79053878],"iteration":467,"passed_time":4.508944404,"remaining_time":5.125552185},
{"learn":[55.75552812],"iteration":468,"passed_time":4.517265746,"remaining_time":5.11443094},
{"learn":[55.71439634],"iteration":469,"passed_time":4.52742582,"remaining_time":5.105395074},
{"learn":[55.6878982],"iteration":470,"passed_time":4.536776112,"remaining_time":5.095444932},
{"learn":[55.64378549],"iteration":471,"passed_time":4.54746143,"remaining_time":5.086990753},
{"learn":[55.61334753],"iteration":472,"passed_time":4.556376961,"remaining_time":5.076555304},
{"learn":[55.59435052],"iteration":473,"passed_time":4.565046512,"remaining_time":5.065853302},
{"learn":[55.5390048],"iteration":474,"passed_time":4.575097146,"remaining_time":5.056686319},
{"learn":[55.48281131],"iteration":475,"passed_time":4.584648726,"remaining_time":5.046966244},
{"learn":[55.45704047],"iteration":476,"passed_time":4.593312143,"remaining_time":5.036273062},
{"learn":[55.42830171],"iteration":477,"passed_time":4.602630447,"remaining_time":5.026303543},
{"learn":[55.38907409],"iteration":478,"passed_time":4.611262369,"remaining_time":5.015590176},
{"learn":[55.35272671],"iteration":479,"passed_time":4.621185174,"remaining_time":5.006283939},
{"learn":[55.32686325],"iteration":480,"passed_time":4.629240173,"remaining_time":4.994959771},
{"learn":[55.29509037],"iteration":481,"passed_time":4.639296482,"remaining_time":4.985799954},
{"learn":[55.26167661],"iteration":482,"passed_time":4.649217979,"remaining_time":4.976492122},
{"learn":[55.21585261],"iteration":483,"passed_time":4.658987856,"remaining_time":4.967020111},
{"learn":[55.1893706],"iteration":484,"passed_time":4.66760893,"remaining_time":4.956327008},
{"learn":[55.16261387],"iteration":485,"passed_time":4.677320598,"remaining_time":4.946795859},
{"learn":[55.13511313],"iteration":486,"passed_time":4.686271291,"remaining_time":4.936462366},
{"learn":[55.10103308],"iteration":487,"passed_time":4.695187305,"remaining_time":4.926098156},
{"learn":[55.08404038],"iteration":488,"passed_time":4.704531639,"remaining_time":4.916187459},
{"learn":[55.05824288],"iteration":489,"passed_time":4.714070403,"remaining_time":4.906481439},
{"learn":[55.01942577],"iteration":490,"passed_time":4.723263919,"remaining_time":4.896418197},
{"learn":[54.99574197],"iteration":491,"passed_time":4.732028387,"remaining_time":4.885915489},
{"learn":[54.95074051],"iteration":492,"passed_time":4.740909321,"remaining_time":4.875539606},
{"learn":[54.92073886],"iteration":493,"passed_time":4.749050669,"remaining_time":4.864412223},
{"learn":[54.89480823],"iteration":494,"passed_time":4.758337394,"remaining_time":4.854465422},
{"learn":[54.87305651],"iteration":495,"passed_time":4.7674617,"remaining_time":4.844356244},
{"learn":[54.85456234],"iteration":496,"passed_time":4.777922094,"remaining_time":4.835603246},
{"learn":[54.825536],"iteration":497,"passed_time":4.787541705,"remaining_time":4.825995855},
{"learn":[54.78727588],"iteration":498,"passed_time":4.797356288,"remaining_time":4.816584169},
{"learn":[54.76320285],"iteration":499,"passed_time":4.823237071,"remaining_time":4.823237071},
{"learn":[54.74484431],"iteration":500,"passed_time":4.834071456,"remaining_time":4.814773766},
{"learn":[54.70717771],"iteration":501,"passed_time":4.8446527,"remaining_time":4.80604989},
{"learn":[54.68213637],"iteration":502,"passed_time":4.855362708,"remaining_time":4.797445857},
{"learn":[54.65528223],"iteration":503,"passed_time":4.865501063,"remaining_time":4.788270887},
{"learn":[54.62567771],"iteration":504,"passed_time":4.874416704,"remaining_time":4.777893601},
{"learn":[54.59119902],"iteration":505,"passed_time":4.885099306,"remaining_time":4.769247148},
{"learn":[54.56706067],"iteration":506,"passed_time":4.89428155,"remaining_time":4.759133736},
{"learn":[54.54828494],"iteration":507,"passed_time":4.902878596,"remaining_time":4.748457223},
{"learn":[54.49784566],"iteration":508,"passed_time":4.91261369,"remaining_time":4.738886683},
{"learn":[54.45643442],"iteration":509,"passed_time":4.921677841,"remaining_time":4.728670867},
{"learn":[54.43631922],"iteration":510,"passed_time":4.931600547,"remaining_time":4.71928115},
{"learn":[54.40241371],"iteration":511,"passed_time":4.940164538,"remaining_time":4.708594325},
{"learn":[54.37605479],"iteration":512,"passed_time":4.949273846,"remaining_time":4.698433456},
{"learn":[54.35472397],"iteration":513,"passed_time":4.957875743,"remaining_time":4.687796909},
{"learn":[54.32670004],"iteration":514,"passed_time":4.967675828,"remaining_time":4.678296654},
{"learn":[54.30137483],"iteration":515,"passed_time":4.976411592,"remaining_time":4.66779692},
{"learn":[54.26199097],"iteration":516,"passed_time":4.984669098,"remaining_time":4.656857204},
{"learn":[54.21970419],"iteration":517,"passed_time":4.993864928,"remaining_time":4.646800956},
{"learn":[54.18847035],"iteration":518,"passed_time":5.002214173,"remaining_time":4.635963425},
{"learn":[54.1627157],"iteration":519,"passed_time":5.011913294,"remaining_time":4.626381502},
{"learn":[54.14437263],"iteration":520,"passed_time":5.02066421,"remaining_time":4.615927364},
{"learn":[54.11466472],"iteration":521,"passed_time":5.02993304,"remaining_time":4.60595401},
{"learn":[54.09441834],"iteration":522,"passed_time":5.039618228,"remaining_time":4.596363087},
{"learn":[54.05053623],"iteration":523,"passed_time":5.049294939,"remaining_time":4.586764105},
{"learn":[54.01022927],"iteration":524,"passed_time":5.058804029,"remaining_time":4.57701317},
{"learn":[53.9823909],"iteration":525,"passed_time":5.068631322,"remaining_time":4.567549899},
{"learn":[53.9432142],"iteration":526,"passed_time":5.077054514,"remaining_time":4.556825019},
{"learn":[53.919625],"iteration":527,"passed_time":5.086443455,"remaining_time":4.54697218},
{"learn":[53.90039084],"iteration":528,"passed_time":5.094899972,"remaining_time":4.536290901},
{"learn":[53.88162203],"iteration":529,"passed_time":5.104360645,"remaining_time":4.526508496},
{"learn":[53.83022779],"iteration":530,"passed_time":5.112936235,"remaining_time":4.515945563},
{"learn":[53.80865104],"iteration":531,"passed_time":5.121409767,"remaining_time":4.505300321},
{"learn":[53.7886994],"iteration":532,"passed_time":5.130514413,"remaining_time":4.495216193},
{"learn":[53.75843789],"iteration":533,"passed_time":5.138979504,"remaining_time":4.48457762},
{"learn":[53.7189175],"iteration":534,"passed_time":5.148834057,"remaining_time":4.475154835},
{"learn":[53.68253094],"iteration":535,"passed_time":5.157976621,"remaining_time":4.46511409},
{"learn":[53.65091128],"iteration":536,"passed_time":5.166823576,"remaining_time":4.454821817},
{"learn":[53.63288951],"iteration":537,"passed_time":5.176081075,"remaining_time":4.444887466},
{"learn":[53.60965866],"iteration":538,"passed_time":5.186016131,"remaining_time":4.435535132},
{"learn":[53.58237152],"iteration":539,"passed_time":5.195152862,"remaining_time":4.425500586},
{"learn":[53.55481349],"iteration":540,"passed_time":5.205518889,"remaining_time":4.416512329},
{"learn":[53.53259362],"iteration":541,"passed_time":5.213970129,"remaining_time":4.405900958},
{"learn":[53.51194795],"iteration":542,"passed_time":5.223517342,"remaining_time":4.396219936},
{"learn":[53.46362127],"iteration":543,"passed_time":5.23217469,"remaining_time":4.38579349},
{"learn":[53.42270647],"iteration":544,"passed_time":5.241472475,"remaining_time":4.375908213},
{"learn":[53.3877904],"iteration":545,"passed_time":5.250983119,"remaining_time":4.36620208},
{"learn":[53.3595863],"iteration":546,"passed_time":5.261047828,"remaining_time":4.356955514},
{"learn":[53.333046],"iteration":547,"passed_time":5.270212271,"remaining_time":4.346963406},
{"learn":[53.31148086],"iteration":548,"passed_time":5.280010306,"remaining_time":4.337494805},
{"learn":[53.28709711],"iteration":549,"passed_time":5.288301572,"remaining_time":4.326792196},
{"learn":[53.2639126],"iteration":550,"passed_time":5.297126466,"remaining_time":4.316533182},
{"learn":[53.23754213],"iteration":551,"passed_time":5.306279523,"remaining_time":4.3065457},
{"learn":[53.20818371],"iteration":552,"passed_time":5.315242507,"remaining_time":4.296407596},
{"learn":[53.17147637],"iteration":553,"passed_time":5.324498102,"remaining_time":4.286509302},
{"learn":[53.16060708],"iteration":554,"passed_time":5.333312523,"remaining_time":4.27625959},
{"learn":[53.12630665],"iteration":555,"passed_time":5.343087797,"remaining_time":4.266782341},
{"learn":[53.09767784],"iteration":556,"passed_time":5.352625085,"remaining_time":4.257114745},
{"learn":[53.06816211],"iteration":557,"passed_time":5.362548397,"remaining_time":4.24775339},
{"learn":[53.03533313],"iteration":558,"passed_time":5.371313846,"remaining_time":4.237476576},
{"learn":[53.00220081],"iteration":559,"passed_time":5.380141275,"remaining_time":4.227253859},
{"learn":[52.96937743],"iteration":560,"passed_time":5.389226094,"remaining_time":4.217237532},
{"learn":[52.93974305],"iteration":561,"passed_time":5.409018972,"remaining_time":4.215569946},
{"learn":[52.91012296],"iteration":562,"passed_time":5.425777147,"remaining_time":4.211482439},
{"learn":[52.88943087],"iteration":563,"passed_time":5.437368777,"remaining_time":4.203356005},
{"learn":[52.87352363],"iteration":564,"passed_time":5.448615062,"remaining_time":4.194951419},
{"learn":[52.85269852],"iteration":565,"passed_time":5.45954041,"remaining_time":4.186290703},
{"learn":[52.83017648],"iteration":566,"passed_time":5.470535035,"remaining_time":4.177674903},
{"learn":[52.7928429],"iteration":567,"passed_time":5.48100866,"remaining_time":4.168654474},
{"learn":[52.7736683],"iteration":568,"passed_time":5.491482008,"remaining_time":4.159628726},
{"learn":[52.73924764],"iteration":569,"passed_time":5.501719855,"remaining_time":4.150420241},
{"learn":[52.71537463],"iteration":570,"passed_time":5.511496015,"remaining_time":4.140861279},
{"learn":[52.69092785],"iteration":571,"passed_time":5.521678395,"remaining_time":4.131605512},
{"learn":[52.66429135],"iteration":572,"passed_time":5.532053511,"remaining_time":4.122490138},
{"learn":[52.63131595],"iteration":573,"passed_time":5.542377342,"remaining_time":4.113332313},
{"learn":[52.5933956],"iteration":574,"passed_time":5.552023513,"remaining_time":4.103669553},
{"learn":[52.55993718],"iteration":575,"passed_time":5.562580571,"remaining_time":4.094677364},
{"learn":[52.5393385],"iteration":576,"passed_time":5.57175141,"remaining_time":4.084663512},
{"learn":[52.5160406],"iteration":577,"passed_time":5.582063156,"remaining_time":4.075485557},
{"learn":[52.49462522],"iteration":578,"passed_time":5.59216944,"remaining_time":4.066154291},
{"learn":[52.47203033],"iteration":579,"passed_time":5.601881949,"remaining_time":4.056535204},
{"learn":[52.45280804],"iteration":580,"passed_time":5.610485566,"remaining_time":4.046116097},
{"learn":[52.42411489],"iteration":581,"passed_time":5.621342077,"remaining_time":4.037321286},
{"learn":[52.38902817],"iteration":582,"passed_time":5.630791835,"remaining_time":4.027513199},
{"learn":[52.3592598],"iteration":583,"passed_time":5.641564144,"remaining_time":4.018648432},
{"learn":[52.32317976],"iteration":584,"passed_time":5.65210552,"remaining_time":4.009613317},
{"learn":[52.30875979],"iteration":585,"passed_time":5.662165817,"remaining_time":4.000233188},
{"learn":[52.29994028],"iteration":586,"passed_time":5.671490185,"remaining_time":3.990332958},
{"learn":[52.28274389],"iteration":587,"passed_time":5.681228323,"remaining_time":3.980724607},
{"learn":[52.2631668],"iteration":588,"passed_time":5.6922827,"remaining_time":3.972034278},
{"learn":[52.23796413],"iteration":589,"passed_time":5.701874702,"remaining_time":3.962319708},
{"learn":[52.22559922],"iteration":590,"passed_time":5.71134425,"remaining_time":3.952520809},
{"learn":[52.20458992],"iteration":591,"passed_time":5.721853609,"remaining_time":3.94343965},
{"learn":[52.17995794],"iteration":592,"passed_time":5.730522598,"remaining_time":3.933090552},
{"learn":[52.15084537],"iteration":593,"passed_time":5.74085531,"remaining_time":3.923884269},
{"learn":[52.11834012],"iteration":594,"passed_time":5.750607822,"remaining_time":3.914279274},
{"learn":[52.08621182],"iteration":595,"passed_time":5.760888969,"remaining_time":3.90503212},
{"learn":[52.05737397],"iteration":596,"passed_time":5.769921268,"remaining_time":3.894938478},
{"learn":[52.0364238],"iteration":597,"passed_time":5.780859023,"remaining_time":3.88612931},
{"learn":[52.01335584],"iteration":598,"passed_time":5.789765753,"remaining_time":3.875953367},
{"learn":[51.98642723],"iteration":599,"passed_time":5.799902948,"remaining_time":3.866601965},
{"learn":[51.96386752],"iteration":600,"passed_time":5.809695601,"remaining_time":3.857019209},
{"learn":[51.93610799],"iteration":601,"passed_time":5.818921038,"remaining_time":3.847060753},
{"learn":[51.91532966],"iteration":602,"passed_time":5.829352013,"remaining_time":3.837898423},
{"learn":[51.87496292],"iteration":603,"passed_time":5.839575031,"remaining_time":3.82859555},
{"learn":[51.85194726],"iteration":604,"passed_time":5.849991773,"remaining_time":3.819416116},
{"learn":[51.81295588],"iteration":605,"passed_time":5.859928264,"remaining_time":3.809920357},
{"learn":[51.78950396],"iteration":606,"passed_time":5.870210166,"remaining_time":3.800646779},
{"learn":[51.75483381],"iteration":607,"passed_time":5.880395287,"remaining_time":3.791307488},
{"learn":[51.73340178],"iteration":608,"passed_time":5.890605768,"remaining_time":3.7819817},
{"learn":[51.70643149],"iteration":609,"passed_time":5.899749152,"remaining_time":3.771970769},
{"learn":[51.67209976],"iteration":610,"passed_time":5.909826574,"remaining_time":3.762557344},
{"learn":[51.64370233],"iteration":611,"passed_time":5.919098992,"remaining_time":3.752631387},
{"learn":[51.61847508],"iteration":612,"passed_time":5.928872519,"remaining_time":3.743023923},
{"learn":[51.58918222],"iteration":613,"passed_time":5.937893504,"remaining_time":3.732942822},
{"learn":[51.56802479],"iteration":614,"passed_time":5.946881846,"remaining_time":3.722844733},
{"learn":[51.54450791],"iteration":615,"passed_time":5.95680597,"remaining_time":3.713333592},
{"learn":[51.5188756],"iteration":616,"passed_time":5.966176679,"remaining_time":3.703477582},
{"learn":[51.49331354],"iteration":617,"passed_time":5.975209631,"remaining_time":3.693414368},
{"learn":[51.45923888],"iteration":618,"passed_time":5.985505478,"remaining_time":3.684131805},
{"learn":[51.44021955],"iteration":619,"passed_time":5.994086634,"remaining_time":3.673795034},
{"learn":[51.423338],"iteration":620,"passed_time":6.003105281,"remaining_time":3.66373092},
{"learn":[51.384962],"iteration":621,"passed_time":6.011820242,"remaining_time":3.653485613},
{"learn":[51.36050975],"iteration":622,"passed_time":6.020477607,"remaining_time":3.643210366},
{"learn":[51.33963016],"iteration":623,"passed_time":6.029260508,"remaining_time":3.633015947},
{"learn":[51.32451771],"iteration":624,"passed_time":6.037553782,"remaining_time":3.622532269},
{"learn":[51.28129468],"iteration":625,"passed_time":6.04758205,"remaining_time":3.613092151},
{"learn":[51.24848809],"iteration":626,"passed_time":6.056107218,"remaining_time":3.602755969},
{"learn":[51.22104368],"iteration":627,"passed_time":6.065760158,"remaining_time":3.593093597},
{"learn":[51.19793114],"iteration":628,"passed_time":6.074318569,"remaining_time":3.582785674},
{"learn":[51.17827855],"iteration":629,"passed_time":6.084851145,"remaining_time":3.573642736},
{"learn":[51.15768578],"iteration":630,"passed_time":6.093658765,"remaining_time":3.563486663},
{"learn":[51.13841377],"iteration":631,"passed_time":6.102829955,"remaining_time":3.553546556},
{"learn":[51.11797158],"iteration":632,"passed_time":6.11182611,"remaining_time":3.543507397},
{"learn":[51.09967421],"iteration":633,"passed_time":6.121443133,"remaining_time":3.533829947},
{"learn":[51.0780497],"iteration":634,"passed_time":6.130428518,"remaining_time":3.52378962},
{"learn":[51.05762447],"iteration":635,"passed_time":6.139879716,"remaining_time":3.514019209},
{"learn":[51.04276577],"iteration":636,"passed_time":6.148152756,"remaining_time":3.503578415},
{"learn":[51.02427007],"iteration":637,"passed_time":6.157172566,"remaining_time":3.493568133},
{"learn":[50.99827169],"iteration":638,"passed_time":6.165767585,"remaining_time":3.483320967},
{"learn":[50.97684436],"iteration":639,"passed_time":6.175133763,"remaining_time":3.473512742},
{"learn":[50.95038769],"iteration":640,"passed_time":6.184365753,"remaining_time":3.463630741},
{"learn":[50.92713583],"iteration":641,"passed_time":6.19320133,"remaining_time":3.453529713},
{"learn":[50.90373285],"iteration":642,"passed_time":6.202491845,"remaining_time":3.443685208},
{"learn":[50.87994169],"iteration":643,"passed_time":6.211017795,"remaining_time":3.433419775},
{"learn":[50.83839227],"iteration":644,"passed_time":6.2209277,"remaining_time":3.423921447},
{"learn":[50.82051172],"iteration":645,"passed_time":6.229286599,"remaining_time":3.413571913},
{"learn":[50.80544143],"iteration":646,"passed_time":6.238453818,"remaining_time":3.403669549},
{"learn":[50.78907068],"iteration":647,"passed_time":6.247604342,"remaining_time":3.393760383},
{"learn":[50.76232802],"iteration":648,"passed_time":6.256746914,"remaining_time":3.383849256},
{"learn":[50.74314161],"iteration":649,"passed_time":6.267395665,"remaining_time":3.374751512},
{"learn":[50.71665679],"iteration":650,"passed_time":6.276085606,"remaining_time":3.364598889},
{"learn":[50.69368443],"iteration":651,"passed_time":6.285846149,"remaining_time":3.355022177},
{"learn":[50.67268887],"iteration":652,"passed_time":6.295706874,"remaining_time":3.34549814},
{"learn":[50.66217802],"iteration":653,"passed_time":6.304326578,"remaining_time":3.335316508},
{"learn":[50.62768955],"iteration":654,"passed_time":6.314440376,"remaining_time":3.325926611},
{"learn":[50.59728075],"iteration":655,"passed_time":6.324227209,"remaining_time":3.316363049},
{"learn":[50.5842725],"iteration":656,"passed_time":6.333433014,"remaining_time":3.30649547},
{"learn":[50.57011558],"iteration":657,"passed_time":6.342706769,"remaining_time":3.29666522},
{"learn":[50.56007004],"iteration":658,"passed_time":6.351181029,"remaining_time":3.28642296},
{"learn":[50.54001357],"iteration":659,"passed_time":6.36059453,"remaining_time":3.276669909},
{"learn":[50.51687527],"iteration":660,"passed_time":6.370498298,"remaining_time":3.267169324},
{"learn":[50.4904873],"iteration":661,"passed_time":6.380763761,"remaining_time":3.257852192},
{"learn":[50.47741331],"iteration":662,"passed_time":6.390829218,"remaining_time":3.248430538},
{"learn":[50.45629532],"iteration":663,"passed_time":6.400354291,"remaining_time":3.238733497},
{"learn":[50.41753964],"iteration":664,"passed_time":6.409054087,"remaining_time":3.228621232},
{"learn":[50.39981224],"iteration":665,"passed_time":6.418647172,"remaining_time":3.218961194},
{"learn":[50.37551411],"iteration":666,"passed_time":6.427017212,"remaining_time":3.208690752},
{"learn":[50.36485512],"iteration":667,"passed_time":6.435821557,"remaining_time":3.198641852},
{"learn":[50.35227096],"iteration":668,"passed_time":6.446616023,"remaining_time":3.189581321},
{"learn":[50.32554964],"iteration":669,"passed_time":6.455893793,"remaining_time":3.179768585},
{"learn":[50.30503927],"iteration":670,"passed_time":6.466132955,"remaining_time":3.170428826},
{"learn":[50.29002876],"iteration":671,"passed_time":6.475354178,"remaining_time":3.160589539},
{"learn":[50.26194432],"iteration":672,"passed_time":6.483878658,"remaining_time":3.150413553},
{"learn":[50.23906748],"iteration":673,"passed_time":6.493373523,"remaining_time":3.140711823},
{"learn":[50.22364799],"iteration":674,"passed_time":6.501711147,"remaining_time":3.130453515},
{"learn":[50.20314226],"iteration":675,"passed_time":6.511047085,"remaining_time":3.120679372},
{"learn":[50.17928504],"iteration":676,"passed_time":6.521183277,"remaining_time":3.111288329},
{"learn":[50.14927018],"iteration":677,"passed_time":6.531315565,"remaining_time":3.101893233},
{"learn":[50.12342176],"iteration":678,"passed_time":6.539972514,"remaining_time":3.091798493},
{"learn":[50.10554387],"iteration":679,"passed_time":6.548872143,"remaining_time":3.081822185},
{"learn":[50.08603943],"iteration":680,"passed_time":6.557650719,"remaining_time":3.071792334},
{"learn":[50.05830718],"iteration":681,"passed_time":6.567086654,"remaining_time":3.062072663},
{"learn":[50.02606178],"iteration":682,"passed_time":6.57665426,"remaining_time":3.052414935},
{"learn":[49.99772081],"iteration":683,"passed_time":6.58553195,"remaining_time":3.042438737},
{"learn":[49.98755438],"iteration":684,"passed_time":6.594970325,"remaining_time":3.03272358},
{"learn":[49.96420435],"iteration":685,"passed_time":6.603414087,"remaining_time":3.02255397},
{"learn":[49.95482242],"iteration":686,"passed_time":6.61301628,"remaining_time":3.01291717},
{"learn":[49.93368939],"iteration":687,"passed_time":6.6214509,"remaining_time":3.00275099},
{"learn":[49.89809354],"iteration":688,"passed_time":6.630923796,"remaining_time":2.993058492},
{"learn":[49.8737202],"iteration":689,"passed_time":6.639322936,"remaining_time":2.982884218},
{"learn":[49.84840773],"iteration":690,"passed_time":6.649400624,"remaining_time":2.973465692},
{"learn":[49.82118831],"iteration":691,"passed_time":6.658189948,"remaining_time":2.963471827},
{"learn":[49.8012872],"iteration":692,"passed_time":6.668457087,"remaining_time":2.954136112},
{"learn":[49.77180019],"iteration":693,"passed_time":6.689516793,"remaining_time":2.949556396},
{"learn":[49.75121518],"iteration":694,"passed_time":6.702737161,"remaining_time":2.94148897},
{"learn":[49.72346087],"iteration":695,"passed_time":6.713667596,"remaining_time":2.932406536},
{"learn":[49.69691677],"iteration":696,"passed_time":6.725327608,"remaining_time":2.923635961},
{"learn":[49.65148878],"iteration":697,"passed_time":6.736425933,"remaining_time":2.914614085},
{"learn":[49.62970822],"iteration":698,"passed_time":6.748489443,"remaining_time":2.906001892},
{"learn":[49.61268555],"iteration":699,"passed_time":6.75939493,"remaining_time":2.896883541},
{"learn":[49.6004779],"iteration":700,"passed_time":6.768749651,"remaining_time":2.887098639},
{"learn":[49.56875072],"iteration":701,"passed_time":6.780555488,"remaining_time":2.878355464},
{"learn":[49.54382198],"iteration":702,"passed_time":6.78981825,"remaining_time":2.86852919},
{"learn":[49.51242293],"iteration":703,"passed_time":6.800243156,"remaining_time":2.859193145},
{"learn":[49.47927583],"iteration":704,"passed_time":6.810771539,"remaining_time":2.849897311},
{"learn":[49.46055648],"iteration":705,"passed_time":6.821136219,"remaining_time":2.840529813},
{"learn":[49.43350318],"iteration":706,"passed_time":6.830385824,"remaining_time":2.830697378},
{"learn":[49.42071016],"iteration":707,"passed_time":6.841600354,"remaining_time":2.821676982},
{"learn":[49.40441272],"iteration":708,"passed_time":6.851273321,"remaining_time":2.812017682},
{"learn":[49.39556261],"iteration":709,"passed_time":6.861187349,"remaining_time":2.802456804},
{"learn":[49.37280686],"iteration":710,"passed_time":6.87058998,"remaining_time":2.792687066},
{"learn":[49.35244123],"iteration":711,"passed_time":6.881128005,"remaining_time":2.78337762},
{"learn":[49.33380462],"iteration":712,"passed_time":6.890790878,"remaining_time":2.773712457},
{"learn":[49.29444774],"iteration":713,"passed_time":6.900297839,"remaining_time":2.763984849},
{"learn":[49.2674816],"iteration":714,"passed_time":6.910787483,"remaining_time":2.754649556},
{"learn":[49.24828509],"iteration":715,"passed_time":6.919782383,"remaining_time":2.744718152},
{"learn":[49.22031855],"iteration":716,"passed_time":6.928567735,"remaining_time":2.734706651},
{"learn":[49.20422199],"iteration":717,"passed_time":6.938577646,"remaining_time":2.725179521},
{"learn":[49.18808162],"iteration":718,"passed_time":6.947871337,"remaining_time":2.715371135},
{"learn":[49.16254019],"iteration":719,"passed_time":6.958693111,"remaining_time":2.706158432},
{"learn":[49.14950676],"iteration":720,"passed_time":6.968256124,"remaining_time":2.696454173},
{"learn":[49.12545776],"iteration":721,"passed_time":6.978500167,"remaining_time":2.68701253},
{"learn":[49.09693537],"iteration":722,"passed_time":6.988175071,"remaining_time":2.677350615},
{"learn":[49.08378925],"iteration":723,"passed_time":6.998490069,"remaining_time":2.667932678},
{"learn":[49.06118119],"iteration":724,"passed_time":7.008670339,"remaining_time":2.658461163},
{"learn":[49.03348502],"iteration":725,"passed_time":7.019369167,"remaining_time":2.649183405},
{"learn":[49.02322099],"iteration":726,"passed_time":7.028335193,"remaining_time":2.639251042},
{"learn":[49.00705268],"iteration":727,"passed_time":7.038849908,"remaining_time":2.629899966},
{"learn":[48.99035675],"iteration":728,"passed_time":7.047658569,"remaining_time":2.619911484},
{"learn":[48.97406487],"iteration":729,"passed_time":7.056994771,"remaining_time":2.610121354},
{"learn":[48.94575588],"iteration":730,"passed_time":7.065934484,"remaining_time":2.600186561},
{"learn":[48.92763104],"iteration":731,"passed_time":7.075109627,"remaining_time":2.590340683},
{"learn":[48.91043586],"iteration":732,"passed_time":7.083612996,"remaining_time":2.580251937},
{"learn":[48.88492045],"iteration":733,"passed_time":7.09343359,"remaining_time":2.57064487},
{"learn":[48.85208537],"iteration":734,"passed_time":7.10304818,"remaining_time":2.560962949},
{"learn":[48.81355582],"iteration":735,"passed_time":7.112613454,"remaining_time":2.551263522},
{"learn":[48.79306904],"iteration":736,"passed_time":7.12099844,"remaining_time":2.54114327},
{"learn":[48.77997357],"iteration":737,"passed_time":7.131107521,"remaining_time":2.531639797},
{"learn":[48.74175986],"iteration":738,"passed_time":7.140052232,"remaining_time":2.521723454},
{"learn":[48.72645067],"iteration":739,"passed_time":7.150447772,"remaining_time":2.512319487},
{"learn":[48.69804802],"iteration":740,"passed_time":7.16072733,"remaining_time":2.502872306},
{"learn":[48.67460389],"iteration":741,"passed_time":7.169953649,"remaining_time":2.49305666},
{"learn":[48.65455728],"iteration":742,"passed_time":7.179228842,"remaining_time":2.483259505},
{"learn":[48.64001535],"iteration":743,"passed_time":7.18796267,"remaining_time":2.473277478},
{"learn":[48.61424485],"iteration":744,"passed_time":7.197188098,"remaining_time":2.463467067},
{"learn":[48.59758789],"iteration":745,"passed_time":7.206948081,"remaining_time":2.453840231},
{"learn":[48.57013322],"iteration":746,"passed_time":7.216011616,"remaining_time":2.44397716},
{"learn":[48.55601373],"iteration":747,"passed_time":7.225309415,"remaining_time":2.43419515},
{"learn":[48.53887125],"iteration":748,"passed_time":7.234667335,"remaining_time":2.424434581},
{"learn":[48.50097232],"iteration":749,"passed_time":7.244387647,"remaining_time":2.414795882},
{"learn":[48.48785999],"iteration":750,"passed_time":7.254234321,"remaining_time":2.405198863},
{"learn":[48.47413606],"iteration":751,"passed_time":7.263252195,"remaining_time":2.395327852},
{"learn":[48.4516337],"iteration":752,"passed_time":7.271880125,"remaining_time":2.385331196},
{"learn":[48.44336208],"iteration":753,"passed_time":7.280684895,"remaining_time":2.375395868},
{"learn":[48.43643867],"iteration":754,"passed_time":7.289912158,"remaining_time":2.365600634},
{"learn":[48.42011309],"iteration":755,"passed_time":7.299514453,"remaining_time":2.355927945},
{"learn":[48.39378889],"iteration":756,"passed_time":7.309340254,"remaining_time":2.346327189},
{"learn":[48.38296236],"iteration":757,"passed_time":7.318313399,"remaining_time":2.336453618},
{"learn":[48.35603162],"iteration":758,"passed_time":7.329157815,"remaining_time":2.327176592},
{"learn":[48.35054521],"iteration":759,"passed_time":7.337386662,"remaining_time":2.317069472},
{"learn":[48.32775858],"iteration":760,"passed_time":7.34730581,"remaining_time":2.307498145},
{"learn":[48.30187955],"iteration":761,"passed_time":7.355798137,"remaining_time":2.297480258},
{"learn":[48.2859145],"iteration":762,"passed_time":7.364364953,"remaining_time":2.287489507},
{"learn":[48.26663147],"iteration":763,"passed_time":7.374773369,"remaining_time":2.278071355},
{"learn":[48.24998094],"iteration":764,"passed_time":7.384495893,"remaining_time":2.268439915},
{"learn":[48.2271178],"iteration":765,"passed_time":7.394241343,"remaining_time":2.258815241},
{"learn":[48.21706877],"iteration":766,"passed_time":7.40380705,"remaining_time":2.249135649},
{"learn":[48.19909139],"iteration":767,"passed_time":7.412519348,"remaining_time":2.239198553},
{"learn":[48.17828001],"iteration":768,"passed_time":7.422446767,"remaining_time":2.229629653},
{"learn":[48.15177165],"iteration":769,"passed_time":7.430889016,"remaining_time":2.2196162},
{"learn":[48.13024476],"iteration":770,"passed_time":7.440727484,"remaining_time":2.210021522},
{"learn":[48.10362892],"iteration":771,"passed_time":7.450922844,"remaining_time":2.200531617},
{"learn":[48.09428204],"iteration":772,"passed_time":7.460517055,"remaining_time":2.190863352},
{"learn":[48.07913573],"iteration":773,"passed_time":7.468939533,"remaining_time":2.180853145},
{"learn":[48.0547746],"iteration":774,"passed_time":7.477717661,"remaining_time":2.170950289},
{"learn":[48.03322102],"iteration":775,"passed_time":7.486620148,"remaining_time":2.161086228},
{"learn":[48.02260596],"iteration":776,"passed_time":7.496277315,"remaining_time":2.151441237},
{"learn":[48.00417519],"iteration":777,"passed_time":7.50500634,"remaining_time":2.141531372},
{"learn":[47.98727195],"iteration":778,"passed_time":7.513928966,"remaining_time":2.131679463},
{"learn":[47.96476878],"iteration":779,"passed_time":7.523940956,"remaining_time":2.122137193},
{"learn":[47.93559374],"iteration":780,"passed_time":7.532555569,"remaining_time":2.112201882},
{"learn":[47.90854009],"iteration":781,"passed_time":7.542199294,"remaining_time":2.102556836},
{"learn":[47.88633775],"iteration":782,"passed_time":7.552327985,"remaining_time":2.093046198},
{"learn":[47.86700957],"iteration":783,"passed_time":7.562042233,"remaining_time":2.083419799},
{"learn":[47.85458208],"iteration":784,"passed_time":7.570305441,"remaining_time":2.073395758},
{"learn":[47.84370485],"iteration":785,"passed_time":7.579130507,"remaining_time":2.063529171},
{"learn":[47.8202404],"iteration":786,"passed_time":7.587984971,"remaining_time":2.053673188},
{"learn":[47.79739126],"iteration":787,"passed_time":7.597053672,"remaining_time":2.043877384},
{"learn":[47.77353548],"iteration":788,"passed_time":7.606368032,"remaining_time":2.034149119},
{"learn":[47.74894891],"iteration":789,"passed_time":7.616113301,"remaining_time":2.024536447},
{"learn":[47.73144377],"iteration":790,"passed_time":7.62520691,"remaining_time":2.014751257},
{"learn":[47.71077444],"iteration":791,"passed_time":7.634554275,"remaining_time":2.005034456},
{"learn":[47.68235871],"iteration":792,"passed_time":7.643587538,"remaining_time":1.995236596},
{"learn":[47.65682569],"iteration":793,"passed_time":7.652219333,"remaining_time":1.985336502},
{"learn":[47.63394288],"iteration":794,"passed_time":7.66096606,"remaining_time":1.975469236},
{"learn":[47.61526588],"iteration":795,"passed_time":7.669815699,"remaining_time":1.965631159},
{"learn":[47.59467567],"iteration":796,"passed_time":7.679219223,"remaining_time":1.95593664},
{"learn":[47.57257619],"iteration":797,"passed_time":7.68852814,"remaining_time":1.946218903},
{"learn":[47.55155611],"iteration":798,"passed_time":7.698502621,"remaining_time":1.936669621},
{"learn":[47.53887245],"iteration":799,"passed_time":7.706942219,"remaining_time":1.926735555},
{"learn":[47.51954912],"iteration":800,"passed_time":7.716230758,"remaining_time":1.917016131},
{"learn":[47.49091821],"iteration":801,"passed_time":7.725143456,"remaining_time":1.907204993},
{"learn":[47.4632233],"iteration":802,"passed_time":7.735454226,"remaining_time":1.897739082},
{"learn":[47.44710259],"iteration":803,"passed_time":7.744347178,"remaining_time":1.887925431},
{"learn":[47.42598543],"iteration":804,"passed_time":7.754079527,"remaining_time":1.878317401},
{"learn":[47.40590004],"iteration":805,"passed_time":7.7626347,"remaining_time":1.868425722},
{"learn":[47.38554462],"iteration":806,"passed_time":7.772115568,"remaining_time":1.858758742},
{"learn":[47.35677532],"iteration":807,"passed_time":7.781355787,"remaining_time":1.849035039},
{"learn":[47.32255024],"iteration":808,"passed_time":7.791700672,"remaining_time":1.839573335},
{"learn":[47.28690449],"iteration":809,"passed_time":7.800004168,"remaining_time":1.829630607},
{"learn":[47.26619119],"iteration":810,"passed_time":7.808978737,"remaining_time":1.819848312},
{"learn":[47.23551444],"iteration":811,"passed_time":7.817825869,"remaining_time":1.810038502},
{"learn":[47.20953863],"iteration":812,"passed_time":7.826425812,"remaining_time":1.800174203},
{"learn":[47.18591486],"iteration":813,"passed_time":7.836204534,"remaining_time":1.790582363},
{"learn":[47.16756594],"iteration":814,"passed_time":7.845127425,"remaining_time":1.780795796},
{"learn":[47.14894803],"iteration":815,"passed_time":7.855913161,"remaining_time":1.771431399},
{"learn":[47.13004616],"iteration":816,"passed_time":7.865812709,"remaining_time":1.761865025},
{"learn":[47.11970818],"iteration":817,"passed_time":7.875201707,"remaining_time":1.752184243},
{"learn":[47.10017161],"iteration":818,"passed_time":7.886688937,"remaining_time":1.742967885},
{"learn":[47.0790824],"iteration":819,"passed_time":7.895595538,"remaining_time":1.733179508},
{"learn":[47.05598415],"iteration":820,"passed_time":7.905768258,"remaining_time":1.723669328},
{"learn":[47.03942916],"iteration":821,"passed_time":7.914963636,"remaining_time":1.713945897},
{"learn":[47.01919614],"iteration":822,"passed_time":7.924161079,"remaining_time":1.704224193},
{"learn":[47.0049238],"iteration":823,"passed_time":7.934159981,"remaining_time":1.694674947},
{"learn":[46.989752],"iteration":824,"passed_time":7.944181168,"remaining_time":1.685129339},
{"learn":[46.97073095],"iteration":825,"passed_time":7.962906127,"remaining_time":1.677416061},
{"learn":[46.95096685],"iteration":826,"passed_time":7.973833907,"remaining_time":1.668045061},
{"learn":[46.91564983],"iteration":827,"passed_time":7.984757532,"remaining_time":1.658669439},
{"learn":[46.90127061],"iteration":828,"passed_time":7.993925772,"remaining_time":1.648927994},
{"learn":[46.88044735],"iteration":829,"passed_time":8.005920573,"remaining_time":1.639766864},
{"learn":[46.86834612],"iteration":830,"passed_time":8.015377959,"remaining_time":1.630082882},
{"learn":[46.8578624],"iteration":831,"passed_time":8.02547079,"remaining_time":1.620527756},
{"learn":[46.85189006],"iteration":832,"passed_time":8.034522925,"remaining_time":1.610762699},
{"learn":[46.83610755],"iteration":833,"passed_time":8.043935165,"remaining_time":1.601071028},
{"learn":[46.81795301],"iteration":834,"passed_time":8.053574682,"remaining_time":1.591424937},
{"learn":[46.79597446],"iteration":835,"passed_time":8.062817562,"remaining_time":1.581701053},
{"learn":[46.78184469],"iteration":836,"passed_time":8.072985738,"remaining_time":1.572158513},
{"learn":[46.77123009],"iteration":837,"passed_time":8.082049424,"remaining_time":1.562400963},
{"learn":[46.76338374],"iteration":838,"passed_time":8.092424404,"remaining_time":1.552896697},
{"learn":[46.74875241],"iteration":839,"passed_time":8.101405059,"remaining_time":1.543124773},
{"learn":[46.72592603],"iteration":840,"passed_time":8.111437618,"remaining_time":1.533553604},
{"learn":[46.72028198],"iteration":841,"passed_time":8.119931299,"remaining_time":1.523692572},
{"learn":[46.7024743],"iteration":842,"passed_time":8.130358013,"remaining_time":1.51419479},
{"learn":[46.68579105],"iteration":843,"passed_time":8.139508491,"remaining_time":1.504458915},
{"learn":[46.66734106],"iteration":844,"passed_time":8.149562427,"remaining_time":1.494890149},
{"learn":[46.63846314],"iteration":845,"passed_time":8.158684367,"remaining_time":1.485150582},
{"learn":[46.61833389],"iteration":846,"passed_time":8.169547955,"remaining_time":1.47572708},
{"learn":[46.60161237],"iteration":847,"passed_time":8.178767947,"remaining_time":1.466005575},
{"learn":[46.57607041],"iteration":848,"passed_time":8.190273065,"remaining_time":1.456691676},
{"learn":[46.54944306],"iteration":849,"passed_time":8.200121136,"remaining_time":1.4470802},
{"learn":[46.53434952],"iteration":850,"passed_time":8.210532521,"remaining_time":1.437566799},
{"learn":[46.50741524],"iteration":851,"passed_time":8.221139541,"remaining_time":1.428085272},
{"learn":[46.46877508],"iteration":852,"passed_time":8.231394051,"remaining_time":1.418540358},
{"learn":[46.45917244],"iteration":853,"passed_time":8.240719412,"remaining_time":1.408834935},
{"learn":[46.45065219],"iteration":854,"passed_time":8.250481098,"remaining_time":1.399204397},
{"learn":[46.43057679],"iteration":855,"passed_time":8.259864043,"remaining_time":1.389509839},
{"learn":[46.41616473],"iteration":856,"passed_time":8.269657167,"remaining_time":1.379884451},
{"learn":[46.39557215],"iteration":857,"passed_time":8.278762589,"remaining_time":1.370144857},
{"learn":[46.37017191],"iteration":858,"passed_time":8.288134851,"remaining_time":1.36045054},
{"learn":[46.3441358],"iteration":859,"passed_time":8.299152782,"remaining_time":1.351024872},
{"learn":[46.32079946],"iteration":860,"passed_time":8.308898533,"remaining_time":1.341390123},
{"learn":[46.30649559],"iteration":861,"passed_time":8.318295173,"remaining_time":1.331699227},
{"learn":[46.28112665],"iteration":862,"passed_time":8.327140495,"remaining_time":1.321921492},
{"learn":[46.25902743],"iteration":863,"passed_time":8.335557022,"remaining_time":1.31207842},
{"learn":[46.24388953],"iteration":864,"passed_time":8.345765622,"remaining_time":1.302518334},
{"learn":[46.22931642],"iteration":865,"passed_time":8.355924099,"remaining_time":1.292948995},
{"learn":[46.22444891],"iteration":866,"passed_time":8.365662546,"remaining_time":1.283313862},
{"learn":[46.19968208],"iteration":867,"passed_time":8.375748242,"remaining_time":1.2737313},
{"learn":[46.18304342],"iteration":868,"passed_time":8.384881187,"remaining_time":1.264003953},
{"learn":[46.16823571],"iteration":869,"passed_time":8.393084149,"remaining_time":1.254139011},
{"learn":[46.15049867],"iteration":870,"passed_time":8.402198258,"remaining_time":1.24441283},
{"learn":[46.13524701],"iteration":871,"passed_time":8.410124508,"remaining_time":1.234513689},
{"learn":[46.11313287],"iteration":872,"passed_time":8.421018506,"remaining_time":1.225050802},
{"learn":[46.09861162],"iteration":873,"passed_time":8.429346206,"remaining_time":1.21521467},
{"learn":[46.08649661],"iteration":874,"passed_time":8.437804701,"remaining_time":1.205400672},
{"learn":[46.07217802],"iteration":875,"passed_time":8.44713661,"remaining_time":1.195713401},
{"learn":[46.06158722],"iteration":876,"passed_time":8.455318785,"remaining_time":1.18586569},
{"learn":[46.04990757],"iteration":877,"passed_time":8.464706541,"remaining_time":1.176189292},
{"learn":[46.03931492],"iteration":878,"passed_time":8.473660344,"remaining_time":1.166453813},
{"learn":[46.03358369],"iteration":879,"passed_time":8.481840436,"remaining_time":1.156614605},
{"learn":[46.02284026],"iteration":880,"passed_time":8.490368277,"remaining_time":1.146826135},
{"learn":[46.00251294],"iteration":881,"passed_time":8.49977235,"remaining_time":1.137157752},
{"learn":[45.98751297],"iteration":882,"passed_time":8.508481864,"remaining_time":1.127397937},
{"learn":[45.98124306],"iteration":883,"passed_time":8.517701149,"remaining_time":1.117707391},
{"learn":[45.96745615],"iteration":884,"passed_time":8.526127288,"remaining_time":1.107914845},
{"learn":[45.94627442],"iteration":885,"passed_time":8.535990165,"remaining_time":1.098310247},
{"learn":[45.91253911],"iteration":886,"passed_time":8.544455838,"remaining_time":1.088527068},
{"learn":[45.8982196],"iteration":887,"passed_time":8.552872412,"remaining_time":1.078740665},
{"learn":[45.87211406],"iteration":888,"passed_time":8.562407483,"remaining_time":1.069096997},
{"learn":[45.85849656],"iteration":889,"passed_time":8.570933686,"remaining_time":1.059328883},
{"learn":[45.84113235],"iteration":890,"passed_time":8.580476565,"remaining_time":1.04968793},
{"learn":[45.82800652],"iteration":891,"passed_time":8.589098132,"remaining_time":1.039935648},
{"learn":[45.80172748],"iteration":892,"passed_time":8.598735775,"remaining_time":1.030307646},
{"learn":[45.79067809],"iteration":893,"passed_time":8.608220298,"remaining_time":1.020661467},
{"learn":[45.77861074],"iteration":894,"passed_time":8.618965745,"remaining_time":1.011163579},
{"learn":[45.75059265],"iteration":895,"passed_time":8.628530934,"remaining_time":1.001525912},
{"learn":[45.72001924],"iteration":896,"passed_time":8.63786651,"remaining_time":0.9918620408},
{"learn":[45.6948307],"iteration":897,"passed_time":8.646643998,"remaining_time":0.9821355098},
{"learn":[45.67899144],"iteration":898,"passed_time":8.656165702,"remaining_time":0.9724947006},
{"learn":[45.67044152],"iteration":899,"passed_time":8.664669359,"remaining_time":0.9627410399},
{"learn":[45.63775149],"iteration":900,"passed_time":8.674543791,"remaining_time":0.9531407717},
{"learn":[45.62202695],"iteration":901,"passed_time":8.68306473,"remaining_time":0.9433928421},
{"learn":[45.5970247],"iteration":902,"passed_time":8.692822185,"remaining_time":0.9337804562},
{"learn":[45.58151002],"iteration":903,"passed_time":8.701336677,"remaining_time":0.9240357533},
{"learn":[45.57293207],"iteration":904,"passed_time":8.711578852,"remaining_time":0.9144751281},
{"learn":[45.56405085],"iteration":905,"passed_time":8.719831839,"remaining_time":0.9047066146},
{"learn":[45.54260683],"iteration":906,"passed_time":8.727855265,"remaining_time":0.8949179048},
{"learn":[45.52985722],"iteration":907,"passed_time":8.737201791,"remaining_time":0.8852671418},
{"learn":[45.52134227],"iteration":908,"passed_time":8.746398683,"remaining_time":0.8756020684},
{"learn":[45.49180024],"iteration":909,"passed_time":8.756572661,"remaining_time":0.8660346587},
{"learn":[45.47222155],"iteration":910,"passed_time":8.76553234,"remaining_time":0.8563472867},
{"learn":[45.44847492],"iteration":911,"passed_time":8.774857185,"remaining_time":0.8466967459},
{"learn":[45.42382937],"iteration":912,"passed_time":8.785353943,"remaining_time":0.8371585904},
{"learn":[45.41187044],"iteration":913,"passed_time":8.79483617,"remaining_time":0.8275228782},
{"learn":[45.39122328],"iteration":914,"passed_time":8.804831545,"remaining_time":0.8179351708},
{"learn":[45.37130931],"iteration":915,"passed_time":8.814000483,"remaining_time":0.8082707866},
{"learn":[45.35066208],"iteration":916,"passed_time":8.822537996,"remaining_time":0.7985503312},
{"learn":[45.33222435],"iteration":917,"passed_time":8.832120097,"remaining_time":0.7889257603},
{"learn":[45.31170324],"iteration":918,"passed_time":8.840049873,"remaining_time":0.7791556472},
{"learn":[45.30805343],"iteration":919,"passed_time":8.849539423,"remaining_time":0.7695251673},
{"learn":[45.28841246],"iteration":920,"passed_time":8.859004887,"remaining_time":0.7598929273},
{"learn":[45.26009239],"iteration":921,"passed_time":8.868806948,"remaining_time":0.7502895249},
{"learn":[45.24803093],"iteration":922,"passed_time":8.877383524,"remaining_time":0.7405834576},
{"learn":[45.23607347],"iteration":923,"passed_time":8.886408148,"remaining_time":0.7309166875},
{"learn":[45.21610769],"iteration":924,"passed_time":8.894730612,"remaining_time":0.7211943739},
{"learn":[45.2030921],"iteration":925,"passed_time":8.90528433,"remaining_time":0.7116533914},
{"learn":[45.18363239],"iteration":926,"passed_time":8.914415181,"remaining_time":0.701998175},
{"learn":[45.17389865],"iteration":927,"passed_time":8.922754206,"remaining_time":0.6922826539},
{"learn":[45.15469398],"iteration":928,"passed_time":8.932344283,"remaining_time":0.6826657094},
{"learn":[45.13869333],"iteration":929,"passed_time":8.941217289,"remaining_time":0.6729948497},
{"learn":[45.12255378],"iteration":930,"passed_time":8.950497938,"remaining_time":0.6633559159},
{"learn":[45.10567199],"iteration":931,"passed_time":8.959459136,"remaining_time":0.6536944434},
{"learn":[45.09392492],"iteration":932,"passed_time":8.968444659,"remaining_time":0.6440362188},
{"learn":[45.07977207],"iteration":933,"passed_time":8.977213953,"remaining_time":0.6343641552},
{"learn":[45.06292982],"iteration":934,"passed_time":8.986468145,"remaining_time":0.624727732},
{"learn":[45.04559147],"iteration":935,"passed_time":8.995384512,"remaining_time":0.6150690264},
{"learn":[45.03485042],"iteration":936,"passed_time":9.003924355,"remaining_time":0.6053865895},
{"learn":[45.01603736],"iteration":937,"passed_time":9.012679823,"remaining_time":0.5957208412},
{"learn":[44.99571947],"iteration":938,"passed_time":9.022363667,"remaining_time":0.5861173415},
{"learn":[44.98776881],"iteration":939,"passed_time":9.030999243,"remaining_time":0.5764467602},
{"learn":[44.97504275],"iteration":940,"passed_time":9.04027083,"remaining_time":0.5668182561},
{"learn":[44.96014329],"iteration":941,"passed_time":9.050247769,"remaining_time":0.5572339391},
{"learn":[44.94758385],"iteration":942,"passed_time":9.058863356,"remaining_time":0.5475665019},
{"learn":[44.92517725],"iteration":943,"passed_time":9.06793302,"remaining_time":0.53792823},
{"learn":[44.91098495],"iteration":944,"passed_time":9.076355562,"remaining_time":0.5282534983},
{"learn":[44.89696117],"iteration":945,"passed_time":9.085879004,"remaining_time":0.518644256},
{"learn":[44.88240044],"iteration":946,"passed_time":9.095045803,"remaining_time":0.509015235},
{"learn":[44.8563086],"iteration":947,"passed_time":9.105147711,"remaining_time":0.4994384821},
{"learn":[44.83851094],"iteration":948,"passed_time":9.114299981,"remaining_time":0.489809588},
{"learn":[44.82508794],"iteration":949,"passed_time":9.123297813,"remaining_time":0.4801735691},
{"learn":[44.81029536],"iteration":950,"passed_time":9.132085479,"remaining_time":0.4705280636},
{"learn":[44.78652031],"iteration":951,"passed_time":9.142831262,"remaining_time":0.4609830888},
{"learn":[44.77353574],"iteration":952,"passed_time":9.151214845,"remaining_time":0.4513190952},
{"learn":[44.75678636],"iteration":953,"passed_time":9.16085607,"remaining_time":0.4417184269},
{"learn":[44.74421456],"iteration":954,"passed_time":9.16881636,"remaining_time":0.4320384672},
{"learn":[44.73249518],"iteration":955,"passed_time":9.177982851,"remaining_time":0.4224176208},
{"learn":[44.70588533],"iteration":956,"passed_time":9.185966038,"remaining_time":0.4127445555},
{"learn":[44.68914244],"iteration":957,"passed_time":9.196415087,"remaining_time":0.4031831249},
{"learn":[44.6809249],"iteration":958,"passed_time":9.204792918,"remaining_time":0.3935312926},
{"learn":[44.66996882],"iteration":959,"passed_time":9.213029922,"remaining_time":0.3838762467},
{"learn":[44.64138556],"iteration":960,"passed_time":9.22284646,"remaining_time":0.3742882539},
{"learn":[44.62359539],"iteration":961,"passed_time":9.235358633,"remaining_time":0.3648062662},
{"learn":[44.61843275],"iteration":962,"passed_time":9.246410221,"remaining_time":0.3552618673},
{"learn":[44.58901424],"iteration":963,"passed_time":9.256697228,"remaining_time":0.3456857886},
{"learn":[44.57222583],"iteration":964,"passed_time":9.266887849,"remaining_time":0.3361047407},
{"learn":[44.55693253],"iteration":965,"passed_time":9.275125044,"remaining_time":0.3264536765},
{"learn":[44.54844614],"iteration":966,"passed_time":9.284078123,"remaining_time":0.316829967},
{"learn":[44.52709272],"iteration":967,"passed_time":9.293884211,"remaining_time":0.3072358417},
{"learn":[44.52123064],"iteration":968,"passed_time":9.301997029,"remaining_time":0.2975871083},
{"learn":[44.49827915],"iteration":969,"passed_time":9.312297239,"remaining_time":0.288009193},
{"learn":[44.48163198],"iteration":970,"passed_time":9.320866274,"remaining_time":0.2783780865},
{"learn":[44.46384436],"iteration":971,"passed_time":9.330444177,"remaining_time":0.2687782273},
{"learn":[44.43879461],"iteration":972,"passed_time":9.339678023,"remaining_time":0.259168866},
{"learn":[44.4210909],"iteration":973,"passed_time":9.348818993,"remaining_time":0.2495577965},
{"learn":[44.41023117],"iteration":974,"passed_time":9.357486584,"remaining_time":0.2399355534},
{"learn":[44.39166966],"iteration":975,"passed_time":9.367247218,"remaining_time":0.2303421447},
{"learn":[44.36432382],"iteration":976,"passed_time":9.375986348,"remaining_time":0.220724346},
{"learn":[44.34809091],"iteration":977,"passed_time":9.384952802,"remaining_time":0.2111134577},
{"learn":[44.33285723],"iteration":978,"passed_time":9.394003865,"remaining_time":0.2015057009},
{"learn":[44.31271178],"iteration":979,"passed_time":9.40366989,"remaining_time":0.1919116304},
{"learn":[44.29656305],"iteration":980,"passed_time":9.411611012,"remaining_time":0.1822840053},
{"learn":[44.2789501],"iteration":981,"passed_time":9.420740293,"remaining_time":0.172681594},
{"learn":[44.25923998],"iteration":982,"passed_time":9.42979197,"remaining_time":0.1630788031},
{"learn":[44.24720419],"iteration":983,"passed_time":9.440387475,"remaining_time":0.1535022354},
{"learn":[44.23277705],"iteration":984,"passed_time":9.449476194,"remaining_time":0.1439006527},
{"learn":[44.22081938],"iteration":985,"passed_time":9.459193634,"remaining_time":0.1343090374},
{"learn":[44.20248959],"iteration":986,"passed_time":9.468466189,"remaining_time":0.1247113075},
{"learn":[44.18899485],"iteration":987,"passed_time":9.477946653,"remaining_time":0.115116761},
{"learn":[44.17858656],"iteration":988,"passed_time":9.487013088,"remaining_time":0.1055178402},
{"learn":[44.15524095],"iteration":989,"passed_time":9.495556465,"remaining_time":0.09591471176},
{"learn":[44.14390162],"iteration":990,"passed_time":9.50435088,"remaining_time":0.08631600194},
{"learn":[44.13475413],"iteration":991,"passed_time":9.51243022,"remaining_time":0.07671314693},
{"learn":[44.11469533],"iteration":992,"passed_time":9.522109908,"remaining_time":0.06712464185},
{"learn":[44.10557398],"iteration":993,"passed_time":9.530673113,"remaining_time":0.05752921396},
{"learn":[44.08559653],"iteration":994,"passed_time":9.541245237,"remaining_time":0.04794595596},
{"learn":[44.06884382],"iteration":995,"passed_time":9.550900265,"remaining_time":0.03835702917},
{"learn":[44.06135571],"iteration":996,"passed_time":9.560283862,"remaining_time":0.02876715304},
{"learn":[44.05114232],"iteration":997,"passed_time":9.568467744,"remaining_time":0.01917528606},
{"learn":[44.03943804],"iteration":998,"passed_time":9.578098855,"remaining_time":0.009587686541},
{"learn":[44.01686678],"iteration":999,"passed_time":9.587585506,"remaining_time":0}
]}